Workbook

Sheet Saving monthly Oct-2022
A1: ក្រុម​សន្សំ​ប្រាក់ «សន្សំSANSAM»
A2: ការសន្សំ​ចាប់​ពី​៥ដុល្លារ​ឡើង​ទៅក្នុង​មួយខែ ដោយ​សមាជិក​នឹង​ទទួល​បានការប្រាក់ប្រចាំ​ខែ0.83%
A3: ចំពោះ​សមាជិក​ដែលដាក់ប្រាក់​កម្ចី​គឺក្នុងអត្រា​ការប្រាក់​១០%ក្នុង​មួយឆ្នាំ​សម្រាប់ក្រុម​ប្រឹក្សាភិបាល​ ១៤.៤%ក្នុង​មួយឆ្នាំសម្រាប់​សមាជិកស្នូល ១៨%ក្នុងមួយឆ្នាំ​សម្រាប់​សមាជិក​ធម្មតា ៣%​ក្នុងមួយឆ្នាំ​សម្រាប់​សមាជិក​បញ្ញើ
A4: ការ​ដាក់​ប្រាក់​សន្សំចាប់ពី​ថ្ងៃទី១ដល់ថ្ងៃទី១០រៀងរាល់ខែ
A5: ពេលវេលាទទួល​បាន​កម្ចី​ចន្លោះពីថ្ងៃទី១០ដល់ថ្ងៃទី១៥​រៀងរាល់ខែ
A6: តារាងសន្សំ​ខែ តុលា ឆ្នាំ២០២២
A7: ល.រ | B7: ឈ្មោះ​សមាជិកដាក់សន្សំ​ | C7: ភេទ | D7: តួនាទី​ក្នុង​សន្សំ | E7: ថ្ងៃខែដាក់សន្សំ | F7: ប្រាក់ដាក់សន្សំ | G7: ការប្រាក់ទទួលបាន | H7: សមតុល្យ​សាច់ប្រាក់ | I7: ប្រាក់បានដក | J7: សមតុល្យ​សាច់ប្រាក់ក្រោយដក
A8: 1 | B8: អាត់ ធន់ | C8: ប្រុស | D8: ស្ថាបនិក | E8: 44844 | F8: 3500 | H8: =F8+G8 -> 3500 | J8: =G8+H8-I8 -> 3500
A9: 2 | B9: ប៉ិច ពិសី | C9: ប្រុស | D9: ស្ថាបនិក | E9: 44844 | F9: 5000 | H9: =F9+G9 -> 5000 | J9: =G9+H9-I9 -> 5000
A10: 3 | B10: ហុង រស្មី | C10: ប្រុស | D10: ស្ថាបនិក | E10: 44844 | F10: 5000 | H10: =F10+G10 -> 5000 | J10: =G10+H10-I10 -> 5000
A11: 4 | B11: ស៊ិន ពុទ្ធារី | C11: ស្រី | D11: ស្ថាបនិក | E11: 44844 | F11: 5000 | H11: =F11+G11 -> 5000 | J11: =G11+H11-I11 -> 5000
A12: 5 | B12: វន់ ពៅ | C12: ប្រុស | D12: ស្ថាបនិក | E12: 44844 | F12: 100 | H12: =F12+G12 -> 100 | J12: =G12+H12-I12 -> 100
A13: 6 | B13: ស ម៉ូរ៉ា | C13: ប្រុស | D13: ស្ថាបនិក | E13: 44844 | F13: 2000 | H13: =F13+G13 -> 2000 | J13: =G13+H13-I13 -> 2000
A14: 7 | B14: ណុប វី | C14: ប្រុស | D14: ស្ថាបនិក | E14: 44844 | F14: 5000 | H14: =F14+G14 -> 5000 | J14: =G14+H14-I14 -> 5000
A15: 8 | B15: អ៊ូ រិទ្ធី | C15: ប្រុស | D15: ស្ថាបនិក | E15: 44844 | F15: 4000 | H15: =F15+G15 -> 4000 | J15: =G15+H15-I15 -> 4000
F16: =SUM(F8:F15) -> 29600 | G16: =SUM(G8:G15) -> 0 | H16: =SUM(H8:H15) -> 29600 | I16: 0 | J16: =SUM(J8:J15) -> 29600

Sheet Saving monthly November-22
A1: ក្រុម​សន្សំ​ប្រាក់ «សន្សំSANSAM»
A2: ការសន្សំ​ចាប់​ពី​៥ដុល្លារ​ឡើង​ទៅក្នុង​មួយខែ ដោយ​សមាជិក​នឹង​ទទួល​បានការប្រាក់ប្រចាំ​ខែ0.83%
A3: ចំពោះ​សមាជិក​ដែលដាក់ប្រាក់​កម្ចី​គឺក្នុងអត្រា​ការប្រាក់​១០%ក្នុង​មួយឆ្នាំ​សម្រាប់ក្រុម​ប្រឹក្សាភិបាល​ ១៤.៤%ក្នុង​មួយឆ្នាំសម្រាប់​សមាជិកស្នូល ១៨%ក្នុងមួយឆ្នាំ​សម្រាប់​សមាជិក​ធម្មតា ៣%​ក្នុងមួយឆ្នាំ​សម្រាប់​សមាជិក​បញ្ញើ
A4: ការ​ដាក់​ប្រាក់​សន្សំចាប់ពី​ថ្ងៃទី១ដល់ថ្ងៃទី១០រៀងរាល់ខែ
A5: ពេលវេលាទទួល​បាន​កម្ចី​ចន្លោះពីថ្ងៃទី១០ដល់ថ្ងៃទី១៥​រៀងរាល់ខែ
A6: តារាងសន្សំ​ខែ វិច្ឆិកា ឆ្នាំ២០២២
A7: ល.រ | B7: ឈ្មោះ​សមាជិកដាក់សន្សំ​ | C7: ភេទ | D7: តួនាទី​ក្នុង​សន្សំ | E7: ថ្ងៃខែដាក់សន្សំ | F7: ប្រាក់ដើម | G7: ប្រាក់ដាក់សន្សំ | H7: ការប្រាក់ទទួលបាន | I7: សមតុល្យ​សាច់ប្រាក់ | J7: ប្រាក់បានដក | K7: សមតុល្យ​សាច់ប្រាក់ក្រោយដក
A8: 1 | B8: អាត់ ធន់ | C8: ប្រុស | D8: ស្ថាបនិក | E8: 44844 | F8: 3500 | H8: =F8*0.83% -> 29.05 | I8: =F8+G8+H8 -> 3529.05 | K8: =I8-J8 -> 3529.05
A9: 2 | B9: ប៉ិច ពិសី | C9: ប្រុស | D9: ស្ថាបនិក | E9: 44844 | F9: 5000 | G9: 500 | H9: =F9*0.83% -> 41.5 | I9: =F9+G9+H9 -> 5541.5 | K9: =I9-J9 -> 5541.5
A10: 3 | B10: ហុង រស្មី | C10: ប្រុស | D10: ស្ថាបនិក | E10: 44844 | F10: 5000 | G10: 100 | H10: =F10*0.83% -> 41.5 | I10: =F10+G10+H10 -> 5141.5 | K10: =I10-J10 -> 5141.5
A11: 4 | B11: ស៊ិន ពុទ្ធារី | C11: ស្រី | D11: ស្ថាបនិក | E11: 44844 | F11: 5000 | G11: 100 | H11: =F11*0.83% -> 41.5 | I11: =F11+G11+H11 -> 5141.5 | K11: =I11-J11 -> 5141.5
A12: 5 | B12: វន់ ពៅ | C12: ប្រុស | D12: ស្ថាបនិក | E12: 44844 | F12: 100 | H12: =F12*0.83% -> 0.83 | I12: =F12+G12+H12 -> 100.83 | K12: =I12-J12 -> 100.83
A13: 6 | B13: ស ម៉ូរ៉ា | C13: ប្រុស | D13: ស្ថាបនិក | E13: 44844 | F13: 2000 | G13: 50.17 | H13: =F13*0.83% -> 16.6 | I13: =F13+G13+H13 -> 2066.77 | K13: =I13-J13 -> 2066.77
A14: 7 | B14: ណុប វី | C14: ប្រុស | D14: ស្ថាបនិក | E14: 44844 | F14: 5000 | G14: 50.8 | H14: =F14*0.83% -> 41.5 | I14: =F14+G14+H14 -> 5092.3 | K14: =I14-J14 -> 5092.3
A15: 8 | B15: អ៊ូ រិទ្ធី | C15: ប្រុស | D15: ស្ថាបនិក | E15: 44844 | F15: 4000 | G15: 100 | H15: =F15*0.83% -> 33.2 | I15: =F15+G15+H15 -> 4133.2 | K15: =I15-J15 -> 4133.2
A16: 9 | B16: សំ​ សុម៉ុនី | C16: ប្រុស | D16: សមាជិក | E16: 44874 | F16: 50 | I16: =F16+G16+H16 -> 50 | K16: =I16-J16 -> 50
F17: =SUM(F8:F16) -> 29650 | G17: =SUM(G8:G16) -> 900.97 | H17: =SUM(H8:H16) -> 245.68 | I17: =SUM(I8:I16) -> 30796.65 | J17: 0 | K17: =SUM(K8:K16) -> 30796.65

Sheet Saving monthly December-22
A1: ក្រុម​សន្សំ​ប្រាក់ «សន្សំSANSAM»
A2: ការសន្សំ​ចាប់​ពី​៥ដុល្លារ​ឡើង​ទៅក្នុង​មួយខែ ដោយ​សមាជិក​នឹង​ទទួល​បានការប្រាក់ប្រចាំ​ខែ0.83%
A3: ចំពោះ​សមាជិក​ដែលដាក់ប្រាក់​កម្ចី​គឺក្នុងអត្រា​ការប្រាក់​១០%ក្នុង​មួយឆ្នាំ​សម្រាប់ក្រុម​ប្រឹក្សាភិបាល​ ១៤.៤%ក្នុង​មួយឆ្នាំសម្រាប់​សមាជិកស្នូល ១៨%ក្នុងមួយឆ្នាំ​សម្រាប់​សមាជិក​ធម្មតា ៣%​ក្នុងមួយឆ្នាំ​សម្រាប់​សមាជិក​បញ្ញើ
A4: ការ​ដាក់​ប្រាក់​សន្សំចាប់ពី​ថ្ងៃទី១ដល់ថ្ងៃទី១០រៀងរាល់ខែ
A5: ពេលវេលាទទួល​បាន​កម្ចី​ចន្លោះពីថ្ងៃទី១០ដល់ថ្ងៃទី១៥​រៀងរាល់ខែ
A6: តារាងសន្សំ​ខែ ធ្នូ ឆ្នាំ២០២២
A7: ល.រ | B7: ឈ្មោះ​សមាជិកដាក់សន្សំ​ | C7: ភេទ | D7: តួនាទី​ក្នុង​សន្សំ | E7: ថ្ងៃខែដាក់សន្សំ | F7: ប្រាក់ដើម | G7: ប្រាក់ដាក់សន្សំ | H7: ការប្រាក់ទទួលបាន | I7: សមតុល្យ​សាច់ប្រាក់ | J7: ប្រាក់បានដក | K7: សមតុល្យ​សាច់ប្រាក់ក្រោយដក
A8: 1 | B8: អាត់ ធន់ | C8: ប្រុស | D8: ស្ថាបនិក | E8: 44844 | F8: ='Saving monthly November-22'!K8 -> 3529.05 | G8: 0.07 | H8: =F8*0.83% -> 29.291115 | I8: =F8+G8+H8 -> 3558.4111 | K8: =I8-J8 -> 3558.4111
A9: 2 | B9: ប៉ិច ពិសី | C9: ប្រុស | D9: ស្ថាបនិក | E9: 44844 | F9: ='Saving monthly November-22'!K9 -> 5541.5 | H9: =F9*0.83% -> 45.99445 | I9: =F9+G9+H9 -> 5587.4945 | K9: =I9-J9 -> 5587.4945
A10: 3 | B10: ហុង រស្មី | C10: ប្រុស | D10: ស្ថាបនិក | E10: 44905 | F10: ='Saving monthly November-22'!K10 -> 5141.5 | G10: 100 | H10: =F10*0.83% -> 42.67445 | I10: =F10+G10+H10 -> 5284.1745 | K10: =I10-J10 -> 5284.1745
A11: 4 | B11: ស៊ិន ពុទ្ធារី | C11: ស្រី | D11: ស្ថាបនិក | E11: 44844 | F11: ='Saving monthly November-22'!K11 -> 5141.5 | H11: =F11*0.83% -> 42.67445 | I11: =F11+G11+H11 -> 5184.1745 | K11: =I11-J11 -> 5184.1745
A12: 5 | B12: វន់ ពៅ | C12: ប្រុស | D12: ស្ថាបនិក | E12: 44844 | F12: ='Saving monthly November-22'!K12 -> 100.83 | G12: 100 | H12: =F12*0.83% -> 0.836889 | I12: =F12+G12+H12 -> 201.66689 | K12: =I12-J12 -> 201.66689
A13: 6 | B13: ស ម៉ូរ៉ា | C13: ប្រុស | D13: ស្ថាបនិក | E13: 44844 | F13: ='Saving monthly November-22'!K13 -> 2066.77 | G13: 31.9 | H13: =F13*0.83% -> 17.154191 | I13: =F13+G13+H13 -> 2115.8242 | K13: =I13-J13 -> 2115.8242
A14: 7 | B14: ណុប វី | C14: ប្រុស | D14: ស្ថាបនិក | E14: 44844 | F14: 5092.3 | G14: 54.12 | H14: =F14*0.83% -> 42.26609 | I14: =F14+G14+H14 -> 5188.6861 | K14: =I14-J14 -> 5188.6861
A15: 8 | B15: អ៊ូ រិទ្ធី | C15: ប្រុស | D15: ស្ថាបនិក | E15: 44844 | F15: ='Saving monthly November-22'!K15 -> 4133.2 | G15: 200 | H15: =F15*0.83% -> 34.30556 | I15: =F15+G15+H15 -> 4367.5056 | K15: =I15-J15 -> 4367.5056
A16: 9 | B16: សំ​ សុម៉ុនី | C16: ប្រុស | D16: សមាជិក | E16: 44874 | F16: 50 | G16: 50 | H16: =F16*0.83% -> 0.415 | I16: =F16+G16+H16 -> 100.415 | K16: =I16-J16 -> 100.415
F17: =SUM(F8:F16) -> 30796.65 | G17: =SUM(G8:G16) -> 536.09 | H17: =SUM(H8:H16) -> 255.6122 | I17: =SUM(I8:I16) -> 31588.352 | J17: 0 | K17: =SUM(K8:K16) -> 31588.352

Sheet Saving monthly Jan-23
A1: ក្រុម​សន្សំ​ប្រាក់ «សន្សំSANSAM»
A2: ការសន្សំ​ចាប់​ពី​៥ដុល្លារ​ឡើង​ទៅក្នុង​មួយខែ ដោយ​សមាជិក​នឹង​ទទួល​បានការប្រាក់ប្រចាំ​ខែ0.83%
A3: ចំពោះ​សមាជិក​ដែលដាក់ប្រាក់​កម្ចី​គឺក្នុងអត្រា​ការប្រាក់​១០%ក្នុង​មួយឆ្នាំ​សម្រាប់ក្រុម​ប្រឹក្សាភិបាល​ ១៤.៤%ក្នុង​មួយឆ្នាំសម្រាប់​សមាជិកស្នូល ១៨%ក្នុងមួយឆ្នាំ​សម្រាប់​សមាជិក​ធម្មតា ៣%​ក្នុងមួយឆ្នាំ​សម្រាប់​សមាជិក​បញ្ញើ
A4: ការ​ដាក់​ប្រាក់​សន្សំចាប់ពី​ថ្ងៃទី១ដល់ថ្ងៃទី១០រៀងរាល់ខែ
A5: ពេលវេលាទទួល​បាន​កម្ចី​ចន្លោះពីថ្ងៃទី១០ដល់ថ្ងៃទី១៥​រៀងរាល់ខែ
A6: តារាងសន្សំ​ខែ មករា​ ឆ្នាំ២០២៣
A7: ល.រ | B7: ឈ្មោះ​សមាជិកដាក់សន្សំ​ | C7: ភេទ | D7: តួនាទី​ក្នុង​សន្សំ | E7: ថ្ងៃខែដាក់សន្សំ | F7: ប្រាក់ដើម | G7: ប្រាក់ដាក់សន្សំ | H7: ការប្រាក់ទទួលបាន | I7: សមតុល្យ​សាច់ប្រាក់ | J7: ប្រាក់បានដក | K7: សមតុល្យ​សាច់ប្រាក់ក្រោយដក
A8: 1 | B8: អាត់ ធន់ | C8: ប្រុស | D8: ស្ថាបនិក | E8: 44928 | F8: 3558.4111 | G8: 44.81 | H8: =F8*0.83% -> 29.534812 | I8: =F8+G8+H8 -> 3632.7559 | K8: =I8-J8 -> 3632.7559
A9: 2 | B9: PECH PISEY | C9: ប្រុស | D9: ស្ថាបនិក | E9: 44936 | F9: 5587.4945 | G9: 100 | H9: =F9*0.83% -> 46.376204 | I9: =F9+G9+H9 -> 5733.8707 | K9: =I9-J9 -> 5733.8707
A10: 3 | B10: HONG REAKSMEY | C10: ប្រុស | D10: ស្ថាបនិក | E10: 44937 | F10: 5284.1745 | G10: 100 | H10: =F10*0.83% -> 43.858648 | I10: =F10+G10+H10 -> 5428.0331 | K10: =I10-J10 -> 5428.0331
A11: 4 | B11: SIN PUTHEARY | C11: ស្រី | D11: ស្ថាបនិក | E11: 44844 | F11: 5184.1745 | H11: =F11*0.83% -> 43.028648 | I11: =F11+G11+H11 -> 5227.2031 | K11: =I11-J11 -> 5227.2031
A12: 5 | B12: PAO VORN | C12: ប្រុស | D12: ស្ថាបនិក | E12: 44844 | F12: 201.66689 | H12: =F12*0.83% -> 1.6738352 | I12: =F12+G12+H12 -> 203.34072 | K12: =I12-J12 -> 203.34072
A13: 6 | B13: SAR MORA | C13: ប្រុស | D13: ស្ថាបនិក | E13: 44936 | F13: 2115.8242 | G13: 33.63 | H13: =F13*0.83% -> 17.561341 | I13: =F13+G13+H13 -> 2167.0155 | K13: =I13-J13 -> 2167.0155
A14: 7 | B14: NOP VY | C14: ប្រុស | D14: ស្ថាបនិក | E14: 44936 | F14: 5188.6861 | G14: 57.44 | H14: =F14*0.83% -> 43.066095 | I14: =F14+G14+H14 -> 5289.1922 | K14: =I14-J14 -> 5289.1922
A15: 8 | B15: OU RITHY | C15: ប្រុស | D15: ស្ថាបនិក | E15: 44935 | F15: 4367.5056 | G15: 223 | H15: =F15*0.83% -> 36.250296 | I15: =F15+G15+H15 -> 4626.7559 | K15: =I15-J15 -> 4626.7559
A16: 9 | B16: SAM SOMONY | C16: ប្រុស | D16: សមាជិក | E16: 44936 | F16: 100.415 | G16: 50 | H16: =F16*0.83% -> 0.8334445 | I16: =F16+G16+H16 -> 151.24844 | K16: =I16-J16 -> 151.24844
A17: 10 | B17: KOY MAQUIS | C17: ប្រុស | D17: សមាជិក | E17: 44941 | F17: 5 | I17: =F17+G17+H17 -> 5 | K17: =I17-J17 -> 5
A18: 11 | B18: Ly Malin | C18: ស្រី | D18: សមាជិក | E18: 44950 | F18: 20 | I18: =F18+G18+H18 -> 20 | K18: =I18-J18 -> 20
A19: 12 | B19: Van Bunna | D19: សមាជិក | E19: 44951 | F19: 10 | I19: =F19+G19+H19 -> 10 | K19: =I19-J19 -> 10
A20: 13 | B20: Long Borin | C20: ស្រី | D20: សមាជិក | E20: 44957 | F20: 15 | I20: =F20+G20+H20 -> 15 | K20: =I20-J20 -> 15
F22: =SUM(F8:F20) -> 31638.352 | G22: =SUM(G8:G17) -> 608.88 | H22: =SUM(H8:H17) -> 262.18332 | I22: =SUM(I8:I20) -> 32509.416 | J22: =SUM(J8:J17) -> 0 | K22: =SUM(K8:K20) -> 32509.416

Sheet Saving monthly Feb-23
A1: ក្រុម​សន្សំ​ប្រាក់ «សន្សំSANSAM»
A2: ការសន្សំ​ចាប់​ពី​៥ដុល្លារ​ឡើង​ទៅក្នុង​មួយខែ ដោយ​សមាជិក​នឹង​ទទួល​បានការប្រាក់ប្រចាំ​ខែ0.83%
A3: ចំពោះ​សមាជិក​ដែលដាក់ប្រាក់​កម្ចី​គឺក្នុងអត្រា​ការប្រាក់​១០%ក្នុង​មួយឆ្នាំ​សម្រាប់ក្រុម​ប្រឹក្សាភិបាល​ ១៤.៤%ក្នុង​មួយឆ្នាំសម្រាប់​សមាជិកស្នូល ១៨%ក្នុងមួយឆ្នាំ​សម្រាប់​សមាជិក​ធម្មតា ៣%​ក្នុងមួយឆ្នាំ​សម្រាប់​សមាជិក​បញ្ញើ
A4: ការ​ដាក់​ប្រាក់​សន្សំចាប់ពី​ថ្ងៃទី១ដល់ថ្ងៃទី១០រៀងរាល់ខែ
A5: ពេលវេលាទទួល​បាន​កម្ចី​ចន្លោះពីថ្ងៃទី១០ដល់ថ្ងៃទី១៥​រៀងរាល់ខែ
A6: តារាងសន្សំ​ខែ កុម្ភះ​ ឆ្នាំ២០២៣
A7: ល.រ | B7: ឈ្មោះ​សមាជិកដាក់សន្សំ​ | C7: ភេទ | D7: តួនាទី​ក្នុង​សន្សំ | E7: ថ្ងៃខែដាក់សន្សំ | F7: ប្រាក់ដើម | G7: ប្រាក់ដាក់សន្សំ | H7: ការប្រាក់ទទួលបាន | I7: សមតុល្យ​សាច់ប្រាក់ | J7: ប្រាក់បានដក | K7: សមតុល្យ​សាច់ប្រាក់ក្រោយដក
A8: 1 | B8: ART THORN | C8: ប្រុស | D8: ស្ថាបនិក | E8: 44972 | F8: 3632.7559 | G8: 30.54 | H8: =F8*0.83% -> 30.151874 | I8: =F8+G8+H8 -> 3693.4478 | K8: =I8-J8 -> 3693.4478
A9: 2 | B9: ប៉ិច ពិសី | C9: ប្រុស | D9: ស្ថាបនិក | E9: 44844 | F9: 5733.8707 | H9: =F9*0.83% -> 47.591126 | I9: =F9+G9+H9 -> 5781.4618 | K9: =I9-J9 -> 5781.4618
A10: 3 | B10: HONG REAKSMEY | C10: ប្រុស | D10: ស្ថាបនិក | E10: 44971 | F10: 5428.0331 | G10: 50 | H10: =F10*0.83% -> 45.052675 | I10: =F10+G10+H10 -> 5523.0858 | K10: =I10-J10 -> 5523.0858
A11: 4 | B11: ស៊ិន ពុទ្ធារី | C11: ស្រី | D11: ស្ថាបនិក | E11: 44844 | F11: 5227.2031 | H11: =F11*0.83% -> 43.385786 | I11: =F11+G11+H11 -> 5270.5889 | K11: =I11-J11 -> 5270.5889
A12: 5 | B12: PAO VORN | C12: ប្រុស | D12: ស្ថាបនិក | E12: 44964 | F12: 203.34072 | G12: 50 | H12: =F12*0.83% -> 1.687728 | I12: =F12+G12+H12 -> 255.02845 | K12: =I12-J12 -> 255.02845
A13: 6 | B13: SOR MORA | C13: ប្រុស | D13: ស្ថាបនិក | E13: 44967 | F13: 2167.0155 | G13: 5.36 | H13: =F13*0.83% -> 17.986229 | I13: =F13+G13+H13 -> 2190.3618 | K13: =I13-J13 -> 2190.3618
A14: 7 | B14: ណុប វី | C14: ប្រុស | D14: ស្ថាបនិក | E14: 44968 | F14: 5289.1922 | G14: 60.76 | H14: =F14*0.83% -> 43.900295 | I14: =F14+G14+H14 -> 5393.8525 | K14: =I14-J14 -> 5393.8525
A15: 8 | B15: OU RITHTY | C15: ប្រុស | D15: ស្ថាបនិក | E15: 44967 | F15: 4626.7559 | G15: 100 | H15: =F15*0.83% -> 38.402074 | I15: =F15+G15+H15 -> 4765.1579 | K15: =I15-J15 -> 4765.1579
A16: 9 | B16: SENG RITHY | C16: ប្រុស | D16: សមាជិក | E16: 44958 | F16: 5 | I16: =F16+G16+H16 -> 5 | K16: =I16-J16 -> 5
A17: 10 | B17: OU TEPPHALIN | C17: ស្រី | D17: សមាជិក | E17: 44958 | F17: 20 | I17: =F17+G17+H17 -> 20 | K17: =I17-J17 -> 20
A18: 11 | B18: YIM BUNTHENG | D18: សមាជិក | E18: 44958 | F18: 10 | I18: =F18+G18+H18 -> 10 | K18: =I18-J18 -> 10
A19: 12 | B19: THENG SAVOEUN | D19: សមាជិក | E19: 44967 | F19: 50 | I19: =F19+G19+H19 -> 50 | K19: =I19-J19 -> 50
A20: 13 | B20: OU VANN | D20: សមាជិក | E20: 44967 | F20: 20 | I20: =F20+G20+H20 -> 20 | K20: =I20-J20 -> 20
A21: 14 | B21: SIYONN SOTHEARITH | C21: ប្រុស | D21: សមាជិក | E21: 44970 | F21: 100 | I21: =F21+G21+H21 -> 100 | K21: =I21-J21 -> 100
A22: 15 | B22: YEAN REAKSMEY | D22: សមាជិក | E22: 44975 | F22: 10 | I22: =F22+G22+H22 -> 10 | K22: =I22-J22 -> 10
A23: 16 | B23: SON PENH | D23: សមាជិក | E23: 44978 | F23: 20 | I23: =F23+G23+H23 -> 20 | K23: =I23-J23 -> 20
A24: 17 | B24: សំ​ សុម៉ុនី | C24: ប្រុស | D24: សមាជិក | E24: 44964 | F24: 151.24844 | G24: 50 | H24: =F24*0.83% -> 1.2553621 | I24: =F24+G24+H24 -> 202.50381 | K24: =I24-J24 -> 202.50381
A25: 18 | B25: KOY MAQUIS | C25: ប្រុស | D25: សមាជិក | E25: 44971 | F25: 5 | G25: 10 | H25: =F25*0.83% -> 0.0415 | I25: =F25+G25+H25 -> 15.0415 | K25: =I25-J25 -> 15.0415
A26: 19 | B26: Ly Malin | C26: ស្រី | D26: សមាជិក | E26: 44967 | F26: 20 | G26: 20 | H26: =F26*0.83% -> 0.166 | I26: =F26+G26+H26 -> 40.166 | K26: =I26-J26 -> 40.166
A27: 20 | B27: Van Bunna | D27: សមាជិក | E27: 44951 | F27: 10 | I27: =F27+G27+H27 -> 10 | K27: =I27-J27 -> 10
A28: 21 | B28: Long Borin | C28: ស្រី | D28: សមាជិក | E28: 44957 | F28: 15 | H28: =F28*0.83% -> 0.1245 | I28: =F28+G28+H28 -> 15.1245 | K28: =I28-J28 -> 15.1245
F30: =SUM(F8:F28) -> 32744.416 | G30: =SUM(G8:G28) -> 376.66 | H30: =SUM(H8:H28) -> 269.74515 | I30: =SUM(I8:I28) -> 33390.821 | J30: =SUM(J8:J28) -> 0 | K30: =SUM(K8:K28) -> 33390.821

Sheet Saving monthly Mar-23
A1: ក្រុម​សន្សំ​ប្រាក់ «សន្សំSANSAM»
A2: ការសន្សំ​ចាប់​ពី​៥ដុល្លារ​ឡើង​ទៅក្នុង​មួយខែ ដោយ​សមាជិក​នឹង​ទទួល​បានការប្រាក់ប្រចាំ​ខែ0.83%
A3: ចំពោះ​សមាជិក​ដែលដាក់ប្រាក់​កម្ចី​គឺក្នុងអត្រា​ការប្រាក់​១០%ក្នុង​មួយឆ្នាំ​សម្រាប់ក្រុម​ប្រឹក្សាភិបាល​ ១៤.៤%ក្នុង​មួយឆ្នាំសម្រាប់​សមាជិកស្នូល ១៨%ក្នុងមួយឆ្នាំ​សម្រាប់​សមាជិក​ធម្មតា ៣%​ក្នុងមួយឆ្នាំ​សម្រាប់​សមាជិក​បញ្ញើ
A4: ការ​ដាក់​ប្រាក់​សន្សំចាប់ពី​ថ្ងៃទី១ដល់ថ្ងៃទី១០រៀងរាល់ខែ
A5: ពេលវេលាទទួល​បាន​កម្ចី​ចន្លោះពីថ្ងៃទី១០ដល់ថ្ងៃទី១៥​រៀងរាល់ខែ
A6: តារាងសន្សំ​ខែ មីនា ឆ្នាំ២០២៣
A7: ល.រ | B7: ឈ្មោះ​សមាជិកដាក់សន្សំ​ | C7: ភេទ | D7: តួនាទី​ក្នុង​សន្សំ | E7: ថ្ងៃខែដាក់សន្សំ | F7: ប្រាក់ដើម | G7: ប្រាក់ដាក់សន្សំ | H7: ការប្រាក់ទទួលបាន | I7: សមតុល្យ​សាច់ប្រាក់ | J7: ប្រាក់បានដក | K7: សមតុល្យ​សាច់ប្រាក់ក្រោយដក
A8: 1 | B8: ART THORN | C8: ប្រុស | D8: ស្ថាបនិក | E8: 44995 | F8: 3693.4478 | G8: 46.27 | H8: =F8*0.83% -> 30.655617 | I8: =F8+G8+H8 -> 3770.3734 | K8: =I8-J8 -> 3770.3734
A9: 2 | B9: PECH PISEY | C9: ប្រុស | D9: ស្ថាបនិក | E9: 44995 | F9: 5781.4618 | G9: 50 | H9: =F9*0.83% -> 47.986133 | I9: =F9+G9+H9 -> 5879.4479 | K9: =I9-J9 -> 5879.4479
A10: 3 | B10: HONG REAKSMEY | C10: ប្រុស | D10: ស្ថាបនិក | E10: 44995 | F10: 5523.0858 | G10: 50 | H10: =F10*0.83% -> 45.841612 | I10: =F10+G10+H10 -> 5618.9274 | K10: =I10-J10 -> 5618.9274
A11: 4 | B11: SIN PUTHEARY | C11: ស្រី | D11: ស្ថាបនិក | E11: 44844 | F11: 5270.5889 | H11: =F11*0.83% -> 43.745888 | I11: =F11+G11+H11 -> 5314.3348 | K11: =I11-J11 -> 5314.3348
A12: 5 | B12: PAO VORN | C12: ប្រុស | D12: ស្ថាបនិក | E12: 44964 | F12: 255.02845 | H12: =F12*0.83% -> 2.1167362 | I12: =F12+G12+H12 -> 257.14519 | K12: =I12-J12 -> 257.14519
A13: 6 | B13: SOR MORA | C13: ប្រុស | D13: ស្ថាបនិក | E13: 44967 | F13: 2190.3618 | G13: 7.09 | H13: =F13*0.83% -> 18.180003 | I13: =F13+G13+H13 -> 2215.6318 | K13: =I13-J13 -> 2215.6318
A14: 7 | B14: NOP VY | C14: ប្រុស | D14: ស្ថាបនិក | E14: 44996 | F14: 5393.8525 | G14: 64.08 | H14: =F14*0.83% -> 44.768976 | I14: =F14+G14+H14 -> 5502.7015 | K14: =I14-J14 -> 5502.7015
A15: 8 | B15: OU RITHTY | C15: ប្រុស | D15: ស្ថាបនិក | E15: 44994 | F15: 4765.1579 | G15: 50 | H15: =F15*0.83% -> 39.550811 | I15: =F15+G15+H15 -> 4854.7087 | K15: =I15-J15 -> 4854.7087
A16: 9 | B16: SENG RITHY | C16: ប្រុស | D16: សមាជិក | E16: 44991 | F16: 5 | G16: 5 | H16: =F16*0.83% -> 0.0415 | I16: =F16+G16+H16 -> 10.0415 | K16: =I16-J16 -> 10.0415
A17: 10 | B17: OU TEP PHALLIN | C17: ស្រី | D17: សមាជិក | E17: 44988 | F17: 20 | G17: 20 | H17: =F17*0.83% -> 0.166 | I17: =F17+G17+H17 -> 40.166 | K17: =I17-J17 -> 40.166
A18: 11 | B18: YIM BUNTHENG | D18: សមាជិក | E18: 44988 | F18: 10 | G18: 10 | H18: =F18*0.83% -> 0.083 | I18: =F18+G18+H18 -> 20.083 | K18: =I18-J18 -> 20.083
A19: 12 | B19: THENG SAVOEUN | D19: សមាជិក | E19: 44967 | F19: 50 | H19: =F19*0.83% -> 0.415 | I19: =F19+G19+H19 -> 50.415 | K19: =I19-J19 -> 50.415
A20: 13 | B20: OU VANN | D20: សមាជិក | E20: 44967 | F20: 20 | H20: =F20*0.83% -> 0.166 | I20: =F20+G20+H20 -> 20.166 | K20: =I20-J20 -> 20.166
A21: 14 | B21: SIYONN SOTHEARITH | C21: ប្រុស | D21: សមាជិក | E21: 44988 | F21: 100 | G21: 100 | H21: =F21*0.83% -> 0.83 | I21: =F21+G21+H21 -> 200.83 | K21: =I21-J21 -> 200.83
A22: 15 | B22: YEAN REAKSMEY | D22: សមាជិក | E22: 44975 | F22: 10 | H22: =F22*0.83% -> 0.083 | I22: =F22+G22+H22 -> 10.083 | K22: =I22-J22 -> 10.083
A23: 16 | B23: SON PENH | D23: សមាជិក | E23: 44995 | F23: 20 | G23: 20 | H23: =F23*0.83% -> 0.166 | I23: =F23+G23+H23 -> 40.166 | K23: =I23-J23 -> 40.166
A24: 17 | B24: SAM SOMONY | C24: ប្រុស | D24: សមាជិក | E24: 44964 | F24: 202.50381 | G24: 50 | H24: =F24*0.83% -> 1.6807816 | I24: =F24+G24+H24 -> 254.18459 | K24: =I24-J24 -> 254.18459
A25: 18 | B25: KOY MAQUIS | C25: ប្រុស | D25: សមាជិក | E25: 44988 | F25: 15.0415 | G25: 10 | H25: =F25*0.83% -> 0.12484445 | I25: =F25+G25+H25 -> 25.166344 | K25: =I25-J25 -> 25.166344
A26: 19 | B26: Ly Malin | C26: ស្រី | D26: សមាជិក | E26: 44988 | F26: 40.166 | G26: 20 | H26: =F26*0.83% -> 0.3333778 | I26: =F26+G26+H26 -> 60.499378 | K26: =I26-J26 -> 60.499378
A27: 20 | B27: Van Bunna | D27: សមាជិក | E27: 44951 | F27: 10 | H27: =F27*0.83% -> 0.083 | I27: =F27+G27+H27 -> 10.083 | K27: =I27-J27 -> 10.083
A28: 21 | B28: Long Borin | C28: ស្រី | D28: សមាជិក | E28: 44988 | F28: 15.1245 | G28: 15 | H28: =F28*0.83% -> 0.12553335 | I28: =F28+G28+H28 -> 30.250033 | K28: =I28-J28 -> 30.250033
A29: 21 | B29: Chan Theara | C29: ស្រី | D29: សមាជិក | E29: 44993 | F29: 5 | I29: =F29+G29+H29 -> 5 | K29: =I29-J29 -> 5
F31: =SUM(F8:F28) -> 33390.821 | G31: =SUM(G8:G28) -> 517.44 | H31: =SUM(H8:H28) -> 277.14381 | I31: =SUM(I8:I28) -> 34185.404 | J31: =SUM(J8:J28) -> 0 | K31: =SUM(K8:K28) -> 34185.404

Sheet Saving monthly Apr-23
A1: ក្រុម​សន្សំ​ប្រាក់ «សន្សំSANSAM»
A2: ការសន្សំ​ចាប់​ពី​៥ដុល្លារ​ឡើង​ទៅក្នុង​មួយខែ ដោយ​សមាជិក​នឹង​ទទួល​បានការប្រាក់ប្រចាំ​ខែ0.83%
A3: ចំពោះ​សមាជិក​ដែលដាក់ប្រាក់​កម្ចី​គឺក្នុងអត្រា​ការប្រាក់​១០%ក្នុង​មួយឆ្នាំ​សម្រាប់ក្រុម​ប្រឹក្សាភិបាល​ ១៤.៤%ក្នុង​មួយឆ្នាំសម្រាប់​សមាជិកស្នូល ១៨%ក្នុងមួយឆ្នាំ​សម្រាប់​សមាជិក​ធម្មតា ៣%​ក្នុងមួយឆ្នាំ​សម្រាប់​សមាជិក​បញ្ញើ
A4: ការ​ដាក់​ប្រាក់​សន្សំចាប់ពី​ថ្ងៃទី១ដល់ថ្ងៃទី១០រៀងរាល់ខែ
A5: ពេលវេលាទទួល​បាន​កម្ចី​ចន្លោះពីថ្ងៃទី១០ដល់ថ្ងៃទី១៥​រៀងរាល់ខែ
A6: តារាងសន្សំ​ខែ មេសា​ ឆ្នាំ២០២៣
A7: ល.រ | B7: ឈ្មោះ​សមាជិកដាក់សន្សំ​ | C7: ភេទ | D7: តួនាទី​ក្នុង​សន្សំ | E7: ថ្ងៃខែដាក់សន្សំ | F7: ប្រាក់ដើម | G7: ប្រាក់ដាក់សន្សំ | H7: ការប្រាក់ទទួលបាន | I7: សមតុល្យ​សាច់ប្រាក់ | J7: ប្រាក់បានដក | K7: សមតុល្យ​សាច់ប្រាក់ក្រោយដក
A8: 1 | B8: ART THORN | C8: ប្រុស | D8: ស្ថាបនិក | E8: 45027 | F8: 3770.3734 | G8: 17.01 | H8: =F8*0.83% -> 31.294099 | I8: =F8+G8+H8 -> 3818.6775 | K8: =I8-J8 -> 3818.6775
A9: 2 | B9: PECH PISEY | C9: ប្រុស | D9: ស្ថាបនិក | E9: 45027 | F9: 5879.4479 | G9: 30 | H9: =F9*0.83% -> 48.799418 | I9: =F9+G9+H9 -> 5958.2473 | K9: =I9-J9 -> 5958.2473
A10: 3 | B10: HONG REAKSMEY | C10: ប្រុស | D10: ស្ថាបនិក | E10: 45026 | F10: 5618.9274 | G10: 50.53 | H10: =F10*0.83% -> 46.637097 | I10: =F10+G10+H10 -> 5716.0945 | K10: =I10-J10 -> 5716.0945
A11: 4 | B11: SIN PUTHEARY | C11: ស្រី | D11: ស្ថាបនិក | E11: 45026 | F11: 5314.3348 | G11: 0.02 | H11: =F11*0.83% -> 44.108979 | I11: =F11+G11+H11 -> 5358.4637 | K11: =I11-J11 -> 5358.4637
A12: 5 | B12: PAO VORN | C12: ប្រុស | D12: ស្ថាបនិក | E12: 45027 | F12: 257.14519 | G12: 50 | H12: =F12*0.83% -> 2.1343051 | I12: =F12+G12+H12 -> 309.27949 | K12: =I12-J12 -> 309.27949
A13: 6 | B13: SOR MORA | C13: ប្រុស | D13: ស្ថាបនិក | E13: 45023 | F13: 2215.6318 | G13: 8.82 | H13: =F13*0.83% -> 18.389744 | I13: =F13+G13+H13 -> 2242.8415 | K13: =I13-J13 -> 2242.8415
A14: 7 | B14: NOP VY | C14: ប្រុស | D14: ស្ថាបនិក | E14: 45026 | F14: 5502.7015 | G14: 67.4 | H14: =F14*0.83% -> 45.672422 | I14: =F14+G14+H14 -> 5615.7739 | K14: =I14-J14 -> 5615.7739
A15: 8 | B15: OU RITHTY | C15: ប្រុស | D15: ស្ថាបនិក | E15: 45026 | F15: 4854.7087 | G15: 50 | H15: =F15*0.83% -> 40.294083 | I15: =F15+G15+H15 -> 4945.0028 | K15: =I15-J15 -> 4945.0028
A16: 9 | B16: SENG RITHY | C16: ប្រុស | D16: សមាជិក | E16: 45026 | F16: 10.0415 | G16: 5 | H16: =F16*0.83% -> 0.08334445 | I16: =F16+G16+H16 -> 15.124844 | K16: =I16-J16 -> 15.124844
A17: 10 | B17: OU TEP PHALLIN | C17: ប្រុស | D17: សមាជិក | E17: 44988 | F17: 40.166 | H17: =F17*0.83% -> 0.3333778 | I17: =F17+G17+H17 -> 40.499378 | K17: =I17-J17 -> 40.499378
A18: 11 | B18: YIM BUNTHENG | D18: សមាជិក | E18: 44988 | F18: 20.083 | H18: =F18*0.83% -> 0.1666889 | I18: =F18+G18+H18 -> 20.249689 | K18: =I18-J18 -> 20.249689
A19: 12 | B19: THENG SAVOEUN | D19: សមាជិក | E19: 45029 | F19: 50.415 | G19: 25 | H19: =F19*0.83% -> 0.4184445 | I19: =F19+G19+H19 -> 75.833444 | K19: =I19-J19 -> 75.833444
A20: 13 | B20: OU VANN | D20: សមាជិក | E20: 44967 | F20: 20.166 | H20: =F20*0.83% -> 0.1673778 | I20: =F20+G20+H20 -> 20.333378 | K20: =I20-J20 -> 20.333378
A21: 14 | B21: SIYONN SOTHEARITH | C21: ប្រុស | D21: សមាជិក | E21: 45034 | F21: 200.83 | G21: 100 | H21: =F21*0.83% -> 1.666889 | I21: =F21+G21+H21 -> 302.49689 | K21: =I21-J21 -> 302.49689
A22: 15 | B22: YEAN REAKSMEY | D22: សមាជិក | E22: 45029 | F22: 10.083 | G22: 30 | H22: =F22*0.83% -> 0.0836889 | I22: =F22+G22+H22 -> 40.166689 | K22: =I22-J22 -> 40.166689
A23: 16 | B23: SON PENH | D23: សមាជិក | E23: 45040 | F23: 40.166 | G23: 20 | H23: =F23*0.83% -> 0.3333778 | I23: =F23+G23+H23 -> 60.499378 | K23: =I23-J23 -> 60.499378
A24: 17 | B24: SAM SOMONY | C24: ប្រុស | D24: សមាជិក | E24: 45024 | F24: 254.18459 | G24: 25 | H24: =F24*0.83% -> 2.1097321 | I24: =F24+G24+H24 -> 281.29432 | K24: =I24-J24 -> 281.29432
A25: 18 | B25: KOY MAQUIS | C25: ប្រុស | D25: សមាជិក | E25: 44971 | F25: 25.166344 | H25: =F25*0.83% -> 0.20888066 | I25: =F25+G25+H25 -> 25.375225 | K25: =I25-J25 -> 25.375225
A26: 19 | B26: Ly Malin | C26: ស្រី | D26: សមាជិក | E26: 45028 | F26: 60.499378 | G26: 20 | H26: =F26*0.83% -> 0.50214484 | I26: =F26+G26+H26 -> 81.001523 | K26: =I26-J26 -> 81.001523
A27: 20 | B27: Van Bunna | D27: សមាជិក | E27: 45031 | F27: 10.083 | G27: 20 | H27: =F27*0.83% -> 0.0836889 | I27: =F27+G27+H27 -> 30.166689 | K27: =I27-J27 -> 30.166689
A28: 21 | B28: Chan Theara | C28: ស្រី | D28: សមាជិក | E28: 44993 | F28: 5 | H28: =F28*0.83% -> 0.0415 | I28: =F28+G28+H28 -> 5.0415 | K28: =I28-J28 -> 5.0415
A29: 22 | B29: Long Borin | C29: ស្រី | D29: សមាជិក | E29: 44957 | F29: 30.25 | G29: 15 | H29: =F29*0.83% -> 0.251075 | I29: =F29+G29+H29 -> 45.501075 | K29: =I29-J29 -> 45.501075
A30: 23 | B30: SOEUNG SAROEUN | D30: សមាជិក | E30: 45034 | F30: 50 | I30: =F30+G30+H30 -> 50 | K30: =I30-J30 -> 50
F32: =SUM(F8:F30) -> 34240.404 | G32: =SUM(G8:G30) -> 533.78 | H32: =SUM(H8:H30) -> 283.78036 | I32: =SUM(I8:I30) -> 35057.965 | J32: =SUM(J8:J30) -> 0 | K32: =SUM(K8:K30) -> 35057.965

Sheet Saving monthly May-23
A1: ក្រុម​សន្សំ​ប្រាក់ «សន្សំSANSAM»
A2: ការសន្សំ​ចាប់​ពី​៥ដុល្លារ​ឡើង​ទៅក្នុង​មួយខែ ដោយ​សមាជិក​នឹង​ទទួល​បានការប្រាក់ប្រចាំ​ខែ0.83%
A3: ចំពោះ​សមាជិក​ដែលដាក់ប្រាក់​កម្ចី​គឺក្នុងអត្រា​ការប្រាក់​១០%ក្នុង​មួយឆ្នាំ​សម្រាប់ក្រុម​ប្រឹក្សាភិបាល​ ១៤.៤%ក្នុង​មួយឆ្នាំសម្រាប់​សមាជិកស្នូល ១៨%ក្នុងមួយឆ្នាំ​សម្រាប់​សមាជិក​ធម្មតា ៣%​ក្នុងមួយឆ្នាំ​សម្រាប់​សមាជិក​បញ្ញើ
A4: ការ​ដាក់​ប្រាក់​សន្សំចាប់ពី​ថ្ងៃទី១ដល់ថ្ងៃទី១០រៀងរាល់ខែ
A5: ពេលវេលាទទួល​បាន​កម្ចី​ចន្លោះពីថ្ងៃទី១០ដល់ថ្ងៃទី១៥​រៀងរាល់ខែ
A6: តារាងសន្សំ​ខែ ឧសភា​ ឆ្នាំ២០២៣
A7: ល.រ | B7: ឈ្មោះ​សមាជិកដាក់សន្សំ​ | C7: ភេទ | D7: តួនាទី​ក្នុង​សន្សំ | E7: ថ្ងៃខែដាក់សន្សំ | F7: ប្រាក់ដើម | G7: ប្រាក់ដាក់សន្សំ | H7: ការប្រាក់ទទួលបាន | I7: សមតុល្យ​សាច់ប្រាក់ | J7: ប្រាក់បានដក | K7: សមតុល្យ​សាច់ប្រាក់ក្រោយដក
A8: 1 | B8: ART THORN | C8: ប្រុស | D8: ស្ថាបនិក | E8: 45059 | F8: 3818.6775 | G8: 17.74 | H8: =F8*0.83% -> 31.695023 | I8: =F8+G8+H8 -> 3868.1125 | K8: =I8-J8 -> 3868.1125
A9: 2 | B9: PECH PISEY | C9: ប្រុស | D9: ស្ថាបនិក | E9: 45060 | F9: 5958.2473 | G9: 50 | H9: =F9*0.83% -> 49.453453 | I9: =F9+G9+H9 -> 6057.7008 | K9: =I9-J9 -> 6057.7008
A10: 3 | B10: HONG REAKSMEY | C10: ប្រុស | D10: ស្ថាបនិក | E10: 45026 | F10: 5716.0945 | H10: =F10*0.83% -> 47.443584 | I10: =F10+G10+H10 -> 5763.5381 | K10: =I10-J10 -> 5763.5381
A11: 4 | B11: SIN PUTHEARY | C11: ស្រី | D11: ស្ថាបនិក | E11: 45026 | F11: 5358.4637 | H11: =F11*0.83% -> 44.475249 | I11: =F11+G11+H11 -> 5402.939 | K11: =I11-J11 -> 5402.939
A12: 5 | B12: PAO VORN | C12: ប្រុស | D12: ស្ថាបនិក | E12: 45027 | F12: 309.27949 | H12: =F12*0.83% -> 2.5670198 | I12: =F12+G12+H12 -> 311.84651 | K12: =I12-J12 -> 311.84651
A13: 6 | B13: SOR MORA | C13: ប្រុស | D13: ស្ថាបនិក | E13: 45056 | F13: 2242.8415 | G13: 10.54 | H13: =F13*0.83% -> 18.615585 | I13: =F13+G13+H13 -> 2271.9971 | K13: =I13-J13 -> 2271.9971
A14: 7 | B14: NOP VY | C14: ប្រុស | D14: ស្ថាបនិក | E14: 45057 | F14: 5615.7739 | G14: 70.72 | H14: =F14*0.83% -> 46.610923 | I14: =F14+G14+H14 -> 5733.1048 | K14: =I14-J14 -> 5733.1048
A15: 8 | B15: OU RITHTY | C15: ប្រុស | D15: ស្ថាបនិក | E15: 45056 | F15: 4945.0028 | G15: 100 | H15: =F15*0.83% -> 41.043523 | I15: =F15+G15+H15 -> 5086.0463 | K15: =I15-J15 -> 5086.0463
A16: 9 | B16: SENG RITHY | C16: ប្រុស | D16: សមាជិក | E16: 45055 | F16: 15.124844 | G16: 5 | H16: =F16*0.83% -> 0.12553621 | I16: =F16+G16+H16 -> 20.250381 | K16: =I16-J16 -> 20.250381
A17: 10 | B17: OU TEP PHALLIN | C17: ប្រុស | D17: សមាជិក | E17: 45055 | F17: 40.499378 | G17: 20 | H17: =F17*0.83% -> 0.33614484 | I17: =F17+G17+H17 -> 60.835523 | K17: =I17-J17 -> 60.835523
A18: 11 | B18: YIM BUNTHENG | D18: សមាជិក | E18: 44988 | F18: 20.249689 | H18: =F18*0.83% -> 0.16807242 | I18: =F18+G18+H18 -> 20.417761 | K18: =I18-J18 -> 20.417761
A19: 12 | B19: THENG SAVOEUN | D19: សមាជិក | E19: 45029 | F19: 75.833444 | H19: =F19*0.83% -> 0.62941759 | I19: =F19+G19+H19 -> 76.462862 | K19: =I19-J19 -> 76.462862
A20: 13 | B20: OU VANN | D20: សមាជិក | E20: 44967 | F20: 20.333378 | H20: =F20*0.83% -> 0.16876704 | I20: =F20+G20+H20 -> 20.502145 | K20: =I20-J20 -> 20.502145
A21: 14 | B21: SIYONN SOTHEARITH | C21: ប្រុស | D21: សមាជិក | E21: 45049 | F21: 302.49689 | G21: 100 | H21: =F21*0.83% -> 2.5107242 | I21: =F21+G21+H21 -> 405.00761 | K21: =I21-J21 -> 405.00761
A22: 15 | B22: YEAN REAKSMEY | D22: សមាជិក | E22: 45056 | F22: 40.166689 | G22: 10 | H22: =F22*0.83% -> 0.33338352 | I22: =F22+G22+H22 -> 50.500072 | K22: =I22-J22 -> 50.500072
A23: 16 | B23: SON PENH | D23: សមាជិក | E23: 45059 | F23: 60.499378 | G23: 20 | H23: =F23*0.83% -> 0.50214484 | I23: =F23+G23+H23 -> 81.001523 | K23: =I23-J23 -> 81.001523
A24: 17 | B24: SAM SOMONY | C24: ប្រុស | D24: សមាជិក | E24: 45049 | F24: 281.29432 | G24: 25 | H24: =F24*0.83% -> 2.3347429 | I24: =F24+G24+H24 -> 308.62906 | K24: =I24-J24 -> 308.62906
A25: 18 | B25: KOY MAQUIS | C25: ប្រុស | D25: សមាជិក | E25: 45057 | F25: 25.375225 | G25: 10 | H25: =F25*0.83% -> 0.21061437 | I25: =F25+G25+H25 -> 35.585839 | K25: =I25-J25 -> 35.585839
A26: 19 | B26: Ly Malin | C26: ស្រី | D26: សមាជិក | E26: 45056 | F26: 81.001523 | G26: 20 | H26: =F26*0.83% -> 0.67231264 | I26: =F26+G26+H26 -> 101.67384 | K26: =I26-J26 -> 101.67384
A27: 20 | B27: Van Bunna | D27: សមាជិក | E27: 45031 | F27: 30.166689 | H27: =F27*0.83% -> 0.25038352 | I27: =F27+G27+H27 -> 30.417072 | K27: =I27-J27 -> 30.417072
A28: 21 | B28: Chan Theara | C28: ស្រី | D28: សមាជិក | E28: 44993 | F28: 5.0415 | H28: =F28*0.83% -> 0.04184445 | I28: =F28+G28+H28 -> 5.0833445 | K28: =I28-J28 -> 5.0833445
A29: 22 | B29: Long Borin | C29: ស្រី | D29: សមាជិក | E29: 45055 | F29: 45.5 | G29: 15 | H29: =F29*0.83% -> 0.37765 | I29: =F29+G29+H29 -> 60.87765 | K29: =I29-J29 -> 60.87765
A30: 23 | B30: SOEUNG SAROEUN | D30: សមាជិក | E30: 45059 | F30: 50 | G30: 25 | H30: =F30*0.83% -> 0.415 | I30: =F30+G30+H30 -> 75.415 | K30: =I30-J30 -> 75.415
A31: 24 | B31: TUY SYTHIENG | D31: សមាជិក | E31: 45056 | F31: 50 | I31: =F31+G31+H31 -> 50 | K31: =I31-J31 -> 50
A32: 25 | B32: CHHEOUNG VEASNA | D32: សមាជិក | E32: 45058 | F32: 100 | I32: =F32+G32+H32 -> 100 | K32: =I32-J32 -> 100
A33: 26 | B33: OM MANITH | D33: សមាជិក | E33: 45059 | F33: 20 | I33: =F33+G33+H33 -> 20 | K33: =I33-J33 -> 20
A34: 27 | B34: IM SOTHY | D34: សមាជិក | E34: 45060 | F34: 30 | I34: =F34+G34+H34 -> 30 | K34: =I34-J34 -> 30
F36: =SUM(F8:F34) -> 35257.964 | G36: =SUM(G8:G34) -> 499 | H36: =SUM(H8:H34) -> 290.9811 | I36: =SUM(I8:I34) -> 36047.945 | J36: =SUM(J8:J34) -> 0 | K36: =SUM(K8:K34) -> 36047.945

Sheet Saving monthly Jun-23
A1: ក្រុម​សន្សំ​ប្រាក់ «សន្សំSANSAM»
A2: ការសន្សំ​ចាប់​ពី​៥ដុល្លារ​ឡើង​ទៅក្នុង​មួយខែ ដោយ​សមាជិក​នឹង​ទទួល​បានការប្រាក់ប្រចាំ​ខែ0.83%
A3: ចំពោះ​សមាជិក​ដែលដាក់ប្រាក់​កម្ចី​គឺក្នុងអត្រា​ការប្រាក់​១០%ក្នុង​មួយឆ្នាំ​សម្រាប់ក្រុម​ប្រឹក្សាភិបាល​ ១៤.៤%ក្នុង​មួយឆ្នាំសម្រាប់​សមាជិកស្នូល ១៨%ក្នុងមួយឆ្នាំ​សម្រាប់​សមាជិក​ធម្មតា ៣%​ក្នុងមួយឆ្នាំ​សម្រាប់​សមាជិក​បញ្ញើ
A4: ការ​ដាក់​ប្រាក់​សន្សំចាប់ពី​ថ្ងៃទី១ដល់ថ្ងៃទី១០រៀងរាល់ខែ
A5: ពេលវេលាទទួល​បាន​កម្ចី​ចន្លោះពីថ្ងៃទី១០ដល់ថ្ងៃទី១៥​រៀងរាល់ខែ
A6: តារាងសន្សំ​ខែ មិថុនា​ ឆ្នាំ២០២៣
A7: ល.រ | B7: ឈ្មោះ​សមាជិកដាក់សន្សំ​ | C7: ភេទ | D7: តួនាទី​ក្នុង​សន្សំ | E7: ថ្ងៃខែដាក់សន្សំ | F7: ប្រាក់ដើម | G7: ប្រាក់ដាក់សន្សំ | H7: ការប្រាក់ទទួលបាន | I7: សមតុល្យ​សាច់ប្រាក់ | J7: ប្រាក់បានដក | K7: សមតុល្យ​សាច់ប្រាក់ក្រោយដក
A8: 1 | B8: ART THORN | C8: ប្រុស | D8: ស្ថាបនិក | E8: 45089 | F8: 3868.1125 | G8: 18.47 | H8: =F8*0.83% -> 32.105334 | I8: =F8+G8+H8 -> 3918.6879 | K8: =I8-J8 -> 3918.6879
A9: 2 | B9: PECH PISEY | C9: ប្រុស | D9: ស្ថាបនិក | E9: 45060 | F9: 6057.7008 | H9: =F9*0.83% -> 50.278917 | I9: =F9+G9+H9 -> 6107.9797 | K9: =I9-J9 -> 6107.9797
A10: 3 | B10: HONG REAKSMEY | C10: ប្រុស | D10: ស្ថាបនិក | E10: 45087 | F10: 5763.5381 | G10: 50 | H10: =F10*0.83% -> 47.837366 | I10: =F10+G10+H10 -> 5861.3754 | K10: =I10-J10 -> 5861.3754
A11: 4 | B11: SIN PUTHEARY | C11: ស្រី | D11: ស្ថាបនិក | E11: 45026 | F11: 5402.939 | H11: =F11*0.83% -> 44.844394 | I11: =F11+G11+H11 -> 5447.7834 | K11: =I11-J11 -> 5447.7834
A12: 5 | B12: PAO VORN | C12: ប្រុស | D12: ស្ថាបនិក | E12: 45087 | F12: 311.84651 | G12: 30 | H12: =F12*0.83% -> 2.5883261 | I12: =F12+G12+H12 -> 344.43484 | K12: =I12-J12 -> 344.43484
A13: 6 | B13: SOR MORA | C13: ប្រុស | D13: ស្ថាបនិក | E13: 45087 | F13: 2271.9971 | G13: 12.27 | H13: =F13*0.83% -> 18.857576 | I13: =F13+G13+H13 -> 2303.1247 | K13: =I13-J13 -> 2303.1247
A14: 7 | B14: NOP VY | C14: ប្រុស | D14: ស្ថាបនិក | E14: 45087 | F14: 5733.1048 | G14: 74.04 | H14: =F14*0.83% -> 47.58477 | I14: =F14+G14+H14 -> 5854.7296 | K14: =I14-J14 -> 5854.7296
A15: 8 | B15: OU RITHTY | C15: ប្រុស | D15: ស្ថាបនិក | E15: 45087 | F15: 5086.0463 | G15: 100 | H15: =F15*0.83% -> 42.214185 | I15: =F15+G15+H15 -> 5228.2605 | K15: =I15-J15 -> 5228.2605
A16: 9 | B16: SENG RITHY | C16: ប្រុស | D16: សមាជិក | E16: 45084 | F16: 20.250381 | G16: 5 | H16: =F16*0.83% -> 0.16807816 | I16: =F16+G16+H16 -> 25.418459 | K16: =I16-J16 -> 25.418459
A17: 10 | B17: OU TEP PHALLIN | C17: ស្រី | D17: សមាជិក | E17: 45084 | F17: 60.835523 | G17: 20 | H17: =F17*0.83% -> 0.50493484 | I17: =F17+G17+H17 -> 81.340457 | K17: =I17-J17 -> 81.340457
A18: 11 | B18: YIM BUNTHENG | D18: សមាជិក | E18: 45086 | F18: 20.417761 | G18: 10 | H18: =F18*0.83% -> 0.16946742 | I18: =F18+G18+H18 -> 30.587229 | K18: =I18-J18 -> 30.587229
A19: 12 | B19: THENG SAVOEUN | D19: សមាជិក | E19: 45029 | F19: 76.462862 | H19: =F19*0.83% -> 0.63464176 | I19: =F19+G19+H19 -> 77.097504 | K19: =I19-J19 -> 77.097504
A20: 13 | B20: OL VANN | D20: សមាជិក | E20: 45088 | F20: 20.502145 | G20: 20 | H20: =F20*0.83% -> 0.1701678 | I20: =F20+G20+H20 -> 40.672313 | K20: =I20-J20 -> 40.672313
A21: 14 | B21: SIYONN SOTHEARITH | C21: ប្រុស | D21: សមាជិក | E21: 45079 | F21: 405.00761 | G21: 100 | H21: =F21*0.83% -> 3.3615632 | I21: =F21+G21+H21 -> 508.36918 | K21: =I21-J21 -> 508.36918
A22: 15 | B22: YEAN REAKSMEY | D22: សមាជិក | E22: 45056 | F22: 50.500072 | H22: =F22*0.83% -> 0.4191506 | I22: =F22+G22+H22 -> 50.919223 | K22: =I22-J22 -> 50.919223
A23: 16 | B23: SON PENH | D23: សមាជិក | E23: 45059 | F23: 81.001523 | G23: 20 | H23: =F23*0.83% -> 0.67231264 | I23: =F23+G23+H23 -> 101.67384 | K23: =I23-J23 -> 101.67384
A24: 17 | B24: SAM SOMONY | C24: ប្រុស | D24: សមាជិក | E24: 45083 | F24: 308.62906 | G24: 25 | H24: =F24*0.83% -> 2.5616212 | I24: =F24+G24+H24 -> 336.19068 | K24: =I24-J24 -> 336.19068
A25: 18 | B25: KOY MAQUIS | C25: ប្រុស | D25: សមាជិក | E25: 45085 | F25: 35.585839 | G25: 10 | H25: =F25*0.83% -> 0.29536247 | I25: =F25+G25+H25 -> 45.881202 | K25: =I25-J25 -> 45.881202
A26: 19 | B26: Ly Malin | C26: ស្រី | D26: សមាជិក | E26: 45083 | F26: 101.67384 | G26: 20 | H26: =F26*0.83% -> 0.84389283 | I26: =F26+G26+H26 -> 122.51773 | K26: =I26-J26 -> 122.51773
A27: 20 | B27: Van Bunna | D27: សមាជិក | E27: 45088 | F27: 30.417072 | G27: 20 | H27: =F27*0.83% -> 0.2524617 | I27: =F27+G27+H27 -> 50.669534 | K27: =I27-J27 -> 50.669534
A28: 21 | B28: Chan Theara | C28: ស្រី | D28: សមាជិក | E28: 44993 | F28: 5.0833445 | H28: =F28*0.83% -> 0.042191759 | I28: =F28+G28+H28 -> 5.1255362 | K28: =I28-J28 -> 5.1255362
A29: 22 | B29: Long Borin | C29: ស្រី | D29: សមាជិក | E29: 45086 | F29: 60.87765 | G29: 15 | H29: =F29*0.83% -> 0.50528449 | I29: =F29+G29+H29 -> 76.382935 | K29: =I29-J29 -> 76.382935
A30: 23 | B30: SOEUNG SAROEUN | D30: សមាជិក | E30: 45059 | F30: 75.415 | H30: =F30*0.83% -> 0.6259445 | I30: =F30+G30+H30 -> 76.040944 | K30: =I30-J30 -> 76.040944
A31: 24 | B31: TUY SYTHIENG | D31: សមាជិក | E31: 45088 | F31: 50 | G31: 50 | H31: =F31*0.83% -> 0.415 | I31: =F31+G31+H31 -> 100.415 | K31: =I31-J31 -> 100.415
A32: 25 | B32: CHHEOUNG VEASNA | D32: សមាជិក | E32: 45087 | F32: 100 | G32: 10 | H32: =F32*0.83% -> 0.83 | I32: =F32+G32+H32 -> 110.83 | K32: =I32-J32 -> 110.83
A33: 26 | B33: OM MANITH | D33: សមាជិក | E33: 45059 | F33: 20 | H33: =F33*0.83% -> 0.166 | I33: =F33+G33+H33 -> 20.166 | K33: =I33-J33 -> 20.166
A34: 27 | B34: SOTHY | D34: សមាជិក | E34: 45060 | F34: 30 | H34: =F34*0.83% -> 0.249 | I34: =F34+G34+H34 -> 30.249 | K34: =I34-J34 -> 30.249
A35: 28 | B35: Pa Chanroeun | C35: ប្រុស | D35: សមាជិក | E35: 45085 | F35: 200 | H35: =F35*0.83% -> 1.66 | I35: =F35+G35+H35 -> 201.66 | K35: =I35-J35 -> 201.66
F37: =SUM(F8:F35) -> 36247.945 | G37: =SUM(G8:G35) -> 609.78 | H37: =SUM(H8:H35) -> 300.85794 | I37: =SUM(I8:I35) -> 37158.583 | J37: =SUM(J8:J35) -> 0 | K37: =SUM(K8:K35) -> 37158.583

Sheet Saving Monthly Jul-23
A1: ក្រុម​សន្សំ​ប្រាក់ «សន្សំSANSAM»
A2: ការសន្សំ​ចាប់​ពី​៥ដុល្លារ​ឡើង​ទៅក្នុង​មួយខែ ដោយ​សមាជិក​នឹង​ទទួល​បានការប្រាក់ប្រចាំ​ខែ0.83%
A3: ចំពោះ​សមាជិក​ដែលដាក់ប្រាក់​កម្ចី​គឺក្នុងអត្រា​ការប្រាក់​១០%ក្នុង​មួយឆ្នាំ​សម្រាប់ក្រុម​ប្រឹក្សាភិបាល​ ១៤.៤%ក្នុង​មួយឆ្នាំសម្រាប់​សមាជិកស្នូល ១៨%ក្នុងមួយឆ្នាំ​សម្រាប់​សមាជិក​ធម្មតា ៣%​ក្នុងមួយឆ្នាំ​សម្រាប់​សមាជិក​បញ្ញើ
A4: ការ​ដាក់​ប្រាក់​សន្សំចាប់ពី​ថ្ងៃទី១ដល់ថ្ងៃទី១០រៀងរាល់ខែ
A5: ពេលវេលាទទួល​បាន​កម្ចី​ចន្លោះពីថ្ងៃទី១០ដល់ថ្ងៃទី១៥​រៀងរាល់ខែ
A6: តារាងសន្សំ​ខែ កក្កដា​ ឆ្នាំ២០២៣
A7: ល.រ | B7: ឈ្មោះ​សមាជិកដាក់សន្សំ​ | C7: ភេទ | D7: តួនាទី​ក្នុង​សន្សំ | E7: ថ្ងៃខែដាក់សន្សំ | F7: ប្រាក់ដើម | G7: ប្រាក់ដាក់សន្សំ | H7: ការប្រាក់ទទួលបាន | I7: សមតុល្យ​សាច់ប្រាក់ | J7: ប្រាក់បានដក | K7: សមតុល្យ​សាច់ប្រាក់ក្រោយដក
A8: 1 | B8: ART THORN | C8: ប្រុស | D8: ស្ថាបនិក | E8: 45118 | F8: 3918.6879 | G8: 19.21 | H8: =F8*0.83% -> 32.525109 | I8: =F8+G8+H8 -> 3970.423 | K8: =I8-J8 -> 3970.423
A9: 2 | B9: PECH PISEY | C9: ប្រុស | D9: ស្ថាបនិក | E9: 45122 | F9: 6107.9797 | G9: 30 | H9: =F9*0.83% -> 50.696232 | I9: =F9+G9+H9 -> 6188.6759 | K9: =I9-J9 -> 6188.6759
A10: 3 | B10: HONG REAKSMEY | C10: ប្រុស | D10: ស្ថាបនិក | E10: 45114 | F10: 5861.3754 | G10: 50 | H10: =F10*0.83% -> 48.649416 | I10: =F10+G10+H10 -> 5960.0248 | K10: =I10-J10 -> 5960.0248
A11: 4 | B11: SIN PUTHEARY | C11: ស្រី | D11: ស្ថាបនិក | E11: 45026 | F11: 5447.7834 | H11: =F11*0.83% -> 45.216602 | I11: =F11+G11+H11 -> 5493 | K11: =I11-J11 -> 5493
A12: 5 | B12: PAO VORN | C12: ប្រុស | D12: ស្ថាបនិក | E12: 45087 | F12: 344.43484 | H12: =F12*0.83% -> 2.8588092 | I12: =F12+G12+H12 -> 347.29365 | K12: =I12-J12 -> 347.29365
A13: 6 | B13: SOR MORA | C13: ប្រុស | D13: ស្ថាបនិក | E13: 45114 | F13: 2303.1247 | G13: 3.44 | H13: =F13*0.83% -> 19.115935 | I13: =F13+G13+H13 -> 2325.6806 | K13: =I13-J13 -> 2325.6806
A14: 7 | B14: NOP VY | C14: ប្រុស | D14: ស្ថាបនិក | E14: 45116 | F14: 5854.7296 | G14: 27.36 | H14: =F14*0.83% -> 48.594255 | I14: =F14+G14+H14 -> 5930.6838 | K14: =I14-J14 -> 5930.6838
A15: 8 | B15: OU RITHTY | C15: ប្រុស | D15: ស្ថាបនិក | E15: 45114 | F15: 5228.2605 | G15: 100 | H15: =F15*0.83% -> 43.394562 | I15: =F15+G15+H15 -> 5371.6551 | K15: =I15-J15 -> 5371.6551
A16: 9 | B16: SENG RITHY | C16: ប្រុស | D16: សមាជិក | E16: 45114 | F16: 25.418459 | G16: 5 | H16: =F16*0.83% -> 0.21097321 | I16: =F16+G16+H16 -> 30.629432 | K16: =I16-J16 -> 30.629432
A17: 10 | B17: OU TEP PHALLIN | C17: ប្រុស | D17: សមាជិក | E17: 45086 | F17: 81.340457 | H17: =F17*0.83% -> 0.6751258 | I17: =F17+G17+H17 -> 82.015583 | K17: =I17-J17 -> 82.015583
A18: 11 | B18: YIM BUNTHENG | D18: សមាជិក | E18: 45114 | F18: 30.587229 | G18: 10 | H18: =F18*0.83% -> 0.253874 | I18: =F18+G18+H18 -> 40.841103 | K18: =I18-J18 -> 40.841103
A19: 12 | B19: THENG SAVOEUN | D19: សមាជិក | E19: 45029 | F19: 77.097504 | H19: =F19*0.83% -> 0.63990928 | I19: =F19+G19+H19 -> 77.737413 | K19: =I19-J19 -> 77.737413
A20: 13 | B20: UL VANN | D20: សមាជិក | E20: 45118 | F20: 40.672313 | G20: 20 | H20: =F20*0.83% -> 0.33758019 | I20: =F20+G20+H20 -> 61.009893 | K20: =I20-J20 -> 61.009893
A21: 14 | B21: SIYONN SOTHEARITH | C21: ប្រុស | D21: សមាជិក | E21: 45079 | F21: 508.36918 | H21: =F21*0.83% -> 4.2194642 | I21: =F21+G21+H21 -> 512.58864 | K21: =I21-J21 -> 512.58864
A22: 15 | B22: YEAN REAKSMEY | D22: សមាជិក | E22: 45056 | F22: 50.919223 | H22: =F22*0.83% -> 0.42262955 | I22: =F22+G22+H22 -> 51.341853 | K22: =I22-J22 -> 51.341853
A23: 16 | B23: SON PENH | D23: សមាជិក | E23: 45104 | F23: 101.67384 | G23: 20 | H23: =F23*0.83% -> 0.84389283 | I23: =F23+G23+H23 -> 122.51773 | K23: =I23-J23 -> 122.51773
A24: 17 | B24: SAM SOMONY | C24: ប្រុស | D24: សមាជិក | E24: 45114 | F24: 336.19068 | G24: 25 | H24: =F24*0.83% -> 2.7903827 | I24: =F24+G24+H24 -> 363.98107 | K24: =I24-J24 -> 363.98107
A25: 18 | B25: KOY MAQUIS | C25: ប្រុស | D25: សមាជិក | E25: 45115 | F25: 45.881202 | G25: 10 | H25: =F25*0.83% -> 0.38081398 | I25: =F25+G25+H25 -> 56.262016 | K25: =I25-J25 -> 56.262016
A26: 19 | B26: Ly Malin | C26: ស្រី | D26: សមាជិក | E26: 45114 | F26: 122.51773 | G26: 20 | H26: =F26*0.83% -> 1.0168971 | I26: =F26+G26+H26 -> 143.53463 | K26: =I26-J26 -> 143.53463
A27: 20 | B27: Van Bunna | D27: សមាជិក | E27: 45088 | F27: 50.669534 | H27: =F27*0.83% -> 0.42055713 | I27: =F27+G27+H27 -> 51.090091 | K27: =I27-J27 -> 51.090091
A28: 21 | B28: Chan Theara | C28: ស្រី | D28: សមាជិក | E28: 44993 | F28: 5.1255362 | H28: =F28*0.83% -> 0.042541951 | I28: =F28+G28+H28 -> 5.1680782 | K28: =I28-J28 -> 5.1680782
A29: 22 | B29: Long Borin | C29: ស្រី | D29: សមាជិក | E29: 45114 | F29: 76.382934 | G29: 15 | H29: =F29*0.83% -> 0.63397836 | I29: =F29+G29+H29 -> 92.016913 | K29: =I29-J29 -> 92.016913
A30: 23 | B30: SOEUNG SAROEUN | D30: សមាជិក | E30: 45059 | F30: 76.040945 | H30: =F30*0.83% -> 0.63113984 | I30: =F30+G30+H30 -> 76.672084 | K30: =I30-J30 -> 76.672084
A31: 24 | B31: TUY SYTHIENG | D31: សមាជិក | E31: 45088 | F31: 100.415 | H31: =F31*0.83% -> 0.8334445 | I31: =F31+G31+H31 -> 101.24844 | K31: =I31-J31 -> 101.24844
A32: 25 | B32: CHHEOUNG VEASNA | D32: សមាជិក | E32: 45118 | F32: 110.83 | G32: 100 | H32: =F32*0.83% -> 0.919889 | I32: =F32+G32+H32 -> 211.74989 | K32: =I32-J32 -> 211.74989
A33: 26 | B33: OM MANITH | D33: សមាជិក | E33: 45059 | F33: 20.166 | H33: =F33*0.83% -> 0.1673778 | I33: =F33+G33+H33 -> 20.333378 | K33: =I33-J33 -> 20.333378
A34: 27 | B34: SOTHY | D34: សមាជិក | E34: 45060 | F34: 30.249 | H34: =F34*0.83% -> 0.2510667 | I34: =F34+G34+H34 -> 30.500067 | K34: =I34-J34 -> 30.500067
A35: 28 | B35: Pa Chanroeun | C35: ប្រុស | D35: សមាជិក | E35: 45085 | F35: 201.66 | I35: =F35+G35+H35 -> 201.66 | K35: =I35-J35 -> 201.66
F37: =SUM(F8:F35) -> 37158.583 | G37: =SUM(G8:G35) -> 455.01 | H37: =SUM(H8:H35) -> 306.74246 | I37: =SUM(I8:I35) -> 37920.335 | J37: =SUM(J8:J35) -> 0 | K37: =SUM(K8:K35) -> 37920.335

Sheet Saving Monthly Aug-23
A1: ក្រុម​សន្សំ​ប្រាក់ «សន្សំSANSAM»
A2: ការសន្សំ​ចាប់​ពី​៥ដុល្លារ​ឡើង​ទៅក្នុង​មួយខែ ដោយ​សមាជិក​នឹង​ទទួល​បានការប្រាក់ប្រចាំ​ខែ0.83%
A3: ចំពោះ​សមាជិក​ដែលដាក់ប្រាក់​កម្ចី​គឺក្នុងអត្រា​ការប្រាក់​១០%ក្នុង​មួយឆ្នាំ​សម្រាប់ក្រុម​ប្រឹក្សាភិបាល​ ១៤.៤%ក្នុង​មួយឆ្នាំសម្រាប់​សមាជិកស្នូល ១៨%ក្នុងមួយឆ្នាំ​សម្រាប់​សមាជិក​ធម្មតា ៣%​ក្នុងមួយឆ្នាំ​សម្រាប់​សមាជិក​បញ្ញើ
A4: ការ​ដាក់​ប្រាក់​សន្សំចាប់ពី​ថ្ងៃទី១ដល់ថ្ងៃទី១០រៀងរាល់ខែ
A5: ពេលវេលាទទួល​បាន​កម្ចី​ចន្លោះពីថ្ងៃទី១០ដល់ថ្ងៃទី១៥​រៀងរាល់ខែ
A6: តារាងសន្សំ​ខែ សីហា ឆ្នាំ២០២៣
A7: ល.រ | B7: ឈ្មោះ​សមាជិកដាក់សន្សំ​ | C7: ភេទ | D7: តួនាទី​ក្នុង​សន្សំ | E7: ថ្ងៃខែដាក់សន្សំ | F7: ប្រាក់ដើម | G7: ប្រាក់ដាក់សន្សំ | H7: ការប្រាក់ទទួលបាន | I7: សមតុល្យ​សាច់ប្រាក់ | J7: ប្រាក់បានដក | K7: សមតុល្យ​សាច់ប្រាក់ក្រោយដក
A8: 1 | B8: ART THORN | C8: ប្រុស | D8: ស្ថាបនិក | E8: 45149 | F8: 3970.423 | G8: 9.94 | H8: =F8*0.83% -> 32.954511 | I8: =F8+G8+H8 -> 4013.3175 | K8: =I8-J8 -> 4013.3175
A9: 2 | B9: PECH PISEY | C9: ប្រុស | D9: ស្ថាបនិក | E9: 45146 | F9: 6188.6759 | G9: 50 | H9: =F9*0.83% -> 51.36601 | I9: =F9+G9+H9 -> 6290.0419 | K9: =I9-J9 -> 6290.0419
A10: 3 | B10: HONG REAKSMEY | C10: ប្រុស | D10: ស្ថាបនិក | E10: 45114 | F10: 5960.0248 | H10: =F10*0.83% -> 49.468206 | I10: =F10+G10+H10 -> 6009.4931 | K10: =I10-J10 -> 6009.4931
A11: 4 | B11: SIN PUTHEARY | C11: ស្រី | D11: ស្ថាបនិក | E11: 45149 | F11: 5493 | G11: 2 | H11: =F11*0.83% -> 45.5919 | I11: =F11+G11+H11 -> 5540.5919 | K11: =I11-J11 -> 5540.5919
A12: 5 | B12: PAO VORN | C12: ប្រុស | D12: ស្ថាបនិក | E12: 45087 | F12: 347.29365 | H12: =F12*0.83% -> 2.8825373 | I12: =F12+G12+H12 -> 350.17619 | K12: =I12-J12 -> 350.17619
A13: 6 | B13: SOR MORA | C13: ប្រុស | D13: ស្ថាបនិក | E13: 45114 | F13: 2325.6806 | H13: =F13*0.83% -> 19.303149 | I13: =F13+G13+H13 -> 2344.9838 | K13: =I13-J13 -> 2344.9838
A14: 7 | B14: NOP VY | C14: ប្រុស | D14: ស្ថាបនិក | E14: 45148 | F14: 5930.6838 | G14: 30.68 | H14: =F14*0.83% -> 49.224676 | I14: =F14+G14+H14 -> 6010.5885 | K14: =I14-J14 -> 6010.5885
A15: 8 | B15: OU RITHTY | C15: ប្រុស | D15: ស្ថាបនិក | E15: 45146 | F15: 5371.6551 | G15: 100 | H15: =F15*0.83% -> 44.584737 | I15: =F15+G15+H15 -> 5516.2398 | K15: =I15-J15 -> 5516.2398
A16: 9 | B16: SENG RITHY | C16: ប្រុស | D16: សមាជិក | E16: 45147 | F16: 30.629432 | G16: 5 | H16: =F16*0.83% -> 0.25422429 | I16: =F16+G16+H16 -> 35.883656 | K16: =I16-J16 -> 35.883656
A17: 10 | B17: OU TEP PHALLIN | C17: ប្រុស | D17: សមាជិក | E17: 45086 | F17: 82.015583 | G17: 20 | H17: =F17*0.83% -> 0.68072934 | I17: =F17+G17+H17 -> 102.69631 | K17: =I17-J17 -> 102.69631
A18: 11 | B18: YIM BUNTHENG | D18: សមាជិក | E18: 45147 | F18: 40.841103 | G18: 10 | H18: =F18*0.83% -> 0.33898115 | I18: =F18+G18+H18 -> 51.180084 | K18: =I18-J18 -> 51.180084
A19: 12 | B19: THENG SAVOEUN | D19: សមាជិក | E19: 45029 | F19: 77.737413 | H19: =F19*0.83% -> 0.64522053 | I19: =F19+G19+H19 -> 78.382634 | K19: =I19-J19 -> 78.382634
A20: 13 | B20: UL VANN | D20: សមាជិក | E20: 45148 | F20: 61.009893 | G20: 20 | H20: =F20*0.83% -> 0.50638211 | I20: =F20+G20+H20 -> 81.516275 | K20: =I20-J20 -> 81.516275
A21: 14 | B21: SIYONN SOTHEARITH | C21: ប្រុស | D21: សមាជិក | E21: 45079 | F21: 512.58864 | H21: =F21*0.83% -> 4.2544857 | I21: =F21+G21+H21 -> 516.84313 | K21: =I21-J21 -> 516.84313
A22: 15 | B22: YEAN REAKSMEY | D22: សមាជិក | E22: 45056 | F22: 51.341853 | H22: =F22*0.83% -> 0.42613738 | I22: =F22+G22+H22 -> 51.76799 | K22: =I22-J22 -> 51.76799
A23: 16 | B23: SON PENH | D23: សមាជិក | E23: 45104 | F23: 122.51773 | H23: =F23*0.83% -> 1.0168971 | I23: =F23+G23+H23 -> 123.53463 | K23: =I23-J23 -> 123.53463
A24: 17 | B24: SAM SOMONY | C24: ប្រុស | D24: សមាជិក | E24: 45143 | F24: 363.98107 | G24: 25 | H24: =F24*0.83% -> 3.0210429 | I24: =F24+G24+H24 -> 392.00211 | K24: =I24-J24 -> 392.00211
A25: 18 | B25: KOY MAQUIS | C25: ប្រុស | D25: សមាជិក | E25: 45147 | F25: 56.262016 | G25: 10 | H25: =F25*0.83% -> 0.46697473 | I25: =F25+G25+H25 -> 66.728991 | K25: =I25-J25 -> 66.728991
A26: 19 | B26: Ly Malin | C26: ស្រី | D26: សមាជិក | E26: 45147 | F26: 143.53463 | G26: 20 | H26: =F26*0.83% -> 1.1913374 | I26: =F26+G26+H26 -> 164.72596 | K26: =I26-J26 -> 164.72596
A27: 20 | B27: Van Bunna | D27: សមាជិក | E27: 45088 | F27: 51.090091 | H27: =F27*0.83% -> 0.42404776 | I27: =F27+G27+H27 -> 51.514139 | K27: =I27-J27 -> 51.514139
A28: 21 | B28: Chan Theara | C28: ស្រី | D28: សមាជិក | E28: 44993 | F28: 5.1680782 | H28: =F28*0.83% -> 0.042895049 | I28: =F28+G28+H28 -> 5.2109732 | K28: =I28-J28 -> 5.2109732
A29: 22 | B29: Long Borin | C29: ស្រី | D29: សមាជិក | E29: 45140 | F29: 92.02 | G29: 15 | H29: =F29*0.83% -> 0.763766 | I29: =F29+G29+H29 -> 107.78377 | K29: =I29-J29 -> 107.78377
A30: 23 | B30: SOEUNG SAROEUN | D30: សមាជិក | E30: 45059 | F30: 76.672084 | H30: =F30*0.83% -> 0.6363783 | I30: =F30+G30+H30 -> 77.308463 | K30: =I30-J30 -> 77.308463
A31: 24 | B31: TUY SYTHIENG | D31: សមាជិក | E31: 45146 | F31: 101.24844 | G31: 100 | H31: =F31*0.83% -> 0.84036209 | I31: =F31+G31+H31 -> 202.08881 | K31: =I31-J31 -> 202.08881
A32: 25 | B32: CHHEOUNG VEASNA | D32: សមាជិក | E32: 45118 | F32: 211.74989 | H32: =F32*0.83% -> 1.7575241 | I32: =F32+G32+H32 -> 213.50741 | K32: =I32-J32 -> 213.50741
A33: 26 | B33: OM MANITH | D33: សមាជិក | E33: 45059 | F33: 20.333378 | H33: =F33*0.83% -> 0.16876704 | I33: =F33+G33+H33 -> 20.502145 | K33: =I33-J33 -> 20.502145
A34: 27 | B34: SOTHY | D34: សមាជិក | E34: 45060 | F34: 30.500067 | H34: =F34*0.83% -> 0.25315055 | I34: =F34+G34+H34 -> 30.753217 | K34: =I34-J34 -> 30.753217
A35: 28 | B35: Pa Chanroeun | C35: ប្រុស | D35: សមាជិក | E35: 45085 | F35: 201.66 | I35: =F35+G35+H35 -> 201.66 | K35: =I35-J35 -> 201.66
F37: =SUM(F8:F35) -> 37920.338 | G37: =SUM(G8:G35) -> 417.62 | H37: =SUM(H8:H35) -> 313.06503 | I37: =SUM(I8:I35) -> 38651.023 | J37: =SUM(J8:J35) -> 0 | K37: =SUM(K8:K35) -> 38651.023

Sheet Saving Monthly Sep-23
A1: SANSAM SAVING GROUP
A2: SAVING FROM 5USD PER MONTH BY GETTING INTEREST 10% PER YEAR
A3: SAVING DEPOSIT FROM 1ST - 10TH EVERY MONTH
A4: ACCESSIBLE LOAN ON 15TH EACH MONTH
A5: SAVING IN SEPTEMBER 2023
A6: NO | B6: NAME | C6: SEX | D6: ROLE | E6: SAVING DATE | F6: TEAM LEADER | G6: CAPITAL | H6: SAVING | I6: INTEREST | J6: BALANCE | K6: WITHDRAWAL | L6: TOTAL
A7: 1 | B7: ART THORN | C7: M | D7: FOUNDER | E7: 45149 | G7: 4013.3175 | H7: 10.67 | I7: =G7*0.83% -> 33.310535 | J7: =G7+H7+I7 -> 4057.298 | L7: =J7-K7 -> 4057.298
A8: 2 | B8: PECH PISEY | C8: M | D8: FOUNDER | E8: 45173 | G8: 6290.0419 | H8: 50 | I8: =G8*0.83% -> 52.207348 | J8: =G8+H8+I8 -> 6392.2493 | L8: =J8-K8 -> 6392.2493
A9: 3 | B9: HONG REAKSMEY | C9: M | D9: FOUNDER | E9: 45171 | G9: 6009.4931 | H9: 100 | I9: =G9*0.83% -> 49.878792 | J9: =G9+H9+I9 -> 6159.3718 | L9: =J9-K9 -> 6159.3718
A10: 4 | B10: SIN PUTHEARY | C10: F | D10: FOUNDER | E10: 45171 | G10: 5540.5919 | H10: 37.94 | I10: =G10*0.83% -> 45.986913 | J10: =G10+H10+I10 -> 5624.5188 | L10: =J10-K10 -> 5624.5188
A11: 5 | B11: PAO VORN | C11: M | D11: FOUNDER | E11: 45087 | G11: 350.17619 | I11: =G11*0.83% -> 2.9064623 | J11: =G11+H11+I11 -> 353.08265 | L11: =J11-K11 -> 353.08265
A12: 6 | B12: SOR MORA | C12: M | D12: FOUNDER | E12: 45181 | G12: 2344.9838 | H12: 5.75 | I12: =G12*0.83% -> 19.463365 | J12: =G12+H12+I12 -> 2370.1971 | L12: =J12-K12 -> 2370.1971
A13: 7 | B13: NOP VY | C13: M | D13: FOUNDER | E13: 45179 | G13: 6010.5885 | H13: 34 | I13: =G13*0.83% -> 49.887885 | J13: =G13+H13+I13 -> 6094.4764 | L13: =J13-K13 -> 6094.4764
A14: 8 | B14: OU RITHTY | C14: M | D14: FOUNDER | E14: 45171 | G14: 5516.2398 | H14: 50 | I14: =G14*0.83% -> 45.784791 | J14: =G14+H14+I14 -> 5612.0246 | L14: =J14-K14 -> 5612.0246
A15: 9 | B15: SENG RITHY | C15: M | D15: MEMBER | E15: 45173 | F15: NOP VY | G15: 35.883656 | H15: 5 | I15: =G15*0.83% -> 0.29783435 | J15: =G15+H15+I15 -> 41.181491 | L15: =J15-K15 -> 41.181491
A16: 10 | B16: OU TEP PHALLIN | C16: F | D16: MEMBER | E16: 45171 | F16: OU RITHY | G16: 102.69631 | H16: 20 | I16: =G16*0.83% -> 0.85237939 | J16: =G16+H16+I16 -> 123.54869 | L16: =J16-K16 -> 123.54869
A17: 11 | B17: YIM BUNTHENG | C17: M | D17: MEMBER | E17: 45147 | F17: HONG REAKSMEY | G17: 51.180084 | I17: =G17*0.83% -> 0.4247947 | J17: =G17+H17+I17 -> 51.604879 | L17: =J17-K17 -> 51.604879
A18: 12 | B18: THENG SAVOEUN | C18: M | D18: MEMBER | E18: 45029 | F18: NOP VY | G18: 78.382634 | I18: =G18*0.83% -> 0.65057586 | J18: =G18+H18+I18 -> 79.03321 | L18: =J18-K18 -> 79.03321
A19: 13 | B19: UL VANN | C19: M | D19: MEMBER | E19: 36770 | F19: NOP VY | G19: 81.516275 | H19: 20 | I19: =G19*0.83% -> 0.67658508 | J19: =G19+H19+I19 -> 102.19286 | L19: =J19-K19 -> 102.19286
A20: 14 | B20: SIYONN SOTHEARITH | C20: M | D20: MEMBER | E20: 45079 | F20: HONG REAKSMEY | G20: 516.84313 | I20: =G20*0.83% -> 4.2897979 | J20: =G20+H20+I20 -> 521.13292 | L20: =J20-K20 -> 521.13292
A21: 15 | B21: YEAN REAKSMEY | C21: M | D21: MEMBER | E21: 45174 | F21: PECH PISEY | G21: 51.76799 | H21: 15 | I21: =G21*0.83% -> 0.42967432 | J21: =G21+H21+I21 -> 67.197664 | L21: =J21-K21 -> 67.197664
A22: 16 | B22: SON PENH | C22: M | D22: MEMBER | E22: 45170 | F22: PECH PISEY | G22: 123.53463 | H22: 40 | I22: =G22*0.83% -> 1.0253374 | J22: =G22+H22+I22 -> 164.55996 | L22: =J22-K22 -> 164.55996
A23: 17 | B23: SAM SOMONY | C23: M | D23: MEMBER | E23: 45171 | F23: NOP VY | G23: 392.00211 | H23: 425 | I23: =G23*0.83% -> 3.2536175 | J23: =G23+H23+I23 -> 820.25573 | L23: =J23-K23 -> 820.25573
A24: 18 | B24: KOY MAQUIS | C24: M | D24: MEMBER | E24: 45173 | F24: HONG REAKSMEY | G24: 66.728991 | H24: 20 | I24: =G24*0.83% -> 0.55385062 | J24: =G24+H24+I24 -> 87.282841 | L24: =J24-K24 -> 87.282841
A25: 19 | B25: LY MALIN | C25: F | D25: MEMBER | E25: 45171 | F25: OU RITHY | G25: 164.72596 | H25: 30 | I25: =G25*0.83% -> 1.3672255 | J25: =G25+H25+I25 -> 196.09319 | L25: =J25-K25 -> 196.09319
A26: 20 | B26: VAN BUNNA | C26: M | D26: MEMBER | E26: 45171 | F26: PECH PISEY | G26: 51.514139 | H26: 20 | I26: =G26*0.83% -> 0.42756735 | J26: =G26+H26+I26 -> 71.941706 | L26: =J26-K26 -> 71.941706
A27: 21 | B27: CHAN THEARA | C27: F | D27: MEMBER | E27: 45175 | F27: HONG REAKSMEY | G27: 5.2109732 | H27: 30 | I27: =G27*0.83% -> 0.043251078 | J27: =G27+H27+I27 -> 35.254224 | L27: =J27-K27 -> 35.254224
A28: 22 | B28: LONG BORIN | C28: F | D28: MEMBER | E28: 45140 | F28: NOP VY | G28: 107.78377 | I28: =G28*0.83% -> 0.89460526 | J28: =G28+H28+I28 -> 108.67837 | L28: =J28-K28 -> 108.67837
A29: 23 | B29: SOEUNG SAROEUN | C29: M | D29: MEMBER | E29: 45171 | F29: NOP VY | G29: 77.308463 | H29: 50 | I29: =G29*0.83% -> 0.64166024 | J29: =G29+H29+I29 -> 127.95012 | L29: =J29-K29 -> 127.95012
A30: 24 | B30: TUY SYTHIENG | C30: M | D30: MEMBER | E30: 45146 | F30: OU RITHY | G30: 202.08881 | I30: =G30*0.83% -> 1.6773371 | J30: =G30+H30+I30 -> 203.76614 | L30: =J30-K30 -> 203.76614
A31: 25 | B31: CHHEOUNG VEASNA | C31: M | D31: MEMBER | E31: 45174 | F31: SAM SOMONY | G31: 213.50741 | H31: 100 | I31: =G31*0.83% -> 1.7721115 | J31: =G31+H31+I31 -> 315.27952 | L31: =J31-K31 -> 315.27952
A32: 26 | B32: OM MANITH | C32: M | D32: MEMBER | E32: 45059 | F32: OU RITHY | G32: 20.502145 | I32: =G32*0.83% -> 0.1701678 | J32: =G32+H32+I32 -> 20.672313 | L32: =J32-K32 -> 20.672313
A33: 27 | B33: IM SOTHY | C33: M | D33: MEMBER | E33: 45060 | F33: PECH PISEY | G33: 30.753217 | I33: =G33*0.83% -> 0.2552517 | J33: =G33+H33+I33 -> 31.008469 | L33: =J33-K33 -> 31.008469
A34: 28 | B34: PA CHANROEUN | C34: M | D34: MEMBER | E34: 45085 | F34: NOP VY | G34: 201.66 | I34: =G34*0.83% -> 1.673778 | J34: =G34+H34+I34 -> 203.33378 | L34: =J34-K34 -> 203.33378
A35: 29 | B35: HENG SOCHEA | C35: F | D35: MEMBER | E35: 45171 | F35: OU RITHY | G35: 5 | J35: =G35+H35+I35 -> 5 | L35: =J35-K35 -> 5
A36: 30 | B36: TUM SOKRAKSA | C36: F | D36: MEMBER | E36: 45171 | F36: SIN PUTHEARY | G36: 50 | J36: =G36+H36+I36 -> 50 | L36: =J36-K36 -> 50
A37: 31 | B37: SDEUNG PHEARONG | D37: MEMBER | E37: 45173 | G37: 5 | J37: =G37+H37+I37 -> 5 | L37: =J37-K37 -> 5
G39: =SUM(G7:G37) -> 38711.023 | H39: =SUM(H7:H37) -> 1063.36 | I39: =SUM(I7:I37) -> 320.80349 | J39: =SUM(J7:J37) -> 40095.187 | K39: =SUM(K7:K37) -> 0 | L39: =SUM(L7:L37) -> 40095.187

Sheet Saving Monthly Oct-23
A1: SANSAM SAVING GROUP
A2: SAVING FROM 5USD PER MONTH BY GETTING INTEREST 10% PER YEAR
A3: SAVING DEPOSIT FROM 1ST - 10TH EVERY MONTH
A4: ACCESSIBLE LOAN ON 15TH EACH MONTH
A5: SAVING IN OCTOBER 2023
A6: NO | B6: NAME | C6: SEX | D6: ROLE | E6: SAVING DATE | F6: TEAM LEADER | G6: CAPITAL | H6: SAVING | I6: INTEREST | J6: BALANCE | K6: WITHDRAWAL | L6: TOTAL
A7: 1 | B7: ART THORN | C7: M | D7: FOUNDER | E7: 45149 | G7: 4057.298 | I7: =G7*0.83% -> 33.675574 | J7: =G7+H7+I7 -> 4090.9736 | L7: =J7-K7 -> 4090.9736
A8: 2 | B8: PECH PISEY | C8: M | D8: FOUNDER | E8: 45209 | G8: 6392.2493 | H8: 20 | I8: =G8*0.83% -> 53.055669 | J8: =G8+H8+I8 -> 6465.305 | L8: =J8-K8 -> 6465.305
A9: 3 | B9: HONG REAKSMEY | C9: M | D9: FOUNDER | E9: 45208 | G9: 6159.3718 | H9: 50 | I9: =G9*0.83% -> 51.122786 | J9: =G9+H9+I9 -> 6260.4946 | L9: =J9-K9 -> 6260.4946
A10: 4 | B10: SIN PUTHEARY | C10: F | D10: FOUNDER | E10: 45171 | G10: 5624.5188 | I10: =G10*0.83% -> 46.683506 | J10: =G10+H10+I10 -> 5671.2023 | L10: =J10-K10 -> 5671.2023
A11: 5 | B11: PAO VORN | C11: M | D11: FOUNDER | E11: 45208 | G11: 353.08265 | H11: 50 | I11: =G11*0.83% -> 2.930586 | J11: =G11+H11+I11 -> 406.01323 | L11: =J11-K11 -> 406.01323
A12: 6 | B12: SOR MORA | C12: M | D12: FOUNDER | E12: 45181 | G12: 2370.1971 | I12: =G12*0.83% -> 19.672636 | J12: =G12+H12+I12 -> 2389.8698 | L12: =J12-K12 -> 2389.8698
A13: 7 | B13: NOP VY | C13: M | D13: FOUNDER | E13: 45179 | G13: 6094.4764 | H13: 37.32 | I13: =G13*0.83% -> 50.584154 | J13: =G13+H13+I13 -> 6182.3805 | L13: =J13-K13 -> 6182.3805
A14: 8 | B14: OU RITHTY | C14: M | D14: FOUNDER | E14: 45201 | G14: 5612.0246 | H14: 50 | I14: =G14*0.83% -> 46.579804 | J14: =G14+H14+I14 -> 5708.6044 | L14: =J14-K14 -> 5708.6044
A15: 9 | B15: SENG RITHY | C15: M | D15: MEMBER | E15: 45201 | F15: NOP VY | G15: 41.181491 | H15: 5 | I15: =G15*0.83% -> 0.34180637 | J15: =G15+H15+I15 -> 46.523297 | L15: =J15-K15 -> 46.523297
A16: 10 | B16: OU TEP PHALLIN | C16: F | D16: MEMBER | E16: 45203 | F16: OU RITHY | G16: 123.54869 | H16: 20 | I16: =G16*0.83% -> 1.0254541 | J16: =G16+H16+I16 -> 144.57415 | L16: =J16-K16 -> 144.57415
A17: 11 | B17: YIM BUNTHENG | C17: M | D17: MEMBER | E17: 45201 | F17: HONG REAKSMEY | G17: 51.604879 | H17: 10 | I17: =G17*0.83% -> 0.42832049 | J17: =G17+H17+I17 -> 62.033199 | L17: =J17-K17 -> 62.033199
A18: 12 | B18: THENG SAVOEUN | C18: M | D18: MEMBER | E18: 45029 | F18: NOP VY | G18: 79.03321 | I18: =G18*0.83% -> 0.65597564 | J18: =G18+H18+I18 -> 79.689185 | L18: =J18-K18 -> 79.689185
A19: 13 | B19: UL VANN | C19: M | D19: MEMBER | E19: 45209 | F19: NOP VY | G19: 102.19286 | H19: 20 | I19: =G19*0.83% -> 0.84820074 | J19: =G19+H19+I19 -> 123.04106 | L19: =J19-K19 -> 123.04106
A20: 14 | B20: SIYONN SOTHEARITH | C20: M | D20: MEMBER | E20: 45079 | F20: HONG REAKSMEY | G20: 521.13292 | I20: =G20*0.83% -> 4.3254033 | J20: =G20+H20+I20 -> 525.45833 | L20: =J20-K20 -> 525.45833
A21: 15 | B21: YEAN REAKSMEY | C21: M | D21: MEMBER | E21: 45201 | F21: PECH PISEY | G21: 67.197664 | H21: 25 | I21: =G21*0.83% -> 0.55774061 | J21: =G21+H21+I21 -> 92.755405 | L21: =J21-K21 -> 92.755405
A22: 16 | B22: SON PENH | C22: M | D22: MEMBER | E22: 45170 | F22: PECH PISEY | G22: 164.55996 | I22: =G22*0.83% -> 1.3658477 | J22: =G22+H22+I22 -> 165.92581 | L22: =J22-K22 -> 165.92581
A23: 17 | B23: SAM SOMONY | C23: M | D23: MEMBER | E23: 45205 | F23: NOP VY | G23: 820.25573 | H23: 25 | I23: =G23*0.83% -> 6.8081225 | J23: =G23+H23+I23 -> 852.06385 | L23: =J23-K23 -> 852.06385
A24: 18 | B24: KOY MAQUIS | C24: M | D24: MEMBER | E24: 45201 | F24: HONG REAKSMEY | G24: 87.282841 | H24: 20 | I24: =G24*0.83% -> 0.72444758 | J24: =G24+H24+I24 -> 108.00729 | L24: =J24-K24 -> 108.00729
A25: 19 | B25: LY MALIN | C25: F | D25: MEMBER | E25: 45201 | F25: OU RITHY | G25: 196.09319 | H25: 30 | I25: =G25*0.83% -> 1.6275735 | J25: =G25+H25+I25 -> 227.72076 | L25: =J25-K25 -> 227.72076
A26: 20 | B26: VAN BUNNA | C26: M | D26: MEMBER | E26: 45171 | F26: PECH PISEY | G26: 71.941706 | H26: 5 | I26: =G26*0.83% -> 0.59711616 | J26: =G26+H26+I26 -> 77.538823 | L26: =J26-K26 -> 77.538823
A27: 21 | B27: CHAN THEARA | C27: F | D27: MEMBER | E27: 45211 | F27: HONG REAKSMEY | G27: 35.254224 | H27: 5 | I27: =G27*0.83% -> 0.29261006 | J27: =G27+H27+I27 -> 40.546834 | L27: =J27-K27 -> 40.546834
A28: 22 | B28: LONG BORIN | C28: F | D28: MEMBER | E28: 45140 | F28: NOP VY | G28: 108.67837 | I28: =G28*0.83% -> 0.90203048 | J28: =G28+H28+I28 -> 109.5804 | L28: =J28-K28 -> 109.5804
A29: 23 | B29: SOEUNG SAROEUN | C29: M | D29: MEMBER | E29: 45171 | F29: NOP VY | G29: 127.95012 | I29: =G29*0.83% -> 1.061986 | J29: =G29+H29+I29 -> 129.01211 | L29: =J29-K29 -> 129.01211
A30: 24 | B30: TUY SYTHIENG | C30: M | D30: MEMBER | E30: 45209 | F30: OU RITHY | G30: 203.76614 | H30: 100 | I30: =G30*0.83% -> 1.691259 | J30: =G30+H30+I30 -> 305.4574 | L30: =J30-K30 -> 305.4574
A31: 25 | B31: CHHEOUNG VEASNA | C31: M | D31: MEMBER | E31: 45201 | F31: SAM SOMONY | G31: 315.27952 | H31: 100 | I31: =G31*0.83% -> 2.6168201 | J31: =G31+H31+I31 -> 417.89634 | L31: =J31-K31 -> 417.89634
A32: 26 | B32: OM MANITH | C32: M | D32: MEMBER | E32: 45059 | F32: OU RITHY | G32: 20.672313 | I32: =G32*0.83% -> 0.17158019 | J32: =G32+H32+I32 -> 20.843893 | L32: =J32-K32 -> 20.843893
A33: 27 | B33: IM SOTHY | C33: M | D33: MEMBER | E33: 45209 | F33: PECH PISEY | G33: 31.008469 | H33: 30 | I33: =G33*0.83% -> 0.25737029 | J33: =G33+H33+I33 -> 61.265839 | L33: =J33-K33 -> 61.265839
A34: 28 | B34: PA CHANROEUN | C34: M | D34: MEMBER | E34: 45085 | F34: NOP VY | G34: 203.33378 | I34: =G34*0.83% -> 1.6876704 | J34: =G34+H34+I34 -> 205.02145 | L34: =J34-K34 -> 205.02145
A35: 29 | B35: HENG SOCHEA | C35: F | D35: MEMBER | E35: 45201 | F35: OU RITHY | G35: 5 | H35: 10 | I35: =G35*0.83% -> 0.0415 | J35: =G35+H35+I35 -> 15.0415 | L35: =J35-K35 -> 15.0415
A36: 30 | B36: TUM SOKRAKSA | C36: F | D36: MEMBER | E36: 45201 | F36: SIN PUTHEARY | G36: 50 | H36: 50 | I36: =G36*0.83% -> 0.415 | J36: =G36+H36+I36 -> 100.415 | L36: =J36-K36 -> 100.415
A37: 31 | B37: SDEUNG PHEARONG | D37: MEMBER | E37: 45173 | G37: 5 | I37: =G37*0.83% -> 0.0415 | J37: =G37+H37+I37 -> 5.0415 | L37: =J37-K37 -> 5.0415
A38: 32 | B38: TY SAMPHORS VICHEKA | D38: MEMBER | E38: 45201 | G38: 15 | J38: =G38+H38+I38 -> 15 | L38: =J38-K38 -> 15
A39: 33 | B39: CHUM CHANDARIN | D39: MEMBER | E39: 45201 | G39: 100 | J39: =G39+H39+I39 -> 100 | L39: =J39-K39 -> 100
A40: 34 | B40: PEANH KOEUN | D40: MEMBER | E40: 45201 | G40: 10 | J40: =G40+H40+I40 -> 10 | L40: =J40-K40 -> 10
A41: 35 | B41: YANG SOPHORN | D41: MEMBER | E41: 45201 | G41: 20 | J41: =G41+H41+I41 -> 20 | L41: =J41-K41 -> 20
A42: 36 | B42: RO VANNAK | D42: MEMBER | E42: 45201 | G42: 10 | J42: =G42+H42+I42 -> 10 | L42: =J42-K42 -> 10
A43: 37 | B43: SENG VANLY | D43: MEMBER | E43: 45202 | G43: 25 | J43: =G43+H43+I43 -> 25 | L43: =J43-K43 -> 25
A44: 38 | B44: YORNG SOKHAI | D44: MEMBER | E44: 45203 | G44: 50 | J44: =G44+H44+I44 -> 50 | L44: =J44-K44 -> 50
A45: 39 | B45: MENGHAK VICHHAY | D45: MEMBER | E45: 45209 | G45: 10.5 | J45: =G45+H45+I45 -> 10.5 | L45: =J45-K45 -> 10.5
A46: 40 | B46: SIM SUNNARY | D46: MEMBER | E46: 45216 | G46: 10 | J46: =G46+H46+I46 -> 10 | L46: =J46-K46 -> 10
G48: =SUM(G7:G46) -> 40345.687 | H48: =SUM(H7:H46) -> 662.32 | I48: =SUM(I7:I46) -> 332.79005 | J48: =SUM(J7:J46) -> 41340.797 | K48: =SUM(K7:K46) -> 0 | L48: =SUM(L7:L46) -> 41340.797

Sheet Saving Monthly Nov-23
A1: SANSAM SAVING GROUP
A2: SAVING FROM 5USD PER MONTH BY GETTING INTEREST 10% PER YEAR
A3: SAVING DEPOSIT FROM 1ST - 10TH EVERY MONTH
A4: ACCESSIBLE LOAN ON 15TH EACH MONTH
A5: SAVING IN NOVEMBER 2023
A6: NO | B6: NAME | C6: SEX | D6: ROLE | E6: SAVING DATE | F6: TEAM LEADER | G6: CAPITAL | H6: SAVING | I6: INTEREST | J6: BALANCE | K6: WITHDRAWAL | L6: TOTAL
A7: 1 | B7: ART THORN | C7: M | D7: FOUNDER | E7: 45235 | G7: 4090.9736 | H7: 22.14 | I7: =G7*0.83% -> 33.955081 | J7: =G7+H7+I7 -> 4147.0687 | L7: =J7-K7 -> 4147.0687
A8: 2 | B8: PECH PISEY | C8: M | D8: FOUNDER | E8: 45240 | G8: 6465.305 | H8: 50 | I8: =G8*0.83% -> 53.662031 | J8: =G8+H8+I8 -> 6568.967 | L8: =J8-K8 -> 6568.967
A9: 3 | B9: HONG REAKSMEY | C9: M | D9: FOUNDER | E9: 45235 | G9: 6260.4946 | H9: 100 | I9: =G9*0.83% -> 51.962105 | J9: =G9+H9+I9 -> 6412.4567 | L9: =J9-K9 -> 6412.4567
A10: 4 | B10: SIN PUTHEARY | C10: F | D10: FOUNDER | E10: 45171 | G10: 5671.2023 | I10: =G10*0.83% -> 47.070979 | J10: =G10+H10+I10 -> 5718.2733 | L10: =J10-K10 -> 5718.2733
A11: 5 | B11: PAO VORN | C11: M | D11: FOUNDER | E11: 45239 | G11: 406.01323 | H11: 20 | I11: =G11*0.83% -> 3.3699098 | J11: =G11+H11+I11 -> 429.38314 | L11: =J11-K11 -> 429.38314
A12: 6 | B12: SOR MORA | C12: M | D12: FOUNDER | E12: 45236 | G12: 2389.8698 | H12: 8.05 | I12: =G12*0.83% -> 19.835919 | J12: =G12+H12+I12 -> 2417.7557 | L12: =J12-K12 -> 2417.7557
A13: 7 | B13: NOP VY | C13: M | D13: FOUNDER | E13: 45245 | G13: 6182.3805 | H13: 40.64 | I13: =G13*0.83% -> 51.313758 | J13: =G13+H13+I13 -> 6274.3343 | L13: =J13-K13 -> 6274.3343
A14: 8 | B14: OU RITHTY | C14: M | D14: FOUNDER | E14: 45235 | G14: 5708.6044 | H14: 100 | I14: =G14*0.83% -> 47.381417 | J14: =G14+H14+I14 -> 5855.9858 | L14: =J14-K14 -> 5855.9858
A15: 9 | B15: SENG RITHY | C15: M | D15: MEMBER | E15: 45236 | F15: NOP VY | G15: 46.523297 | H15: 5 | I15: =G15*0.83% -> 0.38614337 | J15: =G15+H15+I15 -> 51.90944 | L15: =J15-K15 -> 51.90944
A16: 10 | B16: OU TEP PHALLIN | C16: F | D16: MEMBER | E16: 45233 | F16: OU RITHY | G16: 144.57415 | H16: 20 | I16: =G16*0.83% -> 1.1999654 | J16: =G16+H16+I16 -> 165.77411 | L16: =J16-K16 -> 165.77411
A17: 11 | B17: YIM BUNTHENG | C17: M | D17: MEMBER | E17: 45235 | F17: HONG REAKSMEY | G17: 62.033199 | H17: 10 | I17: =G17*0.83% -> 0.51487555 | J17: =G17+H17+I17 -> 72.548075 | L17: =J17-K17 -> 72.548075
A18: 12 | B18: THENG SAVOEUN | C18: M | D18: MEMBER | E18: 45029 | F18: NOP VY | G18: 79.689185 | I18: =G18*0.83% -> 0.66142024 | J18: =G18+H18+I18 -> 80.350605 | L18: =J18-K18 -> 80.350605
A19: 13 | B19: UL VANN | C19: M | D19: MEMBER | E19: 45240 | F19: NOP VY | G19: 123.04106 | H19: 20 | I19: =G19*0.83% -> 1.0212408 | J19: =G19+H19+I19 -> 144.0623 | L19: =J19-K19 -> 144.0623
A20: 14 | B20: SIYONN SOTHEARITH | C20: M | D20: MEMBER | E20: 45235 | F20: HONG REAKSMEY | G20: 525.45833 | H20: 100 | I20: =G20*0.83% -> 4.3613041 | J20: =G20+H20+I20 -> 629.81963 | L20: =J20-K20 -> 629.81963
A21: 15 | B21: YEAN REAKSMEY | C21: M | D21: MEMBER | E21: 45201 | F21: PECH PISEY | G21: 92.755405 | I21: =G21*0.83% -> 0.76986986 | J21: =G21+H21+I21 -> 93.525275 | L21: =J21-K21 -> 93.525275
A22: 16 | B22: SON PENH | C22: M | D22: MEMBER | E22: 45170 | F22: PECH PISEY | G22: 165.92581 | I22: =G22*0.83% -> 1.3771842 | J22: =G22+H22+I22 -> 167.30299 | L22: =J22-K22 -> 167.30299
A23: 17 | B23: SAM SOMONY | C23: M | D23: MEMBER | E23: 45235 | F23: NOP VY | G23: 852.06385 | H23: 25 | I23: =G23*0.83% -> 7.07213 | J23: =G23+H23+I23 -> 884.13598 | L23: =J23-K23 -> 884.13598
A24: 18 | B24: KOY MAQUIS | C24: M | D24: MEMBER | E24: 45234 | F24: HONG REAKSMEY | G24: 108.00729 | H24: 20 | I24: =G24*0.83% -> 0.8964605 | J24: =G24+H24+I24 -> 128.90375 | L24: =J24-K24 -> 128.90375
A25: 19 | B25: LY MALIN | C25: F | D25: MEMBER | E25: 45235 | F25: OU RITHY | G25: 227.72076 | H25: 30 | I25: =G25*0.83% -> 1.8900823 | J25: =G25+H25+I25 -> 259.61084 | L25: =J25-K25 -> 259.61084
A26: 20 | B26: VAN BUNNA | C26: M | D26: MEMBER | E26: 45240 | F26: PECH PISEY | G26: 77.538823 | H26: 10 | I26: =G26*0.83% -> 0.64357223 | J26: =G26+H26+I26 -> 88.182395 | L26: =J26-K26 -> 88.182395
A27: 21 | B27: CHAN THEARA | C27: F | D27: MEMBER | E27: 45242 | F27: HONG REAKSMEY | G27: 40.546834 | H27: 10 | I27: =G27*0.83% -> 0.33653873 | J27: =G27+H27+I27 -> 50.883373 | L27: =J27-K27 -> 50.883373
A28: 22 | B28: LONG BORIN | C28: F | D28: MEMBER | E28: 45140 | F28: NOP VY | G28: 109.5804 | I28: =G28*0.83% -> 0.90951733 | J28: =G28+H28+I28 -> 110.48992 | L28: =J28-K28 -> 110.48992
A29: 23 | B29: SOEUNG SAROEUN | C29: M | D29: MEMBER | E29: 45235 | F29: NOP VY | G29: 129.01211 | I29: =G29*0.83% -> 1.0708005 | J29: =G29+H29+I29 -> 130.08291 | L29: =J29-K29 -> 130.08291
A30: 24 | B30: TUY SYTHIENG | C30: M | D30: MEMBER | E30: 45238 | F30: OU RITHY | G30: 305.4574 | H30: 100 | I30: =G30*0.83% -> 2.5352964 | J30: =G30+H30+I30 -> 407.9927 | L30: =J30-K30 -> 407.9927
A31: 25 | B31: CHHEOUNG VEASNA | C31: M | D31: MEMBER | E31: 45201 | F31: SAM SOMONY | G31: 417.89634 | I31: =G31*0.83% -> 3.4685397 | J31: =G31+H31+I31 -> 421.36488 | L31: =J31-K31 -> 421.36488
A32: 26 | B32: OM MANITH | C32: M | D32: MEMBER | E32: 45059 | F32: OU RITHY | G32: 20.843893 | I32: =G32*0.83% -> 0.17300431 | J32: =G32+H32+I32 -> 21.016897 | L32: =J32-K32 -> 21.016897
A33: 27 | B33: IM SOTHY | C33: M | D33: MEMBER | E33: 45209 | F33: PECH PISEY | G33: 61.265839 | I33: =G33*0.83% -> 0.50850647 | J33: =G33+H33+I33 -> 61.774346 | L33: =J33-K33 -> 61.774346
A34: 28 | B34: PA CHANROEUN | C34: M | D34: MEMBER | E34: 45085 | F34: NOP VY | G34: 205.02145 | I34: =G34*0.83% -> 1.701678 | J34: =G34+H34+I34 -> 206.72313 | L34: =J34-K34 -> 206.72313
A35: 29 | B35: HENG SOCHEA | C35: F | D35: MEMBER | E35: 45235 | F35: OU RITHY | G35: 15.0415 | H35: 10 | I35: =G35*0.83% -> 0.12484445 | J35: =G35+H35+I35 -> 25.166344 | L35: =J35-K35 -> 25.166344
A36: 30 | B36: TUM SOKRAKSA | C36: F | D36: MEMBER | E36: 45235 | F36: SIN PUTHEARY | G36: 100.415 | H36: 900 | I36: =G36*0.83% -> 0.8334445 | J36: =G36+H36+I36 -> 1001.2484 | L36: =J36-K36 -> 1001.2484
A37: 31 | B37: SDEUNG PHEARONG | D37: MEMBER | E37: 45235 | G37: 5.0415 | H37: 5 | I37: =G37*0.83% -> 0.04184445 | J37: =G37+H37+I37 -> 10.083344 | L37: =J37-K37 -> 10.083344
A38: 32 | B38: TY SAMPHORS VICHEKA | D38: MEMBER | E38: 45235 | G38: 15 | H38: 15 | I38: =G38*0.83% -> 0.1245 | J38: =G38+H38+I38 -> 30.1245 | L38: =J38-K38 -> 30.1245
A39: 33 | B39: CHUM CHANDARIN | D39: MEMBER | E39: 45233 | G39: 100 | H39: 10 | I39: =G39*0.83% -> 0.83 | J39: =G39+H39+I39 -> 110.83 | L39: =J39-K39 -> 110.83
A40: 34 | B40: PEANH KOEUN | D40: MEMBER | E40: 45234 | G40: 10 | H40: 10 | I40: =G40*0.83% -> 0.083 | J40: =G40+H40+I40 -> 20.083 | L40: =J40-K40 -> 20.083
A41: 35 | B41: YANG SOPHORN | D41: MEMBER | E41: 45234 | G41: 20 | H41: 20 | I41: =G41*0.83% -> 0.166 | J41: =G41+H41+I41 -> 40.166 | L41: =J41-K41 -> 40.166
A42: 36 | B42: RO VANNAK | D42: MEMBER | E42: 45233 | G42: 10 | H42: 10 | I42: =G42*0.83% -> 0.083 | J42: =G42+H42+I42 -> 20.083 | L42: =J42-K42 -> 20.083
A43: 37 | B43: SENG VANLY | D43: MEMBER | E43: 45232 | G43: 25 | H43: 25 | I43: =G43*0.83% -> 0.2075 | J43: =G43+H43+I43 -> 50.2075 | L43: =J43-K43 -> 50.2075
A44: 38 | B44: YORNG SOKHAI | D44: MEMBER | E44: 45237 | G44: 50 | H44: 50 | I44: =G44*0.83% -> 0.415 | J44: =G44+H44+I44 -> 100.415 | L44: =J44-K44 -> 100.415
A45: 39 | B45: MENGHAK VICHHAY | D45: MEMBER | E45: 45238 | G45: 10.5 | H45: 10 | I45: =G45*0.83% -> 0.08715 | J45: =G45+H45+I45 -> 20.58715 | L45: =J45-K45 -> 20.58715
A46: 40 | B46: SIM SUNNARY | D46: MEMBER | E46: 45245 | G46: 10 | H46: 10 | I46: =G46*0.83% -> 0.083 | J46: =G46+H46+I46 -> 20.083 | L46: =J46-K46 -> 20.083
G48: =SUM(G7:G46) -> 41340.797 | H48: =SUM(H7:H46) -> 1765.83 | I48: =SUM(I7:I46) -> 343.12861 | J48: =SUM(J7:J46) -> 43449.755 | K48: =SUM(K7:K46) -> 0 | L48: =SUM(L7:L46) -> 43449.755

Sheet Saving Monthly Dec-23
A1: SANSAM SAVING GROUP
A2: SAVING FROM 5USD PER MONTH BY GETTING INTEREST 10% PER YEAR
A3: SAVING DEPOSIT FROM 1ST - 10TH EVERY MONTH
A4: ACCESSIBLE LOAN ON 15TH EACH MONTH
A5: SAVING IN DECEMBER 2023
A6: NO | B6: NAME | C6: SEX | D6: ROLE | E6: SAVING DATE | F6: TEAM LEADER | G6: CAPITAL | H6: SAVING | I6: INTEREST | J6: BALANCE | K6: WITHDRAWAL | L6: TOTAL
A7: 1 | B7: ART THORN | C7: M | D7: FOUNDER | E7: 45235 | G7: 4147.0687 | H7: 22.87 | I7: =G7*0.83% -> 34.42067 | J7: =G7+H7+I7 -> 4204.3594 | L7: =J7-K7 -> 4204.3594
A8: 2 | B8: PECH PISEY | C8: M | D8: FOUNDER | E8: 45240 | G8: 6568.967 | H8: 30 | I8: =G8*0.83% -> 54.522426 | J8: =G8+H8+I8 -> 6653.4894 | L8: =J8-K8 -> 6653.4894
A9: 3 | B9: HONG REAKSMEY | C9: M | D9: FOUNDER | E9: 45270 | G9: 6412.4567 | H9: 50 | I9: =G9*0.83% -> 53.223391 | J9: =G9+H9+I9 -> 6515.6801 | L9: =J9-K9 -> 6515.6801
A10: 4 | B10: SIN PUTHEARY | C10: F | D10: FOUNDER | E10: 45171 | G10: 5718.2733 | I10: =G10*0.83% -> 47.461668 | J10: =G10+H10+I10 -> 5765.735 | L10: =J10-K10 -> 5765.735
A11: 5 | B11: PAO VORN | C11: M | D11: FOUNDER | E11: 45239 | G11: 429.38314 | I11: =G11*0.83% -> 3.5638801 | J11: =G11+H11+I11 -> 432.94702 | L11: =J11-K11 -> 432.94702
A12: 6 | B12: SOR MORA | C12: M | D12: FOUNDER | E12: 45270 | G12: 2417.7557 | H12: 5 | I12: =G12*0.83% -> 20.067372 | J12: =G12+H12+I12 -> 2442.823 | L12: =J12-K12 -> 2442.823
A13: 7 | B13: NOP VY | C13: M | D13: FOUNDER | E13: 45245 | G13: 6274.3343 | H13: 43.96 | I13: =G13*0.83% -> 52.076975 | J13: =G13+H13+I13 -> 6370.3713 | L13: =J13-K13 -> 6370.3713
A14: 8 | B14: OU RITHTY | C14: M | D14: FOUNDER | E14: 45265 | G14: 5855.9858 | H14: 50 | I14: =G14*0.83% -> 48.604682 | J14: =G14+H14+I14 -> 5954.5905 | L14: =J14-K14 -> 5954.5905
A15: 9 | B15: SENG RITHY | C15: M | D15: MEMBER | E15: 45266 | F15: NOP VY | G15: 51.90944 | H15: 5 | I15: =G15*0.83% -> 0.43084836 | J15: =G15+H15+I15 -> 57.340289 | L15: =J15-K15 -> 57.340289
A16: 10 | B16: OU TEP PHALLIN | C16: F | D16: MEMBER | E16: 45233 | F16: OU RITHY | G16: 165.77411 | I16: =G16*0.83% -> 1.3759251 | J16: =G16+H16+I16 -> 167.15004 | L16: =J16-K16 -> 167.15004
A17: 11 | B17: YIM BUNTHENG | C17: M | D17: MEMBER | E17: 45266 | F17: HONG REAKSMEY | G17: 72.548075 | H17: 10 | I17: =G17*0.83% -> 0.60214902 | J17: =G17+H17+I17 -> 83.150224 | L17: =J17-K17 -> 83.150224
A18: 12 | B18: THENG SAVOEUN | C18: M | D18: MEMBER | E18: 45029 | F18: NOP VY | G18: 80.350605 | I18: =G18*0.83% -> 0.66691002 | J18: =G18+H18+I18 -> 81.017515 | L18: =J18-K18 -> 81.017515
A19: 13 | B19: UL VANN | C19: M | D19: MEMBER | E19: 45240 | F19: NOP VY | G19: 144.0623 | I19: =G19*0.83% -> 1.1957171 | J19: =G19+H19+I19 -> 145.25802 | L19: =J19-K19 -> 145.25802
A20: 14 | B20: SIYONN SOTHEARITH | C20: M | D20: MEMBER | E20: 45264 | F20: HONG REAKSMEY | G20: 629.81963 | H20: 100 | I20: =G20*0.83% -> 5.2275029 | J20: =G20+H20+I20 -> 735.04713 | L20: =J20-K20 -> 735.04713
A21: 15 | B21: YEAN REAKSMEY | C21: M | D21: MEMBER | E21: 45201 | F21: PECH PISEY | G21: 93.525275 | I21: =G21*0.83% -> 0.77625978 | J21: =G21+H21+I21 -> 94.301535 | L21: =J21-K21 -> 94.301535
A22: 16 | B22: SON PENH | C22: M | D22: MEMBER | E22: 45170 | F22: PECH PISEY | G22: 167.30299 | I22: =G22*0.83% -> 1.3886149 | J22: =G22+H22+I22 -> 168.69161 | L22: =J22-K22 -> 168.69161
A23: 17 | B23: SAM SOMONY | C23: M | D23: MEMBER | E23: 45263 | F23: NOP VY | G23: 884.13598 | H23: 25 | I23: =G23*0.83% -> 7.3383286 | J23: =G23+H23+I23 -> 916.47431 | L23: =J23-K23 -> 916.47431
A24: 18 | B24: KOY MAQUIS | C24: M | D24: MEMBER | E24: 45263 | F24: HONG REAKSMEY | G24: 128.90375 | H24: 15 | I24: =G24*0.83% -> 1.0699011 | J24: =G24+H24+I24 -> 144.97365 | L24: =J24-K24 -> 144.97365
A25: 19 | B25: LY MALIN | C25: F | D25: MEMBER | E25: 45235 | F25: OU RITHY | G25: 259.61084 | H25: 40 | I25: =G25*0.83% -> 2.15477 | J25: =G25+H25+I25 -> 301.76561 | L25: =J25-K25 -> 301.76561
A26: 20 | B26: VAN BUNNA | C26: M | D26: MEMBER | E26: 45240 | F26: PECH PISEY | G26: 88.182395 | I26: =G26*0.83% -> 0.73191388 | J26: =G26+H26+I26 -> 88.914309 | L26: =J26-K26 -> 88.914309
A27: 21 | B27: CHAN THEARA | C27: F | D27: MEMBER | E27: 45264 | F27: HONG REAKSMEY | G27: 50.883373 | H27: 5 | I27: =G27*0.83% -> 0.422332 | J27: =G27+H27+I27 -> 56.305705 | L27: =J27-K27 -> 56.305705
A28: 22 | B28: LONG BORIN | C28: F | D28: MEMBER | E28: 45140 | F28: NOP VY | G28: 110.48992 | I28: =G28*0.83% -> 0.91706633 | J28: =G28+H28+I28 -> 111.40699 | L28: =J28-K28 -> 111.40699
A29: 23 | B29: SOEUNG SAROEUN | C29: M | D29: MEMBER | E29: 45235 | F29: NOP VY | G29: 130.08291 | I29: =G29*0.83% -> 1.0796881 | J29: =G29+H29+I29 -> 131.1626 | L29: =J29-K29 -> 131.1626
A30: 24 | B30: TUY SYTHIENG | C30: M | D30: MEMBER | E30: 45238 | F30: OU RITHY | G30: 407.9927 | I30: =G30*0.83% -> 3.3863394 | J30: =G30+H30+I30 -> 411.37904 | L30: =J30-K30 -> 411.37904
A31: 25 | B31: CHHEOUNG VEASNA | C31: M | D31: MEMBER | E31: 45201 | F31: SAM SOMONY | G31: 421.36488 | I31: =G31*0.83% -> 3.4973285 | J31: =G31+H31+I31 -> 424.86221 | L31: =J31-K31 -> 424.86221
A32: 26 | B32: OM MANITH | C32: M | D32: MEMBER | E32: 45059 | F32: OU RITHY | G32: 21.016897 | I32: =G32*0.83% -> 0.17444025 | J32: =G32+H32+I32 -> 21.191337 | L32: =J32-K32 -> 21.191337
A33: 27 | B33: IM SOTHY | C33: M | D33: MEMBER | E33: 45209 | F33: PECH PISEY | G33: 61.774346 | I33: =G33*0.83% -> 0.51272707 | J33: =G33+H33+I33 -> 62.287073 | L33: =J33-K33 -> 62.287073
A34: 28 | B34: PA CHANROEUN | C34: M | D34: MEMBER | E34: 45085 | F34: NOP VY | G34: 206.72313 | I34: =G34*0.83% -> 1.7158019 | J34: =G34+H34+I34 -> 208.43893 | L34: =J34-K34 -> 208.43893
A35: 29 | B35: HENG SOCHEA | C35: F | D35: MEMBER | E35: 45235 | F35: OU RITHY | G35: 25.166344 | I35: =G35*0.83% -> 0.20888066 | J35: =G35+H35+I35 -> 25.375225 | L35: =J35-K35 -> 25.375225
A36: 30 | B36: TUM SOKRAKSA | C36: F | D36: MEMBER | E36: 45235 | F36: SIN PUTHEARY | G36: 1001.2484 | I36: =G36*0.83% -> 8.3103621 | J36: =G36+H36+I36 -> 1009.5588 | L36: =J36-K36 -> 1009.5588
A37: 31 | B37: SDEUNG PHEARONG | D37: MEMBER | E37: 45638 | G37: 10.083344 | H37: 5 | I37: =G37*0.83% -> 0.083691759 | J37: =G37+H37+I37 -> 15.167036 | L37: =J37-K37 -> 15.167036
A38: 32 | B38: TY SAMPHORS VICHEKA | D38: MEMBER | E38: 45265 | G38: 30.1245 | H38: 15 | I38: =G38*0.83% -> 0.25003335 | J38: =G38+H38+I38 -> 45.374533 | L38: =J38-K38 -> 45.374533
A39: 33 | B39: CHUM CHANDARIN | D39: MEMBER | E39: 45264 | G39: 110.83 | H39: 25 | I39: =G39*0.83% -> 0.919889 | J39: =G39+H39+I39 -> 136.74989 | L39: =J39-K39 -> 136.74989
A40: 34 | B40: PEANH KOEUN | D40: MEMBER | E40: 45264 | G40: 20.083 | H40: 10 | I40: =G40*0.83% -> 0.1666889 | J40: =G40+H40+I40 -> 30.249689 | L40: =J40-K40 -> 30.249689
A41: 35 | B41: YANG SOPHORN | D41: MEMBER | E41: 45266 | G41: 40.166 | H41: 20 | I41: =G41*0.83% -> 0.3333778 | J41: =G41+H41+I41 -> 60.499378 | L41: =J41-K41 -> 60.499378
A42: 36 | B42: RO VANNAK | D42: MEMBER | E42: 45266 | G42: 20.083 | H42: 10 | I42: =G42*0.83% -> 0.1666889 | J42: =G42+H42+I42 -> 30.249689 | L42: =J42-K42 -> 30.249689
A43: 37 | B43: SENG VANLY | D43: MEMBER | E43: 45264 | G43: 50.2075 | H43: 25 | I43: =G43*0.83% -> 0.41672225 | J43: =G43+H43+I43 -> 75.624222 | L43: =J43-K43 -> 75.624222
A44: 38 | B44: YORNG SOKHAI | D44: MEMBER | E44: 45237 | G44: 100.415 | I44: =G44*0.83% -> 0.8334445 | J44: =G44+H44+I44 -> 101.24844 | L44: =J44-K44 -> 101.24844
A45: 39 | B45: MENGHAK VICHHAY | D45: MEMBER | E45: 45270 | G45: 20.58715 | H45: 10 | I45: =G45*0.83% -> 0.17087335 | J45: =G45+H45+I45 -> 30.758023 | L45: =J45-K45 -> 30.758023
A46: 40 | B46: SIM SUNNARY | D46: MEMBER | E46: 45245 | G46: 20.083 | I46: =G46*0.83% -> 0.1666889 | J46: =G46+H46+I46 -> 20.249689 | L46: =J46-K46 -> 20.249689
G48: =SUM(G7:G46) -> 43449.755 | H48: =SUM(H7:H46) -> 521.83 | I48: =SUM(I7:I46) -> 360.63297 | J48: =SUM(J7:J46) -> 44332.218 | K48: =SUM(K7:K46) -> 0 | L48: =SUM(L7:L46) -> 44332.218

Sheet Saving Monthly Jan-24
A1: SANSAM SAVING GROUP
A2: SAVING FROM 5USD PER MONTH BY GETTING INTEREST 10% PER YEAR
A3: SAVING DEPOSIT FROM 1ST - 10TH EVERY MONTH
A4: ACCESSIBLE LOAN ON 15TH EACH MONTH
A5: SAVING IN JANUARY 2024
A6: NO | B6: NAME | C6: SEX | D6: ROLE | E6: SAVING DATE | F6: TEAM LEADER | G6: CAPITAL | H6: SAVING | I6: INTEREST | J6: BALANCE | K6: WITHDRAWAL | L6: TOTAL
A7: 1 | B7: ART THORN | C7: M | D7: FOUNDER | E7: 45235 | G7: 4204.3594 | H7: 23.6 | I7: =G7*0.83% -> 34.896183 | J7: =G7+H7+I7 -> 4262.8555 | L7: =J7-K7 -> 4262.8555
A8: 2 | B8: PECH PISEY | C8: M | D8: FOUNDER | E8: 45240 | G8: 6653.4894 | H8: 30 | I8: =G8*0.83% -> 55.223962 | J8: =G8+H8+I8 -> 6738.7134 | L8: =J8-K8 -> 6738.7134
A9: 3 | B9: HONG REAKSMEY | C9: M | D9: FOUNDER | E9: 45299 | G9: 6515.6801 | H9: 50 | I9: =G9*0.83% -> 54.080145 | J9: =G9+H9+I9 -> 6619.7603 | L9: =J9-K9 -> 6619.7603
A10: 4 | B10: SIN PUTHEARY | C10: F | D10: FOUNDER | E10: 45171 | G10: 5765.735 | I10: =G10*0.83% -> 47.8556 | J10: =G10+H10+I10 -> 5813.5906 | K10: 2909.93 | L10: =J10-K10 -> 2903.6606
A11: 5 | B11: PAO VORN | C11: M | D11: FOUNDER | E11: 45239 | G11: 432.94702 | I11: =G11*0.83% -> 3.5934603 | J11: =G11+H11+I11 -> 436.54048 | L11: =J11-K11 -> 436.54048
A12: 6 | B12: SOR MORA | C12: M | D12: FOUNDER | E12: 45270 | G12: 2442.823 | H12: 5 | I12: =G12*0.83% -> 20.275431 | J12: =G12+H12+I12 -> 2468.0985 | L12: =J12-K12 -> 2468.0985
A13: 7 | B13: NOP VY | C13: M | D13: FOUNDER | E13: 45245 | G13: 6370.3713 | H13: 47.28 | I13: =G13*0.83% -> 52.874082 | J13: =G13+H13+I13 -> 6470.5254 | L13: =J13-K13 -> 6470.5254
A14: 8 | B14: OU RITHTY | C14: M | D14: FOUNDER | E14: 45296 | G14: 5954.5905 | H14: 50 | I14: =G14*0.83% -> 49.423101 | J14: =G14+H14+I14 -> 6054.0136 | L14: =J14-K14 -> 6054.0136
A15: 9 | B15: SENG RITHY | C15: M | D15: MEMBER | E15: 45299 | F15: NOP VY | G15: 57.340289 | H15: 5 | I15: =G15*0.83% -> 0.4759244 | J15: =G15+H15+I15 -> 62.816213 | L15: =J15-K15 -> 62.816213
A16: 10 | B16: OU TEP PHALLIN | C16: F | D16: MEMBER | E16: 45294 | F16: OU RITHY | G16: 167.15004 | H16: 20 | I16: =G16*0.83% -> 1.3873453 | J16: =G16+H16+I16 -> 188.53738 | L16: =J16-K16 -> 188.53738
A17: 11 | B17: YIM BUNTHENG | C17: M | D17: MEMBER | E17: 45294 | F17: HONG REAKSMEY | G17: 83.150224 | H17: 10 | I17: =G17*0.83% -> 0.69014686 | J17: =G17+H17+I17 -> 93.840371 | L17: =J17-K17 -> 93.840371
A18: 12 | B18: THENG SAVOEUN | C18: M | D18: MEMBER | E18: 45029 | F18: NOP VY | G18: 81.017515 | I18: =G18*0.83% -> 0.67244538 | J18: =G18+H18+I18 -> 81.689961 | L18: =J18-K18 -> 81.689961
A19: 13 | B19: UL VANN | C19: M | D19: MEMBER | E19: 45240 | F19: NOP VY | G19: 145.25802 | I19: =G19*0.83% -> 1.2056416 | J19: =G19+H19+I19 -> 146.46366 | L19: =J19-K19 -> 146.46366
A20: 14 | B20: SIYONN SOTHEARITH | C20: M | D20: MEMBER | E20: 45294 | F20: HONG REAKSMEY | G20: 735.04713 | H20: 100 | I20: =G20*0.83% -> 6.1008912 | J20: =G20+H20+I20 -> 841.14803 | L20: =J20-K20 -> 841.14803
A21: 15 | B21: YEAN REAKSMEY | C21: M | D21: MEMBER | E21: 45294 | F21: PECH PISEY | G21: 94.301535 | H21: 15 | I21: =G21*0.83% -> 0.78270274 | J21: =G21+H21+I21 -> 110.08424 | L21: =J21-K21 -> 110.08424
A22: 16 | B22: SAM SOMONY | C22: M | D22: MEMBER | E22: 45299 | F22: NOP VY | G22: 916.47431 | H22: 50 | I22: =G22*0.83% -> 7.6067368 | J22: =G22+H22+I22 -> 974.08105 | L22: =J22-K22 -> 974.08105
A23: 17 | B23: KOY MAQUIS | C23: M | D23: MEMBER | E23: 45293 | F23: HONG REAKSMEY | G23: 144.97365 | H23: 15 | I23: =G23*0.83% -> 1.2032813 | J23: =G23+H23+I23 -> 161.17693 | L23: =J23-K23 -> 161.17693
A24: 18 | B24: LY MALIN | C24: F | D24: MEMBER | E24: 45295 | F24: OU RITHY | G24: 301.76561 | H24: 50 | I24: =G24*0.83% -> 2.5046546 | J24: =G24+H24+I24 -> 354.27027 | L24: =J24-K24 -> 354.27027
A25: 19 | B25: VAN BUNNA | C25: M | D25: MEMBER | E25: 45303 | F25: PECH PISEY | G25: 88.914309 | H25: 10 | I25: =G25*0.83% -> 0.73798876 | J25: =G25+H25+I25 -> 99.652297 | L25: =J25-K25 -> 99.652297
A26: 20 | B26: CHAN THEARA | C26: F | D26: MEMBER | E26: 45295 | F26: HONG REAKSMEY | G26: 56.305705 | H26: 5 | I26: =G26*0.83% -> 0.46733735 | J26: =G26+H26+I26 -> 61.773042 | L26: =J26-K26 -> 61.773042
A27: 21 | B27: LONG BORIN | C27: F | D27: MEMBER | E27: 45140 | F27: NOP VY | G27: 111.40699 | I27: =G27*0.83% -> 0.92467798 | J27: =G27+H27+I27 -> 112.33166 | L27: =J27-K27 -> 112.33166
A28: 22 | B28: SOEUNG SAROEUN | C28: M | D28: MEMBER | E28: 45235 | F28: NOP VY | G28: 131.1626 | I28: =G28*0.83% -> 1.0886496 | J28: =G28+H28+I28 -> 132.25125 | L28: =J28-K28 -> 132.25125
A29: 23 | B29: TUY SYTHIENG | C29: M | D29: MEMBER | E29: 45302 | F29: OU RITHY | G29: 411.37904 | H29: 100 | I29: =G29*0.83% -> 3.414446 | J29: =G29+H29+I29 -> 514.79348 | L29: =J29-K29 -> 514.79348
A30: 24 | B30: CHHEOUNG VEASNA | C30: M | D30: MEMBER | E30: 45201 | F30: SAM SOMONY | G30: 424.86221 | I30: =G30*0.83% -> 3.5263564 | J30: =G30+H30+I30 -> 428.38857 | L30: =J30-K30 -> 428.38857
A31: 25 | B31: OM MANITH | C31: M | D31: MEMBER | E31: 45059 | F31: OU RITHY | G31: 21.191337 | I31: =G31*0.83% -> 0.1758881 | J31: =G31+H31+I31 -> 21.367225 | L31: =J31-K31 -> 21.367225
A32: 26 | B32: IM SOTHY | C32: M | D32: MEMBER | E32: 45209 | F32: PECH PISEY | G32: 62.287073 | I32: =G32*0.83% -> 0.5169827 | J32: =G32+H32+I32 -> 62.804055 | L32: =J32-K32 -> 62.804055
A33: 27 | B33: PA CHANROEUN | C33: M | D33: MEMBER | E33: 45085 | F33: NOP VY | G33: 208.43893 | I33: =G33*0.83% -> 1.7300431 | J33: =G33+H33+I33 -> 210.16897 | L33: =J33-K33 -> 210.16897
A34: 28 | B34: HENG SOCHEA | C34: F | D34: MEMBER | E34: 45235 | F34: OU RITHY | G34: 25.375225 | I34: =G34*0.83% -> 0.21061437 | J34: =G34+H34+I34 -> 25.585839 | L34: =J34-K34 -> 25.585839
A35: 29 | B35: TUM SOKRAKSA | C35: F | D35: MEMBER | E35: 45235 | F35: SIN PUTHEARY | G35: 1009.5588 | I35: =G35*0.83% -> 8.3793381 | J35: =G35+H35+I35 -> 1017.9381 | L35: =J35-K35 -> 1017.9381
A36: 30 | B36: SDEUNG PHEARONG | D36: MEMBER | E36: 45235 | G36: 15.167036 | I36: =G36*0.83% -> 0.1258864 | J36: =G36+H36+I36 -> 15.292923 | L36: =J36-K36 -> 15.292923
A37: 31 | B37: TY SAMPHORS VICHEKA | D37: MEMBER | E37: 45295 | G37: 45.374533 | H37: 15 | I37: =G37*0.83% -> 0.37660863 | J37: =G37+H37+I37 -> 60.751142 | L37: =J37-K37 -> 60.751142
A38: 32 | B38: CHUM CHANDARIN | D38: MEMBER | E38: 45294 | G38: 136.74989 | H38: 50 | I38: =G38*0.83% -> 1.1350241 | J38: =G38+H38+I38 -> 187.88491 | L38: =J38-K38 -> 187.88491
A39: 33 | B39: PEANH KOEUN | D39: MEMBER | E39: 45295 | G39: 30.249689 | H39: 10 | I39: =G39*0.83% -> 0.25107242 | J39: =G39+H39+I39 -> 40.500761 | L39: =J39-K39 -> 40.500761
A40: 34 | B40: YANG SOPHORN | D40: MEMBER | E40: 45295 | G40: 60.499378 | H40: 20 | I40: =G40*0.83% -> 0.50214484 | J40: =G40+H40+I40 -> 81.001523 | L40: =J40-K40 -> 81.001523
A41: 35 | B41: RO VANNAK | D41: MEMBER | E41: 45298 | G41: 30.249689 | H41: 10 | I41: =G41*0.83% -> 0.25107242 | J41: =G41+H41+I41 -> 40.500761 | L41: =J41-K41 -> 40.500761
A42: 36 | B42: SENG VANLY | D42: MEMBER | E42: 45297 | G42: 75.624222 | H42: 25 | I42: =G42*0.83% -> 0.62768104 | J42: =G42+H42+I42 -> 101.2519 | L42: =J42-K42 -> 101.2519
A43: 37 | B43: YORNG SOKHAI | D43: MEMBER | E43: 45237 | G43: 101.24844 | I43: =G43*0.83% -> 0.84036209 | J43: =G43+H43+I43 -> 102.08881 | L43: =J43-K43 -> 102.08881
A44: 38 | B44: MENGHAK VICHHAY | D44: MEMBER | E44: 45302 | G44: 30.758023 | H44: 10 | I44: =G44*0.83% -> 0.25529159 | J44: =G44+H44+I44 -> 41.013315 | L44: =J44-K44 -> 41.013315
A45: 39 | B45: SIM SUNNARY | D45: MEMBER | E45: 45245 | G45: 20.249689 | I45: =G45*0.83% -> 0.16807242 | J45: =G45+H45+I45 -> 20.417761 | L45: =J45-K45 -> 20.417761
A46: 40 | B46: AN NITH | D46: MEMBER | E46: 45316 | G46: 10 | J46: =G46+H46+I46 -> 10 | L46: =J46-K46 -> 10
A47: 41 | B47: SRENG SAREN | D47: MEMBER | E47: 45296 | G47: 50 | J47: =G47+H47+I47 -> 50 | L47: =J47-K47 -> 50
A48: 42 | B48: LAUT PHEAKDEY | D48: MEMBER | E48: 45303 | G48: 20 | J48: =G48+H48+I48 -> 20 | L48: =J48-K48 -> 20
G50: =SUM(G7:G48) -> 44243.527 | H50: =SUM(H7:H47) -> 725.88 | I50: =SUM(I7:I47) -> 366.55727 | J50: =SUM(J7:J48) -> 45335.964 | K50: =SUM(K7:K47) -> 2909.93 | L50: =SUM(L7:L48) -> 42426.034

Sheet Saving Monthly Feb-24
A1: SANSAM SAVING GROUP
A2: SAVING FROM 5USD PER MONTH BY GETTING INTEREST 10% PER YEAR
A3: SAVING DEPOSIT FROM 1ST - 10TH EVERY MONTH
A4: ACCESSIBLE LOAN ON 15TH EACH MONTH
A5: SAVING IN FEB 2024
A6: NO | B6: NAME | C6: SEX | D6: ROLE | E6: SAVING DATE | F6: TEAM LEADER | G6: CAPITAL | H6: SAVING | I6: INTEREST | J6: BALANCE | K6: WITHDRAWAL | L6: TOTAL
A7: 1 | B7: ART THORN | C7: M | D7: FOUNDER | E7: 45351 | G7: 4262.8555 | H7: 20 | I7: =G7*0.83% -> 35.381701 | J7: =G7+H7+I7 -> 4318.2372 | L7: =J7-K7 -> 4318.2372
A8: 2 | B8: PECH PISEY | C8: M | D8: FOUNDER | E8: 45334 | G8: 6738.7134 | H8: 30 | I8: =G8*0.83% -> 55.931321 | J8: =G8+H8+I8 -> 6824.6447 | L8: =J8-K8 -> 6824.6447
A9: 3 | B9: HONG REAKSMEY | C9: M | D9: FOUNDER | E9: 45697 | G9: 6619.7603 | H9: 50 | I9: =G9*0.83% -> 54.94401 | J9: =G9+H9+I9 -> 6724.7043 | L9: =J9-K9 -> 6724.7043
A10: 4 | B10: SIN PUTHEARY | C10: F | D10: FOUNDER | E10: 45171 | G10: 2903.6606 | I10: =G10*0.83% -> 24.100383 | J10: =G10+H10+I10 -> 2927.7609 | L10: =J10-K10 -> 2927.7609
A11: 5 | B11: PAO VORN | C11: M | D11: FOUNDER | E11: 45239 | G11: 436.54048 | I11: =G11*0.83% -> 3.623286 | J11: =G11+H11+I11 -> 440.16377 | L11: =J11-K11 -> 440.16377
A12: 6 | B12: SOR MORA | C12: M | D12: FOUNDER | E12: 45270 | G12: 2468.0985 | I12: =G12*0.83% -> 20.485217 | J12: =G12+H12+I12 -> 2488.5837 | L12: =J12-K12 -> 2488.5837
A13: 7 | B13: NOP VY | C13: M | D13: FOUNDER | E13: 45333 | G13: 6470.5254 | H13: 50.6 | I13: =G13*0.83% -> 53.70536 | J13: =G13+H13+I13 -> 6574.8307 | L13: =J13-K13 -> 6574.8307
A14: 8 | B14: OU RITHTY | C14: M | D14: FOUNDER | E14: 45331 | G14: 6054.0136 | H14: 30 | I14: =G14*0.83% -> 50.248313 | J14: =G14+H14+I14 -> 6134.2619 | L14: =J14-K14 -> 6134.2619
A15: 9 | B15: SENG RITHY | C15: M | D15: MEMBER | E15: 45331 | F15: NOP VY | G15: 62.816213 | H15: 5 | I15: =G15*0.83% -> 0.52137457 | J15: =G15+H15+I15 -> 68.337588 | L15: =J15-K15 -> 68.337588
A16: 10 | B16: OU TEP PHALLIN | C16: F | D16: MEMBER | E16: 45324 | F16: OU RITHY | G16: 188.53738 | H16: 20 | I16: =G16*0.83% -> 1.5648603 | J16: =G16+H16+I16 -> 210.10224 | L16: =J16-K16 -> 210.10224
A17: 11 | B17: YIM BUNTHENG | C17: M | D17: MEMBER | E17: 45294 | F17: HONG REAKSMEY | G17: 93.840371 | I17: =G17*0.83% -> 0.77887508 | J17: =G17+H17+I17 -> 94.619246 | L17: =J17-K17 -> 94.619246
A18: 12 | B18: THENG SAVOEUN | C18: M | D18: MEMBER | E18: 45029 | F18: NOP VY | G18: 81.689961 | I18: =G18*0.83% -> 0.67802667 | J18: =G18+H18+I18 -> 82.367987 | L18: =J18-K18 -> 82.367987
A19: 13 | B19: UL VANN | C19: M | D19: MEMBER | E19: 45240 | F19: NOP VY | G19: 146.46366 | I19: =G19*0.83% -> 1.2156484 | J19: =G19+H19+I19 -> 147.67931 | L19: =J19-K19 -> 147.67931
A20: 14 | B20: SIYONN SOTHEARITH | C20: M | D20: MEMBER | E20: 45690 | F20: HONG REAKSMEY | G20: 841.14803 | H20: 100 | I20: =G20*0.83% -> 6.9815286 | J20: =G20+H20+I20 -> 948.12955 | L20: =J20-K20 -> 948.12955
A21: 15 | B21: YEAN REAKSMEY | C21: M | D21: MEMBER | E21: 45294 | F21: PECH PISEY | G21: 110.08424 | I21: =G21*0.83% -> 0.91369917 | J21: =G21+H21+I21 -> 110.99794 | L21: =J21-K21 -> 110.99794
A22: 16 | B22: SAM SOMONY | C22: M | D22: MEMBER | E22: 45324 | F22: NOP VY | G22: 974.08105 | H22: 50 | I22: =G22*0.83% -> 8.0848727 | J22: =G22+H22+I22 -> 1032.1659 | L22: =J22-K22 -> 1032.1659
A23: 17 | B23: KOY MAQUIS | C23: M | D23: MEMBER | E23: 45690 | F23: HONG REAKSMEY | G23: 161.17693 | H23: 20 | I23: =G23*0.83% -> 1.3377685 | J23: =G23+H23+I23 -> 182.5147 | L23: =J23-K23 -> 182.5147
A24: 18 | B24: LY MALIN | C24: F | D24: MEMBER | E24: 45324 | F24: OU RITHY | G24: 354.27027 | H24: 50 | I24: =G24*0.83% -> 2.9404432 | J24: =G24+H24+I24 -> 407.21071 | L24: =J24-K24 -> 407.21071
A25: 19 | B25: VAN BUNNA | C25: M | D25: MEMBER | E25: 45303 | F25: PECH PISEY | G25: 99.652297 | I25: =G25*0.83% -> 0.82711407 | J25: =G25+H25+I25 -> 100.47941 | L25: =J25-K25 -> 100.47941
A26: 20 | B26: CHAN THEARA | C26: F | D26: MEMBER | E26: 45325 | F26: HONG REAKSMEY | G26: 61.773042 | H26: 5 | I26: =G26*0.83% -> 0.51271625 | J26: =G26+H26+I26 -> 67.285759 | L26: =J26-K26 -> 67.285759
A27: 21 | B27: LONG BORIN | C27: F | D27: MEMBER | E27: 45140 | F27: NOP VY | G27: 112.33166 | I27: =G27*0.83% -> 0.93235281 | J27: =G27+H27+I27 -> 113.26402 | L27: =J27-K27 -> 113.26402
A28: 22 | B28: SOEUNG SAROEUN | C28: M | D28: MEMBER | E28: 45235 | F28: NOP VY | G28: 132.25125 | I28: =G28*0.83% -> 1.0976854 | J28: =G28+H28+I28 -> 133.34893 | L28: =J28-K28 -> 133.34893
A29: 23 | B29: TUY SYTHIENG | C29: M | D29: MEMBER | E29: 45334 | F29: OU RITHY | G29: 514.79348 | H29: 100 | I29: =G29*0.83% -> 4.2727859 | J29: =G29+H29+I29 -> 619.06627 | L29: =J29-K29 -> 619.06627
A30: 24 | B30: CHHEOUNG VEASNA | C30: M | D30: MEMBER | E30: 45201 | F30: SAM SOMONY | G30: 428.38857 | I30: =G30*0.83% -> 3.5556251 | J30: =G30+H30+I30 -> 431.94419 | L30: =J30-K30 -> 431.94419
A31: 25 | B31: OM MANITH | C31: M | D31: MEMBER | E31: 45059 | F31: OU RITHY | G31: 21.367225 | I31: =G31*0.83% -> 0.17734797 | J31: =G31+H31+I31 -> 21.544573 | L31: =J31-K31 -> 21.544573
A32: 26 | B32: IM SOTHY | C32: M | D32: MEMBER | E32: 45209 | F32: PECH PISEY | G32: 62.804055 | I32: =G32*0.83% -> 0.52127366 | J32: =G32+H32+I32 -> 63.325329 | L32: =J32-K32 -> 63.325329
A33: 27 | B33: PA CHANROEUN | C33: M | D33: MEMBER | E33: 45085 | F33: NOP VY | G33: 210.16897 | I33: =G33*0.83% -> 1.7444025 | J33: =G33+H33+I33 -> 211.91337 | L33: =J33-K33 -> 211.91337
A34: 28 | B34: HENG SOCHEA | C34: F | D34: MEMBER | E34: 45330 | F34: OU RITHY | G34: 25.585839 | H34: 10 | I34: =G34*0.83% -> 0.21236247 | J34: =G34+H34+I34 -> 35.798202 | L34: =J34-K34 -> 35.798202
A35: 29 | B35: TUM SOKRAKSA | C35: F | D35: MEMBER | E35: 45235 | F35: SIN PUTHEARY | G35: 1017.9381 | I35: =G35*0.83% -> 8.4488866 | J35: =G35+H35+I35 -> 1026.387 | L35: =J35-K35 -> 1026.387
A36: 30 | B36: SDEUNG PHEARONG | D36: MEMBER | E36: 45235 | G36: 15.292923 | I36: =G36*0.83% -> 0.12693126 | J36: =G36+H36+I36 -> 15.419854 | L36: =J36-K36 -> 15.419854
A37: 31 | B37: TY SAMPHORS VICHEKA | D37: MEMBER | E37: 45331 | G37: 60.751142 | H37: 15 | I37: =G37*0.83% -> 0.50423448 | J37: =G37+H37+I37 -> 76.255376 | L37: =J37-K37 -> 76.255376
A38: 32 | B38: CHUM CHANDARIN | D38: MEMBER | E38: 45294 | G38: 187.88491 | I38: =G38*0.83% -> 1.5594448 | J38: =G38+H38+I38 -> 189.44436 | L38: =J38-K38 -> 189.44436
A39: 33 | B39: PEANH KOEUN | D39: MEMBER | E39: 45333 | G39: 40.500761 | H39: 10 | I39: =G39*0.83% -> 0.33615632 | J39: =G39+H39+I39 -> 50.836918 | L39: =J39-K39 -> 50.836918
A40: 34 | B40: YANG SOPHORN | D40: MEMBER | E40: 45331 | G40: 81.001523 | H40: 20 | I40: =G40*0.83% -> 0.67231264 | J40: =G40+H40+I40 -> 101.67384 | L40: =J40-K40 -> 101.67384
A41: 35 | B41: RO VANNAK | D41: MEMBER | E41: 45330 | G41: 40.500761 | H41: 10 | I41: =G41*0.83% -> 0.33615632 | J41: =G41+H41+I41 -> 50.836918 | L41: =J41-K41 -> 50.836918
A42: 36 | B42: SENG VANLY | D42: MEMBER | E42: 45333 | G42: 101.2519 | H42: 25 | I42: =G42*0.83% -> 0.8403908 | J42: =G42+H42+I42 -> 127.09229 | L42: =J42-K42 -> 127.09229
A43: 37 | B43: YORNG SOKHAI | D43: MEMBER | E43: 45334 | G43: 102.08881 | H43: 25 | I43: =G43*0.83% -> 0.84733709 | J43: =G43+H43+I43 -> 127.93614 | L43: =J43-K43 -> 127.93614
A44: 38 | B44: MENGHAK VICHHAY | D44: MEMBER | E44: 45333 | G44: 41.013315 | H44: 10 | I44: =G44*0.83% -> 0.34041051 | J44: =G44+H44+I44 -> 51.353725 | L44: =J44-K44 -> 51.353725
A45: 39 | B45: SIM SUNNARY | D45: MEMBER | E45: 45245 | G45: 20.417761 | I45: =G45*0.83% -> 0.16946742 | J45: =G45+H45+I45 -> 20.587229 | L45: =J45-K45 -> 20.587229
A46: 40 | B46: AN NITH | D46: MEMBER | E46: 45316 | G46: 10 | I46: =G46*0.83% -> 0.083 | J46: =G46+H46+I46 -> 10.083 | L46: =J46-K46 -> 10.083
A47: 41 | B47: SRENG SAREN | D47: MEMBER | E47: 45324 | G47: 50 | H47: 50 | I47: =G47*0.83% -> 0.415 | J47: =G47+H47+I47 -> 100.415 | L47: =J47-K47 -> 100.415
A48: 42 | B48: LAUT PHEAKDEY | D48: MEMBER | E48: 45303 | G48: 20 | I48: =G48*0.83% -> 0.166 | J48: =G48+H48+I48 -> 20.166 | L48: =J48-K48 -> 20.166
A49: 43 | B49: KRUY BOPHA | D49: MEMBER | E49: 45324 | G49: 10 | J49: =G49+H49+I49 -> 10 | L49: =J49-K49 -> 10
A50: 44 | B50: HORN RITHY | D50: MEMBER | E50: 45324 | G50: 10 | J50: =G50+H50+I50 -> 10 | L50: =J50-K50 -> 10
A51: 45 | B51: SAY POLYDA | D51: MEMBER | E51: 45698 | G51: 10 | J51: =G51+H51+I51 -> 10 | L51: =J51-K51 -> 10
G53: =SUM(G7:G48) -> 42426.034 | H53: =SUM(H7:H47) -> 705.6 | I53: =SUM(I7:I47) -> 351.97008 | J53: =SUM(J7:J48) -> 43483.77 | K53: =SUM(K7:K47) -> 0 | L53: =SUM(L7:L48) -> 43483.77

Sheet March-24
A1: SANSAM SAVING GROUP
A2: SAVING FROM 5USD PER MONTH BY GETTING INTEREST 10% PER YEAR
A3: SAVING DEPOSIT FROM 1ST - 10TH EVERY MONTH
A4: ACCESSIBLE LOAN ON 15TH EACH MONTH
A5: SAVING IN Mar 2024
A6: NO | B6: NAME | C6: SEX | D6: ROLE | E6: SAVING DATE | F6: TEAM LEADER | G6: CAPITAL | H6: SAVING | I6: INTEREST | J6: BALANCE | K6: WITHDRAWAL | L6: TOTAL
A7: 1 | B7: ART THORN | C7: M | D7: FOUNDER | E7: 45235 | G7: 4318.2372 | I7: =G7*0.83% -> 35.841369 | J7: =G7+H7+I7 -> 4354.0786 | L7: =J7-K7 -> 4354.0786
A8: 2 | B8: PECH PISEY | C8: M | D8: FOUNDER | E8: 45362 | G8: 6824.6447 | H8: 30 | I8: =G8*0.83% -> 56.644551 | J8: =G8+H8+I8 -> 6911.2893 | L8: =J8-K8 -> 6911.2893
A9: 3 | B9: HONG REAKSMEY | C9: M | D9: FOUNDER | E9: 45361 | G9: 6724.7043 | H9: 50 | I9: =G9*0.83% -> 55.815046 | J9: =G9+H9+I9 -> 6830.5193 | L9: =J9-K9 -> 6830.5193
A10: 4 | B10: SIN PUTHEARY | C10: F | D10: FOUNDER | E10: 45171 | G10: 2927.7609 | I10: =G10*0.83% -> 24.300416 | J10: =G10+H10+I10 -> 2952.0614 | L10: =J10-K10 -> 2952.0614
A11: 5 | B11: PAO VORN | C11: M | D11: FOUNDER | E11: 45239 | G11: 440.16377 | I11: =G11*0.83% -> 3.6533593 | J11: =G11+H11+I11 -> 443.81713 | L11: =J11-K11 -> 443.81713
A12: 6 | B12: SOR MORA | C12: M | D12: FOUNDER | E12: 45270 | G12: 2488.5837 | H12: 25 | I12: =G12*0.83% -> 20.655245 | J12: =G12+H12+I12 -> 2534.2389 | L12: =J12-K12 -> 2534.2389
A13: 7 | B13: NOP VY | C13: M | D13: FOUNDER | E13: 45361 | G13: 6574.8307 | H13: 53.92 | I13: =G13*0.83% -> 54.571095 | J13: =G13+H13+I13 -> 6683.3218 | L13: =J13-K13 -> 6683.3218
A14: 8 | B14: OU RITHTY | C14: M | D14: FOUNDER | E14: 45359 | G14: 6134.2619 | H14: 100 | I14: =G14*0.83% -> 50.914374 | J14: =G14+H14+I14 -> 6285.1763 | L14: =J14-K14 -> 6285.1763
A15: 9 | B15: SENG RITHY | C15: M | D15: MEMBER | E15: 45331 | F15: NOP VY | G15: 68.337588 | H15: 10 | I15: =G15*0.83% -> 0.56720198 | J15: =G15+H15+I15 -> 78.90479 | L15: =J15-K15 -> 78.90479
A16: 10 | B16: OU TEP PHALLIN | C16: F | D16: MEMBER | E16: 45362 | F16: OU RITHY | G16: 210.10224 | H16: 20 | I16: =G16*0.83% -> 1.7438486 | J16: =G16+H16+I16 -> 231.84609 | L16: =J16-K16 -> 231.84609
A17: 11 | B17: YIM BUNTHENG | C17: M | D17: MEMBER | E17: 45294 | F17: HONG REAKSMEY | G17: 94.619246 | I17: =G17*0.83% -> 0.78533974 | J17: =G17+H17+I17 -> 95.404585 | L17: =J17-K17 -> 95.404585
A18: 12 | B18: THENG SAVOEUN | C18: M | D18: MEMBER | E18: 45029 | F18: NOP VY | G18: 82.367987 | I18: =G18*0.83% -> 0.6836543 | J18: =G18+H18+I18 -> 83.051642 | L18: =J18-K18 -> 83.051642
A19: 13 | B19: UL VANN | C19: M | D19: MEMBER | E19: 45240 | F19: NOP VY | G19: 147.67931 | H19: 20 | I19: =G19*0.83% -> 1.2257383 | J19: =G19+H19+I19 -> 168.90505 | L19: =J19-K19 -> 168.90505
A20: 14 | B20: SIYONN SOTHEARITH | C20: M | D20: MEMBER | E20: 45357 | F20: HONG REAKSMEY | G20: 948.12955 | H20: 100 | I20: =G20*0.83% -> 7.8694753 | J20: =G20+H20+I20 -> 1055.999 | L20: =J20-K20 -> 1055.999
A21: 15 | B21: YEAN REAKSMEY | C21: M | D21: MEMBER | E21: 45294 | F21: PECH PISEY | G21: 110.99794 | H21: 15 | I21: =G21*0.83% -> 0.92128287 | J21: =G21+H21+I21 -> 126.91922 | L21: =J21-K21 -> 126.91922
A22: 16 | B22: SAM SOMONY | C22: M | D22: MEMBER | E22: 45325 | F22: NOP VY | G22: 1032.1659 | H22: 100 | I22: =G22*0.83% -> 8.5669771 | J22: =G22+H22+I22 -> 1140.7329 | L22: =J22-K22 -> 1140.7329
A23: 17 | B23: KOY MAQUIS | C23: M | D23: MEMBER | E23: 45324 | F23: HONG REAKSMEY | G23: 182.5147 | H23: 30 | I23: =G23*0.83% -> 1.514872 | J23: =G23+H23+I23 -> 214.02957 | L23: =J23-K23 -> 214.02957
A24: 18 | B24: LY MALIN | C24: F | D24: MEMBER | E24: 45330 | F24: OU RITHY | G24: 407.21071 | H24: 50 | I24: =G24*0.83% -> 3.3798489 | J24: =G24+H24+I24 -> 460.59056 | L24: =J24-K24 -> 460.59056
A25: 19 | B25: VAN BUNNA | C25: M | D25: MEMBER | E25: 45240 | F25: PECH PISEY | G25: 100.47941 | H25: 20 | I25: =G25*0.83% -> 0.83397912 | J25: =G25+H25+I25 -> 121.31339 | L25: =J25-K25 -> 121.31339
A26: 20 | B26: CHAN THEARA | C26: F | D26: MEMBER | E26: 45325 | F26: HONG REAKSMEY | G26: 67.285759 | H26: 5 | I26: =G26*0.83% -> 0.5584718 | J26: =G26+H26+I26 -> 72.84423 | L26: =J26-K26 -> 72.84423
A27: 21 | B27: LONG BORIN | C27: F | D27: MEMBER | E27: 45140 | F27: NOP VY | G27: 113.26402 | I27: =G27*0.83% -> 0.94009133 | J27: =G27+H27+I27 -> 114.20411 | L27: =J27-K27 -> 114.20411
A28: 22 | B28: SOEUNG SAROEUN | C28: M | D28: MEMBER | E28: 45235 | F28: NOP VY | G28: 133.34893 | I28: =G28*0.83% -> 1.1067961 | J28: =G28+H28+I28 -> 134.45573 | L28: =J28-K28 -> 134.45573
A29: 23 | B29: TUY SYTHIENG | C29: M | D29: MEMBER | E29: 45334 | F29: OU RITHY | G29: 619.06627 | H29: 50 | I29: =G29*0.83% -> 5.13825 | J29: =G29+H29+I29 -> 674.20452 | L29: =J29-K29 -> 674.20452
A30: 24 | B30: CHHEOUNG VEASNA | C30: M | D30: MEMBER | E30: 45361 | F30: SAM SOMONY | G30: 431.94419 | H30: 100 | I30: =G30*0.83% -> 3.5851368 | J30: =G30+H30+I30 -> 535.52933 | L30: =J30-K30 -> 535.52933
A31: 25 | B31: OM MANITH | C31: M | D31: MEMBER | E31: 45059 | F31: OU RITHY | G31: 21.544573 | H31: 10 | I31: =G31*0.83% -> 0.17881996 | J31: =G31+H31+I31 -> 31.723393 | L31: =J31-K31 -> 31.723393
A32: 26 | B32: IM SOTHY | C32: M | D32: MEMBER | E32: 45209 | F32: PECH PISEY | G32: 63.325329 | I32: =G32*0.83% -> 0.52560023 | J32: =G32+H32+I32 -> 63.850929 | L32: =J32-K32 -> 63.850929
A33: 27 | B33: PA CHANROEUN | C33: M | D33: MEMBER | E33: 45085 | F33: NOP VY | G33: 211.91337 | I33: =G33*0.83% -> 1.758881 | J33: =G33+H33+I33 -> 213.67225 | L33: =J33-K33 -> 213.67225
A34: 28 | B34: HENG SOCHEA | C34: F | D34: MEMBER | E34: 45330 | F34: OU RITHY | G34: 35.798202 | I34: =G34*0.83% -> 0.29712508 | J34: =G34+H34+I34 -> 36.095327 | L34: =J34-K34 -> 36.095327
A35: 29 | B35: TUM SOKRAKSA | C35: F | D35: MEMBER | E35: 45235 | F35: SIN PUTHEARY | G35: 1026.387 | I35: =G35*0.83% -> 8.5190124 | J35: =G35+H35+I35 -> 1034.906 | L35: =J35-K35 -> 1034.906
A36: 30 | B36: SDEUNG PHEARONG | D36: MEMBER | E36: 45235 | G36: 15.419854 | I36: =G36*0.83% -> 0.12798479 | J36: =G36+H36+I36 -> 15.547839 | L36: =J36-K36 -> 15.547839
A37: 31 | B37: TY SAMPHORS VICHEKA | D37: MEMBER | E37: 45331 | G37: 76.255376 | I37: =G37*0.83% -> 0.63291962 | J37: =G37+H37+I37 -> 76.888296 | L37: =J37-K37 -> 76.888296
A38: 32 | B38: CHUM CHANDARIN | D38: MEMBER | E38: 45294 | G38: 189.44436 | H38: 15 | I38: =G38*0.83% -> 1.5723882 | J38: =G38+H38+I38 -> 206.01675 | L38: =J38-K38 -> 206.01675
A39: 33 | B39: PEANH KOEUN | D39: MEMBER | E39: 45334 | G39: 50.836918 | H39: 10 | I39: =G39*0.83% -> 0.42194642 | J39: =G39+H39+I39 -> 61.258864 | L39: =J39-K39 -> 61.258864
A40: 34 | B40: YANG SOPHORN | D40: MEMBER | E40: 45360 | G40: 101.67384 | H40: 50 | I40: =G40*0.83% -> 0.84389283 | J40: =G40+H40+I40 -> 152.51773 | L40: =J40-K40 -> 152.51773
A41: 35 | B41: RO VANNAK | D41: MEMBER | E41: 45330 | G41: 50.836918 | I41: =G41*0.83% -> 0.42194642 | J41: =G41+H41+I41 -> 51.258864 | L41: =J41-K41 -> 51.258864
A42: 36 | B42: SENG VANLY | D42: MEMBER | E42: 45372 | G42: 127.09229 | H42: 10 | I42: =G42*0.83% -> 1.054866 | J42: =G42+H42+I42 -> 138.14716 | L42: =J42-K42 -> 138.14716
A43: 37 | B43: YORNG SOKHAI | D43: MEMBER | E43: 45334 | G43: 127.93614 | H43: 10 | I43: =G43*0.83% -> 1.06187 | J43: =G43+H43+I43 -> 138.99801 | L43: =J43-K43 -> 138.99801
A44: 38 | B44: MENGHAK VICHHAY | D44: MEMBER | E44: 45333 | G44: 51.353725 | I44: =G44*0.83% -> 0.42623592 | J44: =G44+H44+I44 -> 51.779961 | L44: =J44-K44 -> 51.779961
A45: 39 | B45: SIM SUNNARY | D45: MEMBER | E45: 45245 | G45: 20.587229 | I45: =G45*0.83% -> 0.170874 | J45: =G45+H45+I45 -> 20.758103 | L45: =J45-K45 -> 20.758103
A46: 40 | B46: AN NITH | D46: MEMBER | E46: 45293 | G46: 10.083 | I46: =G46*0.83% -> 0.0836889 | J46: =G46+H46+I46 -> 10.166689 | L46: =J46-K46 -> 10.166689
A47: 41 | B47: SRENG SAREN | D47: MEMBER | E47: 45324 | G47: 100.415 | H47: 50 | I47: =G47*0.83% -> 0.8334445 | J47: =G47+H47+I47 -> 151.24844 | L47: =J47-K47 -> 151.24844
A48: 42 | B48: LAUT PHEAKDEY | D48: MEMBER | E48: 45303 | G48: 20.166 | I48: =G48*0.83% -> 0.1673778 | J48: =G48+H48+I48 -> 20.333378 | L48: =J48-K48 -> 20.333378
A49: 43 | B49: KRUY BOPHA | D49: MEMBER | E49: 45324 | G49: 10 | H49: 10 | I49: =G49*0.83% -> 0.083 | J49: =G49+H49+I49 -> 20.083 | L49: =J49-K49 -> 20.083
A50: 44 | B50: HORN RITHY | D50: MEMBER | E50: 45324 | G50: 10 | I50: =G50*0.83% -> 0.083 | J50: =G50+H50+I50 -> 10.083 | L50: =J50-K50 -> 10.083
A51: 45 | B51: SAY SAMPOLIDA | D51: MEMBER | E51: 45332 | G51: 10 | I51: =G51*0.83% -> 0.083 | J51: =G51+H51+I51 -> 10.083 | L51: =J51-K51 -> 10.083
A52: 46 | B52: CHHEAV NAK | D52: MEMBER | E52: 45355 | H52: 10 | J52: =G52+H52+I52 -> 10 | L52: =J52-K52 -> 10
A53: 47 | B53: CHUN SOKTHOUTHEAREACH | D53: MEMBER | E53: 45357 | H53: 150 | J53: =G53+H53+I53 -> 150 | L53: =J53-K53 -> 150
A54: 48 | B54: MENG SOTHY VATNAK | D54: MEMBER | E54: 45359 | H54: 20 | J54: =G54+H54+I54 -> 20 | L54: =J54-K54 -> 20
A55: 49 | B55: HUN SOT | D55: MEMBER | E55: 45360 | H55: 10 | J55: =G55+H55+I55 -> 10 | L55: =J55-K55 -> 10
A56: 50 | B56: KET SOKSEILA | D56: MEMBER | E56: 45367 | H56: 50 | J56: =G56+H56+I56 -> 50 | L56: =J56-K56 -> 50
G57: =SUM(G7:G55) -> 43513.77 | H57: =SUM(H7:H56) -> 1183.92 | I57: =SUM(I7:I55) -> 361.16429 | J57: =SUM(J7:J55) -> 45008.855 | K57: =SUM(K7:K55) -> 0 | L57: =SUM(L7:L55) -> 45008.855

Sheet April-24
A1: SANSAM SAVING GROUP
A2: SAVING FROM 5USD PER MONTH BY GETTING INTEREST 10% PER YEAR
A3: SAVING DEPOSIT FROM 1ST - 10TH EVERY MONTH
A4: ACCESSIBLE LOAN ON 15TH EACH MONTH
A5: SAVING IN APRIL 2024
A6: NO | B6: NAME | C6: SEX | D6: ROLE | E6: SAVING DATE | F6: TEAM LEADER | G6: CAPITAL | H6: SAVING | I6: INTEREST | J6: BALANCE | K6: WITHDRAWAL | L6: TOTAL
A7: 1 | B7: ATH THORN | C7: M | D7: FOUNDER | E7: 45235 | G7: 4354.0786 | H7: 25.8 | I7: =G7*0.83% -> 36.138852 | J7: =G7+H7+I7 -> 4416.0175 | L7: =J7-K7 -> 4416.0175
A8: 2 | B8: PECH PISEY | C8: M | D8: FOUNDER | E8: 45392 | G8: 6911.2893 | H8: 30 | I8: =G8*0.83% -> 57.363701 | J8: =G8+H8+I8 -> 6998.653 | L8: =J8-K8 -> 6998.653
A9: 3 | B9: HONG REAKSMEY | C9: M | D9: FOUNDER | E9: 45392 | G9: 6830.5193 | H9: 100 | I9: =G9*0.83% -> 56.69331 | J9: =G9+H9+I9 -> 6987.2126 | L9: =J9-K9 -> 6987.2126
A10: 4 | B10: SIN PUTHEARY | C10: F | D10: FOUNDER | E10: 45171 | G10: 2952.0614 | I10: =G10*0.83% -> 24.502109 | J10: =G10+H10+I10 -> 2976.5635 | L10: =J10-K10 -> 2976.5635
A11: 5 | B11: PAO VORN | C11: M | D11: FOUNDER | E11: 45239 | G11: 443.81713 | I11: =G11*0.83% -> 3.6836822 | J11: =G11+H11+I11 -> 447.50081 | L11: =J11-K11 -> 447.50081
A12: 6 | B12: SOR MORA | C12: M | D12: FOUNDER | E12: 45383 | G12: 2534.2389 | H12: 25 | I12: =G12*0.83% -> 21.034183 | J12: =G12+H12+I12 -> 2580.2731 | L12: =J12-K12 -> 2580.2731
A13: 7 | B13: NOP VY | C13: M | D13: FOUNDER | E13: 45361 | G13: 6683.3218 | H13: 57.24 | I13: =G13*0.83% -> 55.471571 | J13: =G13+H13+I13 -> 6796.0334 | L13: =J13-K13 -> 6796.0334
A14: 8 | B14: OU RITHTY | C14: M | D14: FOUNDER | E14: 45387 | G14: 6285.1763 | H14: 100 | I14: =G14*0.83% -> 52.166963 | J14: =G14+H14+I14 -> 6437.3433 | L14: =J14-K14 -> 6437.3433
A15: 9 | B15: SENG RITHY | C15: M | D15: MEMBER | E15: 45387 | F15: NOP VY | G15: 78.90479 | H15: 10 | I15: =G15*0.83% -> 0.65490975 | J15: =G15+H15+I15 -> 89.559699 | L15: =J15-K15 -> 89.559699
A16: 10 | B16: OU TEP PHALLIN | C16: F | D16: MEMBER | E16: 45383 | F16: OU RITHY | G16: 231.84609 | H16: 50 | I16: =G16*0.83% -> 1.9243226 | J16: =G16+H16+I16 -> 283.77041 | L16: =J16-K16 -> 283.77041
A17: 11 | B17: YIM BUNTHENG | C17: M | D17: MEMBER | E17: 45294 | F17: HONG REAKSMEY | G17: 95.404585 | I17: =G17*0.83% -> 0.79185806 | J17: =G17+H17+I17 -> 96.196443 | L17: =J17-K17 -> 96.196443
A18: 12 | B18: THENG SAVOEUN | C18: M | D18: MEMBER | E18: 45029 | F18: NOP VY | G18: 83.051642 | I18: =G18*0.83% -> 0.68932863 | J18: =G18+H18+I18 -> 83.74097 | L18: =J18-K18 -> 83.74097
A19: 13 | B19: UL VANN | C19: M | D19: MEMBER | E19: 45387 | F19: NOP VY | G19: 168.90505 | H19: 20 | I19: =G19*0.83% -> 1.4019119 | J19: =G19+H19+I19 -> 190.30696 | L19: =J19-K19 -> 190.30696
A20: 14 | B20: SIYONN SOTHEARITH | C20: M | D20: MEMBER | E20: 45384 | F20: HONG REAKSMEY | G20: 1055.999 | H20: 100 | I20: =G20*0.83% -> 8.7647919 | J20: =G20+H20+I20 -> 1164.7638 | L20: =J20-K20 -> 1164.7638
A21: 15 | B21: YEAN REAKSMEY | C21: M | D21: MEMBER | E21: 45386 | F21: PECH PISEY | G21: 126.91922 | H21: 15 | I21: =G21*0.83% -> 1.0534295 | J21: =G21+H21+I21 -> 142.97265 | L21: =J21-K21 -> 142.97265
A22: 16 | B22: SAM SOMONY | C22: M | D22: MEMBER | E22: 45385 | F22: NOP VY | G22: 1140.7329 | H22: 100 | I22: =G22*0.83% -> 9.468083 | J22: =G22+H22+I22 -> 1250.201 | L22: =J22-K22 -> 1250.201
A23: 17 | B23: KOY MAQUIS | C23: M | D23: MEMBER | E23: 45324 | F23: HONG REAKSMEY | G23: 214.02957 | I23: =G23*0.83% -> 1.7764454 | J23: =G23+H23+I23 -> 215.80602 | L23: =J23-K23 -> 215.80602
A24: 18 | B24: LY MALIN | C24: F | D24: MEMBER | E24: 45393 | F24: OU RITHY | G24: 460.59056 | H24: 40 | I24: =G24*0.83% -> 3.8229017 | J24: =G24+H24+I24 -> 504.41346 | L24: =J24-K24 -> 504.41346
A25: 19 | B25: VAN BUNNA | C25: M | D25: MEMBER | E25: 45388 | F25: PECH PISEY | G25: 121.31339 | H25: 100 | I25: =G25*0.83% -> 1.0069011 | J25: =G25+H25+I25 -> 222.32029 | L25: =J25-K25 -> 222.32029
A26: 20 | B26: CHAN THEARA | C26: F | D26: MEMBER | E26: 45386 | F26: HONG REAKSMEY | G26: 72.84423 | H26: 5 | I26: =G26*0.83% -> 0.60460711 | J26: =G26+H26+I26 -> 78.448838 | L26: =J26-K26 -> 78.448838
A27: 21 | B27: LONG BORIN | C27: F | D27: MEMBER | E27: 45140 | F27: NOP VY | G27: 114.20411 | I27: =G27*0.83% -> 0.94789409 | J27: =G27+H27+I27 -> 115.152 | L27: =J27-K27 -> 115.152
A28: 22 | B28: SOEUNG SAROEUN | C28: M | D28: MEMBER | E28: 45235 | F28: NOP VY | G28: 134.45573 | I28: =G28*0.83% -> 1.1159825 | J28: =G28+H28+I28 -> 135.57171 | L28: =J28-K28 -> 135.57171
A29: 23 | B29: TUY SYTHIENG | C29: M | D29: MEMBER | E29: 45383 | F29: OU RITHY | G29: 674.20452 | H29: 100 | I29: =G29*0.83% -> 5.5958975 | J29: =G29+H29+I29 -> 779.80042 | L29: =J29-K29 -> 779.80042
A30: 24 | B30: CHHEOUNG VEASNA | C30: M | D30: MEMBER | E30: 45361 | F30: SAM SOMONY | G30: 535.52933 | I30: =G30*0.83% -> 4.4448934 | J30: =G30+H30+I30 -> 539.97422 | L30: =J30-K30 -> 539.97422
A31: 25 | B31: OM MANITH | C31: M | D31: MEMBER | E31: 45383 | F31: OU RITHY | G31: 31.723393 | H31: 10 | I31: =G31*0.83% -> 0.26330417 | J31: =G31+H31+I31 -> 41.986698 | L31: =J31-K31 -> 41.986698
A32: 26 | B32: IM SOTHY | C32: M | D32: MEMBER | E32: 45209 | F32: PECH PISEY | G32: 63.850929 | I32: =G32*0.83% -> 0.52996271 | J32: =G32+H32+I32 -> 64.380892 | L32: =J32-K32 -> 64.380892
A33: 27 | B33: PA CHANROEUN | C33: M | D33: MEMBER | E33: 45085 | F33: NOP VY | G33: 213.67225 | I33: =G33*0.83% -> 1.7734797 | J33: =G33+H33+I33 -> 215.44573 | L33: =J33-K33 -> 215.44573
A34: 28 | B34: HENG SOCHEA | C34: F | D34: MEMBER | E34: 45330 | F34: OU RITHY | G34: 36.095327 | I34: =G34*0.83% -> 0.29959121 | J34: =G34+H34+I34 -> 36.394918 | L34: =J34-K34 -> 36.394918
A35: 29 | B35: TUM SOKRAKSA | C35: F | D35: MEMBER | E35: 45235 | F35: SIN PUTHEARY | G35: 1034.906 | I35: =G35*0.83% -> 8.5897202 | J35: =G35+H35+I35 -> 1043.4958 | L35: =J35-K35 -> 1043.4958
A36: 30 | B36: SDEUNG PHEARONG | D36: MEMBER | E36: 45235 | G36: 15.547839 | I36: =G36*0.83% -> 0.12904706 | J36: =G36+H36+I36 -> 15.676886 | L36: =J36-K36 -> 15.676886
A37: 31 | B37: TY SAMPHORS VICHEKA | D37: MEMBER | E37: 45396 | G37: 76.888296 | H37: 15 | I37: =G37*0.83% -> 0.63817286 | J37: =G37+H37+I37 -> 92.526469 | L37: =J37-K37 -> 92.526469
A38: 32 | B38: CHUM CHANDARIN | D38: MEMBER | E38: 45387 | G38: 206.01675 | H38: 15 | I38: =G38*0.83% -> 1.709939 | J38: =G38+H38+I38 -> 222.72669 | L38: =J38-K38 -> 222.72669
A39: 33 | B39: PEANH KOEUN | D39: MEMBER | E39: 45383 | G39: 61.258864 | H39: 10 | I39: =G39*0.83% -> 0.50844857 | J39: =G39+H39+I39 -> 71.767313 | L39: =J39-K39 -> 71.767313
A40: 34 | B40: YANG SOPHORN | D40: MEMBER | E40: 45331 | G40: 152.51773 | I40: =G40*0.83% -> 1.2658971 | J40: =G40+H40+I40 -> 153.78363 | L40: =J40-K40 -> 153.78363
A41: 35 | B41: RO VANNAK | D41: MEMBER | E41: 45330 | G41: 51.258864 | I41: =G41*0.83% -> 0.42544857 | J41: =G41+H41+I41 -> 51.684313 | L41: =J41-K41 -> 51.684313
A42: 36 | B42: SENG VANLY | D42: MEMBER | E42: 45333 | G42: 138.14716 | I42: =G42*0.83% -> 1.1466214 | J42: =G42+H42+I42 -> 139.29378 | L42: =J42-K42 -> 139.29378
A43: 37 | B43: YORNG SOKHAI | D43: MEMBER | E43: 45386 | G43: 138.99801 | H43: 10 | I43: =G43*0.83% -> 1.1536835 | J43: =G43+H43+I43 -> 150.1517 | L43: =J43-K43 -> 150.1517
A44: 38 | B44: MENGHAK VICHHAY | D44: MEMBER | E44: 45333 | G44: 51.779961 | I44: =G44*0.83% -> 0.42977368 | J44: =G44+H44+I44 -> 52.209735 | L44: =J44-K44 -> 52.209735
A45: 39 | B45: SIM SUNNARY | D45: MEMBER | E45: 45245 | G45: 20.758103 | I45: =G45*0.83% -> 0.17229225 | J45: =G45+H45+I45 -> 20.930395 | L45: =J45-K45 -> 20.930395
A46: 40 | B46: AN NITH | D46: MEMBER | E46: 45293 | G46: 10.166689 | I46: =G46*0.83% -> 0.084383518 | J46: =G46+H46+I46 -> 10.251072 | L46: =J46-K46 -> 10.251072
A47: 41 | B47: SRENG SAREN | D47: MEMBER | E47: 45383 | G47: 151.24844 | H47: 50 | I47: =G47*0.83% -> 1.2553621 | J47: =G47+H47+I47 -> 202.50381 | L47: =J47-K47 -> 202.50381
A48: 42 | B48: LAUT PHEAKDEY | D48: MEMBER | E48: 45303 | G48: 20.333378 | I48: =G48*0.83% -> 0.16876704 | J48: =G48+H48+I48 -> 20.502145 | L48: =J48-K48 -> 20.502145
A49: 43 | B49: KRUY BOPHA | D49: MEMBER | E49: 45392 | G49: 20.083 | H49: 10 | I49: =G49*0.83% -> 0.1666889 | J49: =G49+H49+I49 -> 30.249689 | L49: =J49-K49 -> 30.249689
A50: 44 | B50: HORN RITHY | D50: MEMBER | E50: 45324 | G50: 10.083 | I50: =G50*0.83% -> 0.0836889 | J50: =G50+H50+I50 -> 10.166689 | L50: =J50-K50 -> 10.166689
A51: 45 | B51: SAY SAMPOLIDA | D51: MEMBER | E51: 45332 | G51: 10.083 | I51: =G51*0.83% -> 0.0836889 | J51: =G51+H51+I51 -> 10.166689 | L51: =J51-K51 -> 10.166689
A52: 46 | B52: CHHEAV NAK | D52: MEMBER | E52: 45387 | G52: 10 | H52: 40 | I52: =G52*0.83% -> 0.083 | J52: =G52+H52+I52 -> 50.083 | L52: =J52-K52 -> 50.083
A53: 47 | B53: CHUN SOKTHOUTHEAREACH | D53: MEMBER | E53: 45357 | G53: 150 | H53: 25 | I53: =G53*0.83% -> 1.245 | J53: =G53+H53+I53 -> 176.245 | L53: =J53-K53 -> 176.245
A54: 48 | B54: MENG SOTHY VATNAK | D54: MEMBER | E54: 45359 | G54: 20 | I54: =G54*0.83% -> 0.166 | J54: =G54+H54+I54 -> 20.166 | L54: =J54-K54 -> 20.166
A55: 49 | B55: HUN SOT | D55: MEMBER | E55: 45384 | G55: 10 | H55: 10 | I55: =G55*0.83% -> 0.083 | J55: =G55+H55+I55 -> 20.083 | L55: =J55-K55 -> 20.083
A56: 50 | B56: KET SOKSEILA | D56: MEMBER | E56: 45393 | G56: 50 | H56: 50 | I56: =G56*0.83% -> 0.415 | J56: =G56+H56+I56 -> 100.415 | L56: =J56-K56 -> 100.415
A57: 50 | B57: UM SAROM | D57: MEMBER | E57: 45383 | H57: 5 | J57: =G57+H57+I57 -> 5 | L57: =J57-K57 -> 5
A58: 51 | B58: PHAL CHANTHA | D58: MEMBER | E58: 45384 | H58: 20 | J58: =G58+H58+I58 -> 20 | L58: =J58-K58 -> 20
A59: 52 | B59: VA SARA | D59: MEMBER | E59: 45390 | F59: ATH THORN | H59: 10 | J59: =G59+H59+I59 -> 10 | L59: =J59-K59 -> 10
A60: 53 | B60: KET LENG | D60: MEMBER | E60: 45390 | F60: ATH THORN | H60: 10 | J60: =G60+H60+I60 -> 10 | L60: =J60-K60 -> 10
A61: 54 | B61: EAN OUN | D61: MEMBER | E61: 45390 | F61: ATH THORN | H61: 10 | J61: =G61+H61+I61 -> 10 | L61: =J61-K61 -> 10
G64: =SUM(G7:G59) -> 45058.855 | H64: =SUM(H7:H63) -> 1178.04 | I64: =SUM(I7:I57) -> 373.98849 | J64: =SUM(J7:J59) -> 46590.883 | K64: =SUM(K7:K55) -> 0 | L64: =SUM(L7:L59) -> 46590.883

Sheet May-24
A1: SANSAM SAVING GROUP
A2: SAVING FROM 5USD PER MONTH BY GETTING INTEREST 10% PER YEAR
A3: SAVING DEPOSIT FROM 1ST - 10TH EVERY MONTH
A4: ACCESSIBLE LOAN ON 15TH EACH MONTH
A5: SAVING IN MAY 2024
A6: NO | B6: NAME | C6: SEX | D6: ROLE | E6: SAVING DATE | F6: TEAM LEADER | G6: CAPITAL | H6: SAVING | I6: INTEREST | J6: BALANCE | K6: WITHDRAWAL | L6: TOTAL
A7: 1 | B7: ATH THORN | C7: M | D7: FOUNDER | E7: 45422 | G7: 4416.0175 | H7: 26.54 | I7: =G7*0.83% -> 36.652945 | J7: =G7+H7+I7 -> 4479.2104 | L7: =J7-K7 -> 4479.2104
A8: 2 | B8: PECH PISEY | C8: M | D8: FOUNDER | E8: 45422 | G8: 6998.653 | H8: 50 | I8: =G8*0.83% -> 58.088819 | J8: =G8+H8+I8 -> 7106.7418 | L8: =J8-K8 -> 7106.7418
A9: 3 | B9: HONG REAKSMEY | C9: M | D9: FOUNDER | E9: 45423 | G9: 6987.2126 | H9: 100 | I9: =G9*0.83% -> 57.993865 | J9: =G9+H9+I9 -> 7145.2065 | L9: =J9-K9 -> 7145.2065
A10: 4 | B10: SIN PUTHEARY | C10: F | D10: FOUNDER | E10: 45171 | G10: 2976.5635 | I10: =G10*0.83% -> 24.705477 | J10: =G10+H10+I10 -> 3001.2689 | L10: =J10-K10 -> 3001.2689
A11: 5 | B11: PAO VORN | C11: M | D11: FOUNDER | E11: 45239 | G11: 447.50081 | I11: =G11*0.83% -> 3.7142567 | J11: =G11+H11+I11 -> 451.21507 | L11: =J11-K11 -> 451.21507
A12: 6 | B12: SOR MORA | C12: M | D12: FOUNDER | E12: 45383 | G12: 2580.2731 | I12: =G12*0.83% -> 21.416267 | J12: =G12+H12+I12 -> 2601.6894 | L12: =J12-K12 -> 2601.6894
A13: 7 | B13: NOP VY | C13: M | D13: FOUNDER | E13: 45422 | G13: 6796.0334 | H13: 60.56 | I13: =G13*0.83% -> 56.407077 | J13: =G13+H13+I13 -> 6913.0005 | L13: =J13-K13 -> 6913.0005
A14: 8 | B14: OU RITHTY | C14: M | D14: FOUNDER | E14: 45414 | G14: 6437.3433 | H14: 100 | I14: =G14*0.83% -> 53.429949 | J14: =G14+H14+I14 -> 6590.7732 | L14: =J14-K14 -> 6590.7732
A15: 9 | B15: SENG RITHY | C15: M | D15: MEMBER | E15: 45418 | F15: NOP VY | G15: 89.559699 | H15: 10 | I15: =G15*0.83% -> 0.74334551 | J15: =G15+H15+I15 -> 100.30304 | L15: =J15-K15 -> 100.30304
A16: 10 | B16: OU TEP PHALLIN | C16: F | D16: MEMBER | E16: 45383 | F16: OU RITHY | G16: 283.77041 | I16: =G16*0.83% -> 2.3552944 | J16: =G16+H16+I16 -> 286.12571 | L16: =J16-K16 -> 286.12571
A17: 11 | B17: YIM BUNTHENG | C17: M | D17: MEMBER | E17: 45294 | F17: HONG REAKSMEY | G17: 96.196443 | I17: =G17*0.83% -> 0.79843048 | J17: =G17+H17+I17 -> 96.994874 | L17: =J17-K17 -> 96.994874
A18: 12 | B18: THENG SAVOEUN | C18: M | D18: MEMBER | E18: 45029 | F18: NOP VY | G18: 83.74097 | I18: =G18*0.83% -> 0.69505005 | J18: =G18+H18+I18 -> 84.43602 | L18: =J18-K18 -> 84.43602
A19: 13 | B19: UL VANN | C19: M | D19: MEMBER | E19: 45387 | F19: NOP VY | G19: 190.30696 | I19: =G19*0.83% -> 1.5795478 | J19: =G19+H19+I19 -> 191.88651 | L19: =J19-K19 -> 191.88651
A20: 14 | B20: SIYONN SOTHEARITH | C20: M | D20: MEMBER | E20: 45414 | F20: HONG REAKSMEY | G20: 1164.7638 | H20: 100 | I20: =G20*0.83% -> 9.6675397 | J20: =G20+H20+I20 -> 1274.4314 | L20: =J20-K20 -> 1274.4314
A21: 15 | B21: YEAN REAKSMEY | C21: M | D21: MEMBER | E21: 45386 | F21: PECH PISEY | G21: 142.97265 | I21: =G21*0.83% -> 1.186673 | J21: =G21+H21+I21 -> 144.15932 | L21: =J21-K21 -> 144.15932
A22: 16 | B22: SAM SOMONY | C22: M | D22: MEMBER | E22: 45415 | F22: NOP VY | G22: 1250.201 | H22: 50 | I22: =G22*0.83% -> 10.376668 | J22: =G22+H22+I22 -> 1310.5776 | L22: =J22-K22 -> 1310.5776
A23: 17 | B23: KOY MAQUIS | C23: M | D23: MEMBER | E23: 45414 | F23: HONG REAKSMEY | G23: 215.80602 | H23: 10 | I23: =G23*0.83% -> 1.7911899 | J23: =G23+H23+I23 -> 227.59721 | L23: =J23-K23 -> 227.59721
A24: 18 | B24: LY MALIN | C24: F | D24: MEMBER | E24: 45427 | F24: OU RITHY | G24: 504.41346 | H24: 40 | I24: =G24*0.83% -> 4.1866317 | J24: =G24+H24+I24 -> 548.60009 | L24: =J24-K24 -> 548.60009
A25: 19 | B25: VAN BUNNA | C25: M | D25: MEMBER | E25: 45388 | F25: PECH PISEY | G25: 222.32029 | I25: =G25*0.83% -> 1.8452584 | J25: =G25+H25+I25 -> 224.16555 | L25: =J25-K25 -> 224.16555
A26: 20 | B26: CHAN THEARA | C26: F | D26: MEMBER | E26: 45386 | F26: HONG REAKSMEY | G26: 78.448838 | I26: =G26*0.83% -> 0.65112535 | J26: =G26+H26+I26 -> 79.099963 | L26: =J26-K26 -> 79.099963
A27: 21 | B27: LONG BORIN | C27: F | D27: MEMBER | E27: 45140 | F27: NOP VY | G27: 115.152 | I27: =G27*0.83% -> 0.95576161 | J27: =G27+H27+I27 -> 116.10776 | L27: =J27-K27 -> 116.10776
A28: 22 | B28: SOEUNG SAROEUN | C28: M | D28: MEMBER | E28: 45235 | F28: NOP VY | G28: 135.57171 | I28: =G28*0.83% -> 1.1252452 | J28: =G28+H28+I28 -> 136.69696 | L28: =J28-K28 -> 136.69696
A29: 23 | B29: TUY SYTHIENG | C29: M | D29: MEMBER | E29: 45422 | F29: OU RITHY | G29: 779.80042 | H29: 100 | I29: =G29*0.83% -> 6.4723435 | J29: =G29+H29+I29 -> 886.27276 | L29: =J29-K29 -> 886.27276
A30: 24 | B30: CHHEOUNG VEASNA | C30: M | D30: MEMBER | E30: 45420 | F30: SAM SOMONY | G30: 539.97422 | H30: 100 | I30: =G30*0.83% -> 4.4817861 | J30: =G30+H30+I30 -> 644.45601 | L30: =J30-K30 -> 644.45601
A31: 25 | B31: OM MANITH | C31: M | D31: MEMBER | E31: 45383 | F31: OU RITHY | G31: 41.986698 | I31: =G31*0.83% -> 0.34848959 | J31: =G31+H31+I31 -> 42.335187 | L31: =J31-K31 -> 42.335187
A32: 26 | B32: IM SOTHY | C32: M | D32: MEMBER | E32: 45209 | F32: PECH PISEY | G32: 64.380892 | I32: =G32*0.83% -> 0.5343614 | J32: =G32+H32+I32 -> 64.915254 | L32: =J32-K32 -> 64.915254
A33: 27 | B33: PA CHANROEUN | C33: M | D33: MEMBER | E33: 45085 | F33: NOP VY | G33: 215.44573 | I33: =G33*0.83% -> 1.7881996 | J33: =G33+H33+I33 -> 217.23393 | L33: =J33-K33 -> 217.23393
A34: 28 | B34: HENG SOCHEA | C34: F | D34: MEMBER | E34: 45427 | F34: OU RITHY | G34: 36.394918 | H34: 30 | I34: =G34*0.83% -> 0.30207782 | J34: =G34+H34+I34 -> 66.696996 | L34: =J34-K34 -> 66.696996
A35: 29 | B35: TUM SOKRAKSA | C35: F | D35: MEMBER | E35: 45235 | G35: 1043.4958 | I35: =G35*0.83% -> 8.6610148 | J35: =G35+H35+I35 -> 1052.1568 | L35: =J35-K35 -> 1052.1568
A36: 30 | B36: SDEUNG PHEARONG | D36: MEMBER | E36: 45235 | G36: 15.676886 | I36: =G36*0.83% -> 0.13011815 | J36: =G36+H36+I36 -> 15.807004 | L36: =J36-K36 -> 15.807004
A37: 31 | B37: TY SAMPHORS VICHEKA | D37: MEMBER | E37: 45416 | G37: 92.526469 | H37: 15 | I37: =G37*0.83% -> 0.76796969 | J37: =G37+H37+I37 -> 108.29444 | L37: =J37-K37 -> 108.29444
A38: 32 | B38: CHUM CHANDARIN | D38: MEMBER | E38: 45420 | G38: 222.72669 | H38: 5 | I38: =G38*0.83% -> 1.8486315 | J38: =G38+H38+I38 -> 229.57532 | L38: =J38-K38 -> 229.57532
A39: 33 | B39: PEANH KOEUN | D39: MEMBER | E39: 45414 | G39: 71.767313 | H39: 10 | I39: =G39*0.83% -> 0.59566869 | J39: =G39+H39+I39 -> 82.362981 | L39: =J39-K39 -> 82.362981
A40: 34 | B40: YANG SOPHORN | D40: MEMBER | E40: 45414 | G40: 153.78363 | H40: 50 | I40: =G40*0.83% -> 1.2764041 | J40: =G40+H40+I40 -> 205.06003 | L40: =J40-K40 -> 205.06003
A41: 35 | B41: RO VANNAK | D41: MEMBER | E41: 45330 | G41: 51.684313 | I41: =G41*0.83% -> 0.42897979 | J41: =G41+H41+I41 -> 52.113292 | L41: =J41-K41 -> 52.113292
A42: 36 | B42: SENG VANLY | D42: MEMBER | E42: 45333 | G42: 139.29378 | I42: =G42*0.83% -> 1.1561384 | J42: =G42+H42+I42 -> 140.44992 | L42: =J42-K42 -> 140.44992
A43: 37 | B43: YORNG SOKHAI | D43: MEMBER | E43: 45418 | G43: 150.1517 | H43: 15 | I43: =G43*0.83% -> 1.2462591 | J43: =G43+H43+I43 -> 166.39796 | L43: =J43-K43 -> 166.39796
A44: 38 | B44: MENGHAK VICHHAY | D44: MEMBER | E44: 45333 | G44: 52.209735 | I44: =G44*0.83% -> 0.4333408 | J44: =G44+H44+I44 -> 52.643076 | L44: =J44-K44 -> 52.643076
A45: 39 | B45: SIM SUNNARY | D45: MEMBER | E45: 45245 | G45: 20.930395 | I45: =G45*0.83% -> 0.17372228 | J45: =G45+H45+I45 -> 21.104117 | L45: =J45-K45 -> 21.104117
A46: 40 | B46: AN NITH | D46: MEMBER | E46: 45293 | G46: 10.251072 | I46: =G46*0.83% -> 0.085083901 | J46: =G46+H46+I46 -> 10.336156 | L46: =J46-K46 -> 10.336156
A47: 41 | B47: SRENG SAREN | D47: MEMBER | E47: 45414 | G47: 202.50381 | H47: 50 | I47: =G47*0.83% -> 1.6807816 | J47: =G47+H47+I47 -> 254.18459 | L47: =J47-K47 -> 254.18459
A48: 42 | B48: LAUT PHEAKDEY | D48: MEMBER | E48: 45303 | G48: 20.502145 | I48: =G48*0.83% -> 0.1701678 | J48: =G48+H48+I48 -> 20.672313 | L48: =J48-K48 -> 20.672313
A49: 43 | B49: KRUY BOPHA | D49: MEMBER | E49: 45419 | G49: 30.249689 | H49: 10 | I49: =G49*0.83% -> 0.25107242 | J49: =G49+H49+I49 -> 40.500761 | L49: =J49-K49 -> 40.500761
A50: 44 | B50: HORN RITHY | D50: MEMBER | E50: 45324 | G50: 10.166689 | I50: =G50*0.83% -> 0.084383518 | J50: =G50+H50+I50 -> 10.251072 | L50: =J50-K50 -> 10.251072
A51: 45 | B51: SAY SAMPOLIDA | D51: MEMBER | E51: 45332 | G51: 10.166689 | I51: =G51*0.83% -> 0.084383518 | J51: =G51+H51+I51 -> 10.251072 | L51: =J51-K51 -> 10.251072
A52: 46 | B52: CHHEAV NAK | D52: MEMBER | E52: 45423 | G52: 50.083 | H52: 50 | I52: =G52*0.83% -> 0.4156889 | J52: =G52+H52+I52 -> 100.49869 | L52: =J52-K52 -> 100.49869
A53: 47 | B53: CHUN SOKTHOUTHEAREACH | D53: MEMBER | E53: 45420 | G53: 176.245 | H53: 25 | I53: =G53*0.83% -> 1.4628335 | J53: =G53+H53+I53 -> 202.70783 | L53: =J53-K53 -> 202.70783
A54: 48 | B54: MENG SOTHY VATNAK | D54: MEMBER | E54: 45420 | G54: 20.166 | H54: 20 | I54: =G54*0.83% -> 0.1673778 | J54: =G54+H54+I54 -> 40.333378 | L54: =J54-K54 -> 40.333378
A55: 49 | B55: HUN SOT | D55: MEMBER | E55: 45414 | G55: 20.083 | H55: 10 | I55: =G55*0.83% -> 0.1666889 | J55: =G55+H55+I55 -> 30.249689 | L55: =J55-K55 -> 30.249689
A56: 50 | B56: KET SOKSEILA | D56: MEMBER | E56: 45423 | F56: TUM SOKRAKSA | G56: 100.415 | H56: 150 | I56: =G56*0.83% -> 0.8334445 | J56: =G56+H56+I56 -> 251.24844 | L56: =J56-K56 -> 251.24844
A57: 50 | B57: UM SAROM | D57: MEMBER | E57: 45420 | G57: 5 | H57: 10 | I57: =G57*0.83% -> 0.0415 | J57: =G57+H57+I57 -> 15.0415 | L57: =J57-K57 -> 15.0415
A58: 51 | B58: PHAL CHANTHA | D58: MEMBER | E58: 45418 | G58: 20 | H58: 30 | I58: =G58*0.83% -> 0.166 | J58: =G58+H58+I58 -> 50.166 | L58: =J58-K58 -> 50.166
A59: 52 | B59: VA SARA | D59: MEMBER | E59: 45390 | F59: ATH THORN | G59: 10 | H59: 10 | I59: =G59*0.83% -> 0.083 | J59: =G59+H59+I59 -> 20.083 | L59: =J59-K59 -> 20.083
A60: 53 | B60: KET LENG | D60: MEMBER | E60: 45390 | F60: ATH THORN | G60: 10 | H60: 10 | I60: =G60*0.83% -> 0.083 | J60: =G60+H60+I60 -> 20.083 | L60: =J60-K60 -> 20.083
A61: 54 | B61: EAN OUN | D61: MEMBER | E61: 45390 | F61: ATH THORN | G61: 10 | H61: 10 | I61: =G61*0.83% -> 0.083 | J61: =G61+H61+I61 -> 20.083 | L61: =J61-K61 -> 20.083
A62: 55 | B62: IEN SOPHOEURN | D62: MEMBER | E62: 45420 | H62: 10 | I62: =G62*0.83% -> 0 | J62: =G62+H62+I62 -> 10 | L62: =J62-K62 -> 10
G69: =SUM(G7:G59) -> 46590.883 | H69: =SUM(H7:H68) -> 1267.1 | I69: =SUM(I7:I57) -> 386.45533 | J69: =SUM(J7:J59) -> 48214.687 | K69: =SUM(K7:K55) -> 0 | L69: =SUM(L7:L59) -> 48214.687

Sheet Jun-24
A1: SANSAM SAVING GROUP
A2: SAVING FROM 5USD PER MONTH BY GETTING INTEREST 10% PER YEAR
A3: SAVING DEPOSIT FROM 1ST - 10TH EVERY MONTH
A4: ACCESSIBLE LOAN ON 15TH EACH MONTH
A5: SAVING IN Jun 2024
A6: NO | B6: NAME | C6: SEX | D6: ROLE | E6: SAVING DATE | F6: TEAM LEADER | G6: CAPITAL | H6: SAVING | I6: INTEREST | J6: BALANCE | K6: WITHDRAWAL | L6: TOTAL
A7: 1 | B7: ATH THORN | C7: M | D7: FOUNDER | E7: 45422 | G7: 4479.2104 | I7: =G7*0.83% -> 37.177446 | J7: =G7+H7+I7 -> 4516.3879 | L7: =J7-K7 -> 4516.3879
A8: 2 | B8: PECH PISEY | C8: M | D8: FOUNDER | E8: 45422 | G8: 7106.7418 | I8: =G8*0.83% -> 58.985957 | J8: =G8+H8+I8 -> 7165.7277 | L8: =J8-K8 -> 7165.7277
A9: 3 | B9: HONG REAKSMEY | C9: M | D9: FOUNDER | E9: 45423 | G9: 7145.2065 | H9: 100 | I9: =G9*0.83% -> 59.305214 | J9: =G9+H9+I9 -> 7304.5117 | L9: =J9-K9 -> 7304.5117
A10: 4 | B10: SIN PUTHEARY | C10: F | D10: FOUNDER | E10: 45171 | G10: 3001.2689 | I10: =G10*0.83% -> 24.910532 | J10: =G10+H10+I10 -> 3026.1795 | L10: =J10-K10 -> 3026.1795
A11: 5 | B11: PAO VORN | C11: M | D11: FOUNDER | E11: 45239 | G11: 451.21507 | H11: 30 | I11: =G11*0.83% -> 3.7450851 | J11: =G11+H11+I11 -> 484.96015 | L11: =J11-K11 -> 484.96015
A12: 6 | B12: SOR MORA | C12: M | D12: FOUNDER | E12: 45383 | G12: 2601.6894 | H12: 25 | I12: =G12*0.83% -> 21.594022 | J12: =G12+H12+I12 -> 2648.2834 | L12: =J12-K12 -> 2648.2834
A13: 7 | B13: NOP VY | C13: M | D13: FOUNDER | E13: 45422 | G13: 6913.0005 | H13: 63.88 | I13: =G13*0.83% -> 57.377904 | J13: =G13+H13+I13 -> 7034.2584 | L13: =J13-K13 -> 7034.2584
A14: 8 | B14: OU RITHTY | C14: M | D14: FOUNDER | E14: 45814 | G14: 6590.7732 | H14: 50 | I14: =G14*0.83% -> 54.703418 | J14: =G14+H14+I14 -> 6695.4766 | L14: =J14-K14 -> 6695.4766
A15: 9 | B15: SENG RITHY | C15: M | D15: MEMBER | E15: 45418 | F15: NOP VY | G15: 100.30304 | H15: 10 | I15: =G15*0.83% -> 0.83251527 | J15: =G15+H15+I15 -> 111.13556 | L15: =J15-K15 -> 111.13556
A16: 10 | B16: OU TEP PHALLIN | C16: F | D16: MEMBER | E16: 45383 | F16: OU RITHY | G16: 286.12571 | I16: =G16*0.83% -> 2.3748434 | J16: =G16+H16+I16 -> 288.50055 | L16: =J16-K16 -> 288.50055
A17: 11 | B17: YIM BUNTHENG | C17: M | D17: MEMBER | E17: 45294 | F17: HONG REAKSMEY | G17: 96.994874 | I17: =G17*0.83% -> 0.80505745 | J17: =G17+H17+I17 -> 97.799931 | L17: =J17-K17 -> 97.799931
A18: 12 | B18: THENG SAVOEUN | C18: M | D18: MEMBER | E18: 45029 | F18: NOP VY | G18: 84.43602 | I18: =G18*0.83% -> 0.70081897 | J18: =G18+H18+I18 -> 85.136839 | L18: =J18-K18 -> 85.136839
A19: 13 | B19: UL VANN | C19: M | D19: MEMBER | E19: 45387 | F19: NOP VY | G19: 191.88651 | H19: 20 | I19: =G19*0.83% -> 1.592658 | J19: =G19+H19+I19 -> 213.47916 | L19: =J19-K19 -> 213.47916
A20: 14 | B20: SIYONN SOTHEARITH | C20: M | D20: MEMBER | E20: 45445 | F20: HONG REAKSMEY | G20: 1274.4314 | H20: 100 | I20: =G20*0.83% -> 10.57778 | J20: =G20+H20+I20 -> 1385.0091 | L20: =J20-K20 -> 1385.0091
A21: 15 | B21: YEAN REAKSMEY | C21: M | D21: MEMBER | E21: 45386 | F21: PECH PISEY | G21: 144.15932 | H21: 15 | I21: =G21*0.83% -> 1.1965224 | J21: =G21+H21+I21 -> 160.35584 | L21: =J21-K21 -> 160.35584
A22: 16 | B22: SAM SOMONY | C22: M | D22: MEMBER | E22: 45415 | F22: NOP VY | G22: 1310.5776 | H22: 50 | I22: =G22*0.83% -> 10.877794 | J22: =G22+H22+I22 -> 1371.4554 | L22: =J22-K22 -> 1371.4554
A23: 17 | B23: KOY MAQUIS | C23: M | D23: MEMBER | E23: 45414 | F23: HONG REAKSMEY | G23: 227.59721 | H23: 20 | I23: =G23*0.83% -> 1.8890568 | J23: =G23+H23+I23 -> 249.48626 | L23: =J23-K23 -> 249.48626
A24: 18 | B24: LY MALIN | C24: F | D24: MEMBER | E24: 45427 | F24: OU RITHY | G24: 548.60009 | H24: 40 | I24: =G24*0.83% -> 4.5533808 | J24: =G24+H24+I24 -> 593.15347 | L24: =J24-K24 -> 593.15347
A25: 19 | B25: VAN BUNNA | C25: M | D25: MEMBER | E25: 45388 | F25: PECH PISEY | G25: 224.16555 | I25: =G25*0.83% -> 1.8605741 | J25: =G25+H25+I25 -> 226.02612 | L25: =J25-K25 -> 226.02612
A26: 20 | B26: CHAN THEARA | C26: F | D26: MEMBER | E26: 45386 | F26: HONG REAKSMEY | G26: 79.099963 | I26: =G26*0.83% -> 0.65652969 | J26: =G26+H26+I26 -> 79.756493 | L26: =J26-K26 -> 79.756493
A27: 21 | B27: LONG BORIN | C27: F | D27: MEMBER | E27: 45140 | F27: NOP VY | G27: 116.10776 | I27: =G27*0.83% -> 0.96369443 | J27: =G27+H27+I27 -> 117.07146 | L27: =J27-K27 -> 117.07146
A28: 22 | B28: SOEUNG SAROEUN | C28: M | D28: MEMBER | E28: 45235 | F28: NOP VY | G28: 136.69696 | I28: =G28*0.83% -> 1.1345847 | J28: =G28+H28+I28 -> 137.83154 | L28: =J28-K28 -> 137.83154
A29: 23 | B29: TUY SYTHIENG | C29: M | D29: MEMBER | E29: 45422 | F29: OU RITHY | G29: 886.27276 | H29: 100 | I29: =G29*0.83% -> 7.3560639 | J29: =G29+H29+I29 -> 993.62883 | L29: =J29-K29 -> 993.62883
A30: 24 | B30: CHHEOUNG VEASNA | C30: M | D30: MEMBER | E30: 45420 | F30: SAM SOMONY | G30: 644.45601 | I30: =G30*0.83% -> 5.3489849 | J30: =G30+H30+I30 -> 649.805 | L30: =J30-K30 -> 649.805
A31: 25 | B31: OM MANITH | C31: M | D31: MEMBER | E31: 45383 | F31: OU RITHY | G31: 42.335187 | I31: =G31*0.83% -> 0.35138205 | J31: =G31+H31+I31 -> 42.686569 | L31: =J31-K31 -> 42.686569
A32: 26 | B32: IM SOTHY | C32: M | D32: MEMBER | E32: 45209 | F32: PECH PISEY | G32: 64.915253 | I32: =G32*0.83% -> 0.5387966 | J32: =G32+H32+I32 -> 65.45405 | L32: =J32-K32 -> 65.45405
A33: 27 | B33: PA CHANROEUN | C33: M | D33: MEMBER | E33: 45085 | F33: NOP VY | G33: 217.23393 | I33: =G33*0.83% -> 1.8030417 | J33: =G33+H33+I33 -> 219.03698 | L33: =J33-K33 -> 219.03698
A34: 28 | B34: HENG SOCHEA | C34: F | D34: MEMBER | E34: 45427 | F34: OU RITHY | G34: 66.696996 | I34: =G34*0.83% -> 0.55358507 | J34: =G34+H34+I34 -> 67.250581 | L34: =J34-K34 -> 67.250581
A35: 29 | B35: TUM SOKRAKSA | C35: F | D35: MEMBER | E35: 45235 | G35: 1052.1568 | I35: =G35*0.83% -> 8.7329013 | J35: =G35+H35+I35 -> 1060.8897 | L35: =J35-K35 -> 1060.8897
A36: 30 | B36: SDEUNG PHEARONG | D36: MEMBER | E36: 45235 | G36: 15.807004 | I36: =G36*0.83% -> 0.13119813 | J36: =G36+H36+I36 -> 15.938202 | L36: =J36-K36 -> 15.938202
A37: 31 | B37: TY SAMPHORS VICHEKA | D37: MEMBER | E37: 45416 | G37: 108.29444 | I37: =G37*0.83% -> 0.89884384 | J37: =G37+H37+I37 -> 109.19328 | L37: =J37-K37 -> 109.19328
A38: 32 | B38: CHUM CHANDARIN | D38: MEMBER | E38: 45420 | G38: 229.57532 | H38: 5 | I38: =G38*0.83% -> 1.9054751 | J38: =G38+H38+I38 -> 236.48079 | L38: =J38-K38 -> 236.48079
A39: 33 | B39: PEANH KOEUN | D39: MEMBER | E39: 45414 | G39: 82.362981 | I39: =G39*0.83% -> 0.68361275 | J39: =G39+H39+I39 -> 83.046594 | L39: =J39-K39 -> 83.046594
A40: 34 | B40: YANG SOPHORN | D40: MEMBER | E40: 45414 | G40: 205.06003 | I40: =G40*0.83% -> 1.7019982 | J40: =G40+H40+I40 -> 206.76203 | L40: =J40-K40 -> 206.76203
A41: 35 | B41: RO VANNAK | D41: MEMBER | E41: 45330 | G41: 52.113292 | H41: 5 | I41: =G41*0.83% -> 0.43254033 | J41: =G41+H41+I41 -> 57.545833 | L41: =J41-K41 -> 57.545833
A42: 36 | B42: SENG VANLY | D42: MEMBER | E42: 45333 | G42: 140.44992 | H42: 25 | I42: =G42*0.83% -> 1.1657343 | J42: =G42+H42+I42 -> 166.61565 | L42: =J42-K42 -> 166.61565
A43: 37 | B43: YORNG SOKHAI | D43: MEMBER | E43: 45418 | G43: 166.39796 | I43: =G43*0.83% -> 1.381103 | J43: =G43+H43+I43 -> 167.77906 | L43: =J43-K43 -> 167.77906
A44: 38 | B44: MENGHAK VICHHAY | D44: MEMBER | E44: 45333 | G44: 52.643076 | I44: =G44*0.83% -> 0.43693753 | J44: =G44+H44+I44 -> 53.080013 | L44: =J44-K44 -> 53.080013
A45: 39 | B45: SIM SUNNARY | D45: MEMBER | E45: 45245 | G45: 21.104117 | I45: =G45*0.83% -> 0.17516417 | J45: =G45+H45+I45 -> 21.279281 | L45: =J45-K45 -> 21.279281
A46: 40 | B46: AN NITH | D46: MEMBER | E46: 45293 | G46: 10.336156 | I46: =G46*0.83% -> 0.085790097 | J46: =G46+H46+I46 -> 10.421946 | L46: =J46-K46 -> 10.421946
A47: 41 | B47: SRENG SAREN | D47: MEMBER | E47: 45414 | G47: 254.18459 | H47: 50 | I47: =G47*0.83% -> 2.1097321 | J47: =G47+H47+I47 -> 306.29432 | L47: =J47-K47 -> 306.29432
A48: 42 | B48: LAUT PHEAKDEY | D48: MEMBER | E48: 45303 | G48: 20.672313 | I48: =G48*0.83% -> 0.17158019 | J48: =G48+H48+I48 -> 20.843893 | L48: =J48-K48 -> 20.843893
A49: 43 | B49: KRUY BOPHA | D49: MEMBER | E49: 45419 | G49: 40.500761 | H49: 10 | I49: =G49*0.83% -> 0.33615632 | J49: =G49+H49+I49 -> 50.836918 | L49: =J49-K49 -> 50.836918
A50: 44 | B50: HORN RITHY | D50: MEMBER | E50: 45324 | G50: 10.251072 | I50: =G50*0.83% -> 0.085083901 | J50: =G50+H50+I50 -> 10.336156 | L50: =J50-K50 -> 10.336156
A51: 45 | B51: SAY SAMPOLIDA | D51: MEMBER | E51: 45332 | G51: 10.251072 | I51: =G51*0.83% -> 0.085083901 | J51: =G51+H51+I51 -> 10.336156 | L51: =J51-K51 -> 10.336156
A52: 46 | B52: CHHEAV NAK | D52: MEMBER | E52: 45423 | G52: 100.49869 | I52: =G52*0.83% -> 0.83413912 | J52: =G52+H52+I52 -> 101.33283 | L52: =J52-K52 -> 101.33283
A53: 47 | B53: CHUN SOKTHOUTHEAREACH | D53: MEMBER | E53: 45420 | G53: 202.70783 | H53: 10 | I53: =G53*0.83% -> 1.682475 | J53: =G53+H53+I53 -> 214.39031 | L53: =J53-K53 -> 214.39031
A54: 48 | B54: MENG SOTHY VATNAK | D54: MEMBER | E54: 45420 | G54: 40.333378 | I54: =G54*0.83% -> 0.33476704 | J54: =G54+H54+I54 -> 40.668145 | L54: =J54-K54 -> 40.668145
A55: 49 | B55: HUN SOT | D55: MEMBER | E55: 45414 | G55: 30.249689 | H55: 10 | I55: =G55*0.83% -> 0.25107242 | J55: =G55+H55+I55 -> 40.500761 | L55: =J55-K55 -> 40.500761
A56: 50 | B56: KET SOKSEILA | D56: MEMBER | E56: 45453 | F56: TUM SOKRAKSA | G56: 251.24844 | H56: 320 | I56: =G56*0.83% -> 2.0853621 | J56: =G56+H56+I56 -> 573.33381 | L56: =J56-K56 -> 573.33381
A57: 50 | B57: UM SAROM | D57: MEMBER | E57: 45420 | G57: 15.0415 | I57: =G57*0.83% -> 0.12484445 | J57: =G57+H57+I57 -> 15.166344 | L57: =J57-K57 -> 15.166344
A58: 51 | B58: PHAL CHANTHA | D58: MEMBER | E58: 45453 | G58: 50.166 | H58: 30 | I58: =G58*0.83% -> 0.4163778 | J58: =G58+H58+I58 -> 80.582378 | L58: =J58-K58 -> 80.582378
A59: 52 | B59: VA SARA | D59: MEMBER | E59: 45390 | F59: ATH THORN | G59: 20.083 | I59: =G59*0.83% -> 0.1666889 | J59: =G59+H59+I59 -> 20.249689 | L59: =J59-K59 -> 20.249689
A60: 53 | B60: KET LENG | D60: MEMBER | E60: 45390 | F60: ATH THORN | G60: 20.083 | I60: =G60*0.83% -> 0.1666889 | J60: =G60+H60+I60 -> 20.249689 | L60: =J60-K60 -> 20.249689
A61: 54 | B61: EAN OUN | D61: MEMBER | E61: 45390 | F61: ATH THORN | G61: 20.083 | I61: =G61*0.83% -> 0.1666889 | J61: =G61+H61+I61 -> 20.249689 | L61: =J61-K61 -> 20.249689
A62: 55 | B62: IEN SOPHOEURN | D62: MEMBER | E62: 45420 | G62: 10 | I62: =G62*0.83% -> 0.083 | J62: =G62+H62+I62 -> 10.083 | L62: =J62-K62 -> 10.083
G69: =SUM(G7:G59) -> 48214.687 | H69: =SUM(H7:H68) -> 1088.88 | I69: =SUM(I7:I57) -> 399.59884 | J69: =SUM(J7:J59) -> 49703.749 | K69: =SUM(K7:K55) -> 0 | L69: =SUM(L7:L59) -> 49703.749

Sheet Jul-24
A1: SANSAM SAVING GROUP
A2: SAVING FROM 5USD PER MONTH BY GETTING INTEREST 10% PER YEAR
A3: SAVING DEPOSIT FROM 1ST - 10TH EVERY MONTH
A4: ACCESSIBLE LOAN ON 15TH EACH MONTH
A5: SAVING IN Jul 2024
A6: NO | B6: NAME | C6: SEX | D6: ROLE | E6: SAVING DATE | F6: TEAM LEADER | G6: CAPITAL | H6: SAVING | I6: INTEREST | J6: BALANCE | K6: WITHDRAWAL | L6: TOTAL
A7: NO | B7: NAME | C7: SEX | D7: ROLE | E7: SAVING DATE | F7: TEAM LEADER | G7: CAPITAL | H7: SAVING | I7: INTEREST | J7: BALANCE | K7: WITHDRAWAL | L7: TOTAL
A8: 1 | B8: ATH THORN | C8: M | D8: FOUNDER | E8: 45422 | G8: 4516.3879 | I8: =G8*0.83% -> 37.486019 | J8: =G8+H8+I8 -> 4553.8739 | L8: =J8-K8 -> 4553.8739
A9: 2 | B9: PECH PISEY | C9: M | D9: FOUNDER | E9: 45483 | G9: 7165.7277 | H9: 100 | I9: =G9*0.83% -> 59.47554 | J9: =G9+H9+I9 -> 7325.2033 | L9: =J9-K9 -> 7325.2033
A10: 3 | B10: HONG REAKSMEY | C10: M | D10: FOUNDER | E10: 45483 | G10: 7304.5117 | H10: 50 | I10: =G10*0.83% -> 60.627447 | J10: =G10+H10+I10 -> 7415.1392 | L10: =J10-K10 -> 7415.1392
A11: 4 | B11: SIN PUTHEARY | C11: F | D11: FOUNDER | E11: 45171 | G11: 3026.1795 | I11: =G11*0.83% -> 25.11729 | J11: =G11+H11+I11 -> 3051.2968 | L11: =J11-K11 -> 3051.2968
A12: 5 | B12: PAO VORN | C12: M | D12: FOUNDER | E12: 45239 | G12: 484.96015 | I12: =G12*0.83% -> 4.0251693 | J12: =G12+H12+I12 -> 488.98532 | L12: =J12-K12 -> 488.98532
A13: 6 | B13: SOR MORA | C13: M | D13: FOUNDER | E13: 45383 | G13: 2648.2834 | H13: 25 | I13: =G13*0.83% -> 21.980752 | J13: =G13+H13+I13 -> 2695.2642 | L13: =J13-K13 -> 2695.2642
A14: 7 | B14: NOP VY | C14: M | D14: FOUNDER | E14: 45422 | G14: 7034.2584 | H14: 67.2 | I14: =G14*0.83% -> 58.384344 | J14: =G14+H14+I14 -> 7159.8427 | L14: =J14-K14 -> 7159.8427
A15: 8 | B15: OU RITHTY | C15: M | D15: FOUNDER | E15: 45481 | G15: 6695.4766 | H15: 100 | I15: =G15*0.83% -> 55.572456 | J15: =G15+H15+I15 -> 6851.0491 | L15: =J15-K15 -> 6851.0491
A16: 9 | B16: SENG RITHY | C16: M | D16: MEMBER | E16: 45418 | F16: NOP VY | G16: 111.13556 | H16: 10 | I16: =G16*0.83% -> 0.92242515 | J16: =G16+H16+I16 -> 122.05799 | L16: =J16-K16 -> 122.05799
A17: 10 | B17: OU TEP PHALLIN | C17: F | D17: MEMBER | E17: 45383 | F17: OU RITHY | G17: 288.50055 | H17: 10 | I17: =G17*0.83% -> 2.3945546 | J17: =G17+H17+I17 -> 300.89511 | L17: =J17-K17 -> 300.89511
A18: 11 | B18: YIM BUNTHENG | C18: M | D18: MEMBER | E18: 45294 | F18: HONG REAKSMEY | G18: 97.799931 | I18: =G18*0.83% -> 0.81173943 | J18: =G18+H18+I18 -> 98.611671 | L18: =J18-K18 -> 98.611671
A19: 12 | B19: THENG SAVOEUN | C19: M | D19: MEMBER | E19: 45029 | F19: NOP VY | G19: 85.136839 | I19: =G19*0.83% -> 0.70663577 | J19: =G19+H19+I19 -> 85.843475 | L19: =J19-K19 -> 85.843475
A20: 13 | B20: UL VANN | C20: M | D20: MEMBER | E20: 45387 | F20: NOP VY | G20: 213.47916 | H20: 20 | I20: =G20*0.83% -> 1.7718771 | J20: =G20+H20+I20 -> 235.25104 | L20: =J20-K20 -> 235.25104
A21: 14 | B21: SIYONN SOTHEARITH | C21: M | D21: MEMBER | E21: 45475 | F21: HONG REAKSMEY | G21: 1385.0091 | H21: 100 | I21: =G21*0.83% -> 11.495576 | J21: =G21+H21+I21 -> 1496.5047 | L21: =J21-K21 -> 1496.5047
A22: 15 | B22: YEAN REAKSMEY | C22: M | D22: MEMBER | E22: 45386 | F22: PECH PISEY | G22: 160.35584 | H22: 20 | I22: =G22*0.83% -> 1.3309535 | J22: =G22+H22+I22 -> 181.6868 | L22: =J22-K22 -> 181.6868
A23: 16 | B23: SAM SOMONY | C23: M | D23: MEMBER | E23: 45415 | F23: NOP VY | G23: 1371.4554 | H23: 400 | I23: =G23*0.83% -> 11.38308 | J23: =G23+H23+I23 -> 1782.8385 | L23: =J23-K23 -> 1782.8385
A24: 17 | B24: KOY MAQUIS | C24: M | D24: MEMBER | E24: 45414 | F24: HONG REAKSMEY | G24: 249.48626 | H24: 20 | I24: =G24*0.83% -> 2.070736 | J24: =G24+H24+I24 -> 271.557 | L24: =J24-K24 -> 271.557
A25: 18 | B25: LY MALIN | C25: F | D25: MEMBER | E25: 45427 | F25: OU RITHY | G25: 593.15347 | H25: 10 | I25: =G25*0.83% -> 4.9231738 | J25: =G25+H25+I25 -> 608.07665 | L25: =J25-K25 -> 608.07665
A26: 19 | B26: VAN BUNNA | C26: M | D26: MEMBER | E26: 45388 | F26: PECH PISEY | G26: 226.02612 | I26: =G26*0.83% -> 1.8760168 | J26: =G26+H26+I26 -> 227.90214 | L26: =J26-K26 -> 227.90214
A27: 20 | B27: CHAN THEARA | C27: F | D27: MEMBER | E27: 45386 | F27: HONG REAKSMEY | G27: 79.756493 | I27: =G27*0.83% -> 0.66197889 | J27: =G27+H27+I27 -> 80.418472 | L27: =J27-K27 -> 80.418472
A28: 21 | B28: LONG BORIN | C28: F | D28: MEMBER | E28: 45140 | F28: NOP VY | G28: 117.07146 | I28: =G28*0.83% -> 0.9716931 | J28: =G28+H28+I28 -> 118.04315 | L28: =J28-K28 -> 118.04315
A29: 22 | B29: SOEUNG SAROEUN | C29: M | D29: MEMBER | E29: 45235 | F29: NOP VY | G29: 137.83154 | I29: =G29*0.83% -> 1.1440018 | J29: =G29+H29+I29 -> 138.97554 | L29: =J29-K29 -> 138.97554
A30: 23 | B30: TUY SYTHIENG | C30: M | D30: MEMBER | E30: 45422 | F30: OU RITHY | G30: 993.62883 | I30: =G30*0.83% -> 8.2471193 | J30: =G30+H30+I30 -> 1001.8759 | L30: =J30-K30 -> 1001.8759
A31: 24 | B31: CHHEOUNG VEASNA | C31: M | D31: MEMBER | E31: 45420 | F31: SAM SOMONY | G31: 649.805 | I31: =G31*0.83% -> 5.3933815 | J31: =G31+H31+I31 -> 655.19838 | L31: =J31-K31 -> 655.19838
A32: 25 | B32: OM MANITH | C32: M | D32: MEMBER | E32: 45383 | F32: OU RITHY | G32: 42.686569 | I32: =G32*0.83% -> 0.35429852 | J32: =G32+H32+I32 -> 43.040868 | L32: =J32-K32 -> 43.040868
A33: 26 | B33: IM SOTHY | C33: M | D33: MEMBER | E33: 45209 | F33: PECH PISEY | G33: 65.45405 | I33: =G33*0.83% -> 0.54326862 | J33: =G33+H33+I33 -> 65.997319 | L33: =J33-K33 -> 65.997319
A34: 27 | B34: PA CHANROEUN | C34: M | D34: MEMBER | E34: 45085 | F34: NOP VY | G34: 219.03698 | I34: =G34*0.83% -> 1.8180069 | J34: =G34+H34+I34 -> 220.85498 | L34: =J34-K34 -> 220.85498
A35: 28 | B35: HENG SOCHEA | C35: F | D35: MEMBER | E35: 45427 | F35: OU RITHY | G35: 67.250581 | I35: =G35*0.83% -> 0.55817982 | J35: =G35+H35+I35 -> 67.808761 | L35: =J35-K35 -> 67.808761
A36: 29 | B36: TUM SOKRAKSA | C36: F | D36: MEMBER | E36: 45235 | G36: 1060.8897 | I36: =G36*0.83% -> 8.8053843 | J36: =G36+H36+I36 -> 1069.6951 | L36: =J36-K36 -> 1069.6951
A37: 30 | B37: SDEUNG PHEARONG | D37: MEMBER | E37: 45235 | G37: 15.938202 | I37: =G37*0.83% -> 0.13228708 | J37: =G37+H37+I37 -> 16.070489 | L37: =J37-K37 -> 16.070489
A38: 31 | B38: TY SAMPHORS VICHEKA | D38: MEMBER | E38: 45416 | G38: 109.19328 | H38: 15 | I38: =G38*0.83% -> 0.90630424 | J38: =G38+H38+I38 -> 125.09959 | L38: =J38-K38 -> 125.09959
A39: 32 | B39: CHUM CHANDARIN | D39: MEMBER | E39: 45420 | G39: 236.48079 | H39: 5 | I39: =G39*0.83% -> 1.9627906 | J39: =G39+H39+I39 -> 243.44358 | L39: =J39-K39 -> 243.44358
A40: 33 | B40: PEANH KOEUN | D40: MEMBER | E40: 45414 | G40: 83.046594 | H40: 15 | I40: =G40*0.83% -> 0.68928673 | J40: =G40+H40+I40 -> 98.735881 | L40: =J40-K40 -> 98.735881
A41: 34 | B41: YANG SOPHORN | D41: MEMBER | E41: 45414 | G41: 206.76203 | I41: =G41*0.83% -> 1.7161248 | J41: =G41+H41+I41 -> 208.47815 | L41: =J41-K41 -> 208.47815
A42: 35 | B42: RO VANNAK | D42: MEMBER | E42: 45330 | G42: 57.545833 | I42: =G42*0.83% -> 0.47763041 | J42: =G42+H42+I42 -> 58.023463 | L42: =J42-K42 -> 58.023463
A43: 36 | B43: SENG VANLY | D43: MEMBER | E43: 45333 | G43: 166.61565 | I43: =G43*0.83% -> 1.3829099 | J43: =G43+H43+I43 -> 167.99856 | L43: =J43-K43 -> 167.99856
A44: 37 | B44: YORNG SOKHAI | D44: MEMBER | E44: 45418 | G44: 167.77906 | I44: =G44*0.83% -> 1.3925662 | J44: =G44+H44+I44 -> 169.17163 | L44: =J44-K44 -> 169.17163
A45: 38 | B45: MENGHAK VICHHAY | D45: MEMBER | E45: 45333 | G45: 53.080013 | I45: =G45*0.83% -> 0.44056411 | J45: =G45+H45+I45 -> 53.520578 | L45: =J45-K45 -> 53.520578
A46: 39 | B46: SIM SUNNARY | D46: MEMBER | E46: 45245 | G46: 21.279281 | I46: =G46*0.83% -> 0.17661804 | J46: =G46+H46+I46 -> 21.455899 | L46: =J46-K46 -> 21.455899
A47: 40 | B47: AN NITH | D47: MEMBER | E47: 45293 | G47: 10.421946 | I47: =G47*0.83% -> 0.086502155 | J47: =G47+H47+I47 -> 10.508449 | L47: =J47-K47 -> 10.508449
A48: 41 | B48: SRENG SAREN | D48: MEMBER | E48: 45414 | G48: 306.29432 | I48: =G48*0.83% -> 2.5422429 | J48: =G48+H48+I48 -> 308.83656 | L48: =J48-K48 -> 308.83656
A49: 42 | B49: LAUT PHEAKDEY | D49: MEMBER | E49: 45303 | G49: 20.843893 | I49: =G49*0.83% -> 0.17300431 | J49: =G49+H49+I49 -> 21.016897 | L49: =J49-K49 -> 21.016897
A50: 43 | B50: KRUY BOPHA | D50: MEMBER | E50: 45419 | G50: 50.836918 | H50: 10 | I50: =G50*0.83% -> 0.42194642 | J50: =G50+H50+I50 -> 61.258864 | L50: =J50-K50 -> 61.258864
A51: 44 | B51: HORN RITHY | D51: MEMBER | E51: 45324 | G51: 10.336156 | I51: =G51*0.83% -> 0.085790097 | J51: =G51+H51+I51 -> 10.421946 | L51: =J51-K51 -> 10.421946
A52: 45 | B52: SAY SAMPOLIDA | D52: MEMBER | E52: 45332 | G52: 10.336156 | H52: 10 | I52: =G52*0.83% -> 0.085790097 | J52: =G52+H52+I52 -> 20.421946 | L52: =J52-K52 -> 20.421946
A53: 46 | B53: CHHEAV NAK | D53: MEMBER | E53: 45423 | G53: 101.33283 | I53: =G53*0.83% -> 0.84106247 | J53: =G53+H53+I53 -> 102.17389 | L53: =J53-K53 -> 102.17389
A54: 47 | B54: CHUN SOKTHOUTHEAREACH | D54: MEMBER | E54: 45420 | G54: 214.39031 | H54: 10 | I54: =G54*0.83% -> 1.7794396 | J54: =G54+H54+I54 -> 226.16975 | L54: =J54-K54 -> 226.16975
A55: 48 | B55: MENG SOTHY VATNAK | D55: MEMBER | E55: 45420 | G55: 40.668145 | I55: =G55*0.83% -> 0.3375456 | J55: =G55+H55+I55 -> 41.00569 | L55: =J55-K55 -> 41.00569
A56: 49 | B56: HUN SOT | D56: MEMBER | E56: 45414 | G56: 40.500761 | H56: 10 | I56: =G56*0.83% -> 0.33615632 | J56: =G56+H56+I56 -> 50.836918 | L56: =J56-K56 -> 50.836918
A57: 50 | B57: KET SOKSEILA | D57: MEMBER | E57: 45483 | F57: TUM SOKRAKSA | G57: 573.33381 | H57: 446.66 | I57: =G57*0.83% -> 4.7586706 | J57: =G57+H57+I57 -> 1024.7525 | L57: =J57-K57 -> 1024.7525
A58: 50 | B58: UM SAROM | D58: MEMBER | E58: 45420 | G58: 15.166344 | I58: =G58*0.83% -> 0.12588066 | J58: =G58+H58+I58 -> 15.292225 | L58: =J58-K58 -> 15.292225
A59: 51 | B59: PHAL CHANTHA | D59: MEMBER | E59: 45475 | G59: 80.582378 | H59: 30 | I59: =G59*0.83% -> 0.66883374 | J59: =G59+H59+I59 -> 111.25121 | L59: =J59-K59 -> 111.25121
A60: 52 | B60: VA SARA | D60: MEMBER | E60: 45390 | F60: ATH THORN | G60: 20.249689 | I60: =G60*0.83% -> 0.16807242 | J60: =G60+H60+I60 -> 20.417761 | L60: =J60-K60 -> 20.417761
A61: 53 | B61: KET LENG | D61: MEMBER | E61: 45390 | F61: ATH THORN | G61: 20.249689 | H61: 20 | I61: =G61*0.83% -> 0.16807242 | J61: =G61+H61+I61 -> 40.417761 | L61: =J61-K61 -> 40.417761
A62: 54 | B62: EAN OUN | D62: MEMBER | E62: 45390 | F62: ATH THORN | G62: 20.249689 | I62: =G62*0.83% -> 0.16807242 | J62: =G62+H62+I62 -> 20.417761 | L62: =J62-K62 -> 20.417761
A63: 55 | B63: IEN SOPHOEURN | D63: MEMBER | E63: 45420 | G63: 10.083 | I63: =G63*0.83% -> 0.0836889 | J63: =G63+H63+I63 -> 10.166689 | L63: =J63-K63 -> 10.166689
G69: =SUM(G7:G59) -> 49683.5 | H69: =SUM(H7:H68) -> 1503.86 | I69: =SUM(I7:I57) -> 411.57833 | J69: =SUM(J7:J59) -> 51579.733 | K69: =SUM(K7:K55) -> 0 | L69: =SUM(L7:L59) -> 51579.733

Sheet Aug-24
A1: SANSAM SAVING GROUP
A2: SAVING FROM 5USD PER MONTH BY GETTING INTEREST 10% PER YEAR
A3: SAVING DEPOSIT FROM 1ST - 10TH EVERY MONTH
A4: ACCESSIBLE LOAN ON 15TH EACH MONTH
A5: SAVING IN Aug 2024
A6: NO | B6: NAME | C6: SEX | D6: ROLE | E6: SAVING DATE | F6: TEAM LEADER | G6: CAPITAL | H6: SAVING | I6: INTEREST | J6: BALANCE | K6: WITHDRAWAL | L6: TOTAL
A7: 1 | B7: ATH THORN | C7: M | D7: FOUNDER | E7: 45422 | G7: 4553.8739 | I7: =G7*0.83% -> 37.797153 | J7: =G7+H7+I7 -> 4591.671 | L7: =J7-K7 -> 4591.671
A8: 2 | B8: PECH PISEY | C8: M | D8: FOUNDER | E8: 45514 | G8: 7325.2033 | H8: 200 | I8: =G8*0.83% -> 60.799187 | J8: =G8+H8+I8 -> 7586.0025 | L8: =J8-K8 -> 7586.0025
A9: 3 | B9: HONG REAKSMEY | C9: M | D9: FOUNDER | E9: 45423 | G9: 7415.1392 | I9: =G9*0.83% -> 61.545655 | J9: =G9+H9+I9 -> 7476.6848 | L9: =J9-K9 -> 7476.6848
A10: 4 | B10: SIN PUTHEARY | C10: F | D10: FOUNDER | E10: 45171 | G10: 3051.2968 | I10: =G10*0.83% -> 25.325763 | J10: =G10+H10+I10 -> 3076.6225 | L10: =J10-K10 -> 3076.6225
A11: 5 | B11: PAO VORN | C11: M | D11: FOUNDER | E11: 45239 | G11: 488.98532 | I11: =G11*0.83% -> 4.0585782 | J11: =G11+H11+I11 -> 493.0439 | L11: =J11-K11 -> 493.0439
A12: 6 | B12: SOR MORA | C12: M | D12: FOUNDER | E12: 45383 | G12: 235.61416 | H12: 25 | I12: =G12*0.83% -> 1.9555975 | J12: =G12+H12+I12 -> 262.56976 | L12: =J12-K12 -> 262.56976
A13: 7 | B13: NOP VY | C13: M | D13: FOUNDER | E13: 45422 | G13: 7159.8427 | H13: 20.52 | I13: =G13*0.83% -> 59.426694 | J13: =G13+H13+I13 -> 7239.7894 | L13: =J13-K13 -> 7239.7894
A14: 8 | B14: OU RITHTY | C14: M | D14: FOUNDER | E14: 45511 | G14: 6851.0491 | H14: 100 | I14: =G14*0.83% -> 56.863708 | J14: =G14+H14+I14 -> 7007.9128 | L14: =J14-K14 -> 7007.9128
A15: 9 | B15: SENG RITHY | C15: M | D15: MEMBER | E15: 45418 | F15: NOP VY | G15: 122.05799 | H15: 10 | I15: =G15*0.83% -> 1.0130813 | J15: =G15+H15+I15 -> 133.07107 | L15: =J15-K15 -> 133.07107
A16: 10 | B16: OU TEP PHALLIN | C16: F | D16: MEMBER | E16: 45383 | F16: OU RITHY | G16: 300.89511 | H16: 20 | I16: =G16*0.83% -> 2.4974294 | J16: =G16+H16+I16 -> 323.39254 | L16: =J16-K16 -> 323.39254
A17: 11 | B17: YIM BUNTHENG | C17: M | D17: MEMBER | E17: 45294 | F17: HONG REAKSMEY | G17: 98.611671 | I17: =G17*0.83% -> 0.81847687 | J17: =G17+H17+I17 -> 99.430148 | L17: =J17-K17 -> 99.430148
A18: 12 | B18: THENG SAVOEUN | C18: M | D18: MEMBER | E18: 45029 | F18: NOP VY | G18: 85.843475 | I18: =G18*0.83% -> 0.71250084 | J18: =G18+H18+I18 -> 86.555976 | L18: =J18-K18 -> 86.555976
A19: 13 | B19: UL VANN | C19: M | D19: MEMBER | E19: 45387 | F19: NOP VY | G19: 235.25104 | I19: =G19*0.83% -> 1.9525836 | J19: =G19+H19+I19 -> 237.20363 | L19: =J19-K19 -> 237.20363
A20: 14 | B20: SIYONN SOTHEARITH | C20: M | D20: MEMBER | E20: 45506 | F20: HONG REAKSMEY | G20: 1496.5047 | H20: 100 | I20: =G20*0.83% -> 12.420989 | J20: =G20+H20+I20 -> 1608.9257 | L20: =J20-K20 -> 1608.9257
A21: 15 | B21: YEAN REAKSMEY | C21: M | D21: MEMBER | E21: 45386 | F21: PECH PISEY | G21: 181.6868 | I21: =G21*0.83% -> 1.5080004 | J21: =G21+H21+I21 -> 183.1948 | L21: =J21-K21 -> 183.1948
A22: 16 | B22: SAM SOMONY | C22: M | D22: MEMBER | E22: 45415 | F22: NOP VY | G22: 1782.8385 | I22: =G22*0.83% -> 14.79756 | J22: =G22+H22+I22 -> 1797.6361 | L22: =J22-K22 -> 1797.6361
A23: 17 | B23: KOY MAQUIS | C23: M | D23: MEMBER | E23: 45414 | F23: HONG REAKSMEY | G23: 271.557 | I23: =G23*0.83% -> 2.2539231 | J23: =G23+H23+I23 -> 273.81092 | L23: =J23-K23 -> 273.81092
A24: 18 | B24: LY MALIN | C24: F | D24: MEMBER | E24: 45427 | F24: OU RITHY | G24: 608.07665 | H24: 10 | I24: =G24*0.83% -> 5.0470362 | J24: =G24+H24+I24 -> 623.12368 | L24: =J24-K24 -> 623.12368
A25: 19 | B25: VAN BUNNA | C25: M | D25: MEMBER | E25: 45388 | F25: PECH PISEY | G25: 227.90214 | H25: 10 | I25: =G25*0.83% -> 1.8915878 | J25: =G25+H25+I25 -> 239.79373 | L25: =J25-K25 -> 239.79373
A26: 20 | B26: CHAN THEARA | C26: F | D26: MEMBER | E26: 45386 | F26: HONG REAKSMEY | G26: 80.418472 | I26: =G26*0.83% -> 0.66747331 | J26: =G26+H26+I26 -> 81.085945 | L26: =J26-K26 -> 81.085945
A27: 21 | B27: LONG BORIN | C27: F | D27: MEMBER | E27: 45140 | F27: NOP VY | G27: 118.04315 | I27: =G27*0.83% -> 0.97975815 | J27: =G27+H27+I27 -> 119.02291 | L27: =J27-K27 -> 119.02291
A28: 22 | B28: SOEUNG SAROEUN | C28: M | D28: MEMBER | E28: 45235 | F28: NOP VY | G28: 138.97554 | I28: =G28*0.83% -> 1.153497 | J28: =G28+H28+I28 -> 140.12904 | L28: =J28-K28 -> 140.12904
A29: 23 | B29: TUY SYTHIENG | C29: M | D29: MEMBER | E29: 45422 | F29: OU RITHY | G29: 1001.8759 | I29: =G29*0.83% -> 8.3155703 | J29: =G29+H29+I29 -> 1010.1915 | L29: =J29-K29 -> 1010.1915
A30: 24 | B30: CHHEOUNG VEASNA | C30: M | D30: MEMBER | E30: 45420 | F30: SAM SOMONY | G30: 655.19838 | I30: =G30*0.83% -> 5.4381465 | J30: =G30+H30+I30 -> 660.63652 | L30: =J30-K30 -> 660.63652
A31: 25 | B31: OM MANITH | C31: M | D31: MEMBER | E31: 45383 | F31: OU RITHY | G31: 43.040868 | I31: =G31*0.83% -> 0.3572392 | J31: =G31+H31+I31 -> 43.398107 | L31: =J31-K31 -> 43.398107
A32: 26 | B32: IM SOTHY | C32: M | D32: MEMBER | E32: 45209 | F32: PECH PISEY | G32: 65.997319 | I32: =G32*0.83% -> 0.54777775 | J32: =G32+H32+I32 -> 66.545096 | L32: =J32-K32 -> 66.545096
A33: 27 | B33: PA CHANROEUN | C33: M | D33: MEMBER | E33: 45085 | F33: NOP VY | G33: 222.68453 | I33: =G33*0.83% -> 1.8482816 | J33: =G33+H33+I33 -> 224.53282 | L33: =J33-K33 -> 224.53282
A34: 28 | B34: HENG SOCHEA | C34: F | D34: MEMBER | E34: 45427 | F34: OU RITHY | G34: 67.808761 | I34: =G34*0.83% -> 0.56281272 | J34: =G34+H34+I34 -> 68.371574 | L34: =J34-K34 -> 68.371574
A35: 29 | B35: TUM SOKRAKSA | C35: F | D35: MEMBER | E35: 45235 | G35: 1069.6951 | I35: =G35*0.83% -> 8.878469 | J35: =G35+H35+I35 -> 1078.5735 | L35: =J35-K35 -> 1078.5735
A36: 30 | B36: SDEUNG PHEARONG | D36: MEMBER | E36: 45235 | G36: 16.070489 | I36: =G36*0.83% -> 0.13338506 | J36: =G36+H36+I36 -> 16.203874 | L36: =J36-K36 -> 16.203874
A37: 31 | B37: TY SAMPHORS VICHEKA | D37: MEMBER | E37: 45416 | G37: 125.09959 | H37: 15 | I37: =G37*0.83% -> 1.0383266 | J37: =G37+H37+I37 -> 141.13791 | L37: =J37-K37 -> 141.13791
A38: 32 | B38: CHUM CHANDARIN | D38: MEMBER | E38: 45420 | G38: 243.44358 | H38: 5 | I38: =G38*0.83% -> 2.0205817 | J38: =G38+H38+I38 -> 250.46416 | L38: =J38-K38 -> 250.46416
A39: 33 | B39: PEANH KOEUN | D39: MEMBER | E39: 45414 | G39: 98.735881 | H39: 10 | I39: =G39*0.83% -> 0.81950781 | J39: =G39+H39+I39 -> 109.55539 | L39: =J39-K39 -> 109.55539
A40: 34 | B40: YANG SOPHORN | D40: MEMBER | E40: 45414 | G40: 208.47815 | I40: =G40*0.83% -> 1.7303687 | J40: =G40+H40+I40 -> 210.20852 | L40: =J40-K40 -> 210.20852
A41: 35 | B41: RO VANNAK | D41: MEMBER | E41: 45330 | G41: 58.023463 | I41: =G41*0.83% -> 0.48159474 | J41: =G41+H41+I41 -> 58.505058 | L41: =J41-K41 -> 58.505058
A42: 36 | B42: SENG VANLY | D42: MEMBER | E42: 45333 | G42: 167.99856 | I42: =G42*0.83% -> 1.3943881 | J42: =G42+H42+I42 -> 169.39295 | L42: =J42-K42 -> 169.39295
A43: 37 | B43: YORNG SOKHAI | D43: MEMBER | E43: 45418 | G43: 169.17163 | I43: =G43*0.83% -> 1.4041245 | J43: =G43+H43+I43 -> 170.57575 | L43: =J43-K43 -> 170.57575
A44: 38 | B44: MENGHAK VICHHAY | D44: MEMBER | E44: 45333 | G44: 53.520577 | I44: =G44*0.83% -> 0.44422079 | J44: =G44+H44+I44 -> 53.964798 | L44: =J44-K44 -> 53.964798
A45: 39 | B45: SIM SUNNARY | D45: MEMBER | E45: 45245 | G45: 21.455899 | I45: =G45*0.83% -> 0.17808397 | J45: =G45+H45+I45 -> 21.633983 | L45: =J45-K45 -> 21.633983
A46: 40 | B46: AN NITH | D46: MEMBER | E46: 45293 | G46: 10.508449 | I46: =G46*0.83% -> 0.087220123 | J46: =G46+H46+I46 -> 10.595669 | L46: =J46-K46 -> 10.595669
A47: 41 | B47: SRENG SAREN | D47: MEMBER | E47: 45414 | G47: 308.83656 | H47: 50 | I47: =G47*0.83% -> 2.5633435 | J47: =G47+H47+I47 -> 361.39991 | L47: =J47-K47 -> 361.39991
A48: 42 | B48: LAUT PHEAKDEY | D48: MEMBER | E48: 45303 | G48: 21.016897 | I48: =G48*0.83% -> 0.17444025 | J48: =G48+H48+I48 -> 21.191337 | L48: =J48-K48 -> 21.191337
A49: 43 | B49: KRUY BOPHA | D49: MEMBER | E49: 45419 | G49: 61.258864 | H49: 10 | I49: =G49*0.83% -> 0.50844857 | J49: =G49+H49+I49 -> 71.767313 | L49: =J49-K49 -> 71.767313
A50: 44 | B50: HORN RITHY | D50: MEMBER | E50: 45324 | G50: 10.421946 | I50: =G50*0.83% -> 0.086502155 | J50: =G50+H50+I50 -> 10.508449 | L50: =J50-K50 -> 10.508449
A51: 45 | B51: SAY SAMPOLIDA | D51: MEMBER | E51: 45332 | G51: 20.421946 | H51: 10 | I51: =G51*0.83% -> 0.16950216 | J51: =G51+H51+I51 -> 30.591449 | L51: =J51-K51 -> 30.591449
A52: 46 | B52: CHHEAV NAK | D52: MEMBER | E52: 45423 | G52: 102.17389 | I52: =G52*0.83% -> 0.84804329 | J52: =G52+H52+I52 -> 103.02193 | L52: =J52-K52 -> 103.02193
A53: 47 | B53: CHUN SOKTHOUTHEAREACH | D53: MEMBER | E53: 45420 | G53: 226.16975 | H53: 10 | I53: =G53*0.83% -> 1.8772089 | J53: =G53+H53+I53 -> 238.04696 | L53: =J53-K53 -> 238.04696
A54: 48 | B54: MENG SOTHY VATNAK | D54: MEMBER | E54: 45420 | G54: 41.00569 | I54: =G54*0.83% -> 0.34034723 | J54: =G54+H54+I54 -> 41.346038 | L54: =J54-K54 -> 41.346038
A55: 49 | B55: HUN SOT | D55: MEMBER | E55: 45414 | G55: 50.836918 | H55: 10 | I55: =G55*0.83% -> 0.42194642 | J55: =G55+H55+I55 -> 61.258864 | L55: =J55-K55 -> 61.258864
A56: 50 | B56: KET SOKSEILA | D56: MEMBER | E56: 45514 | F56: TUM SOKRAKSA | G56: 1024.7525 | H56: 10 | I56: =G56*0.83% -> 8.5054456 | J56: =G56+H56+I56 -> 1043.2579 | L56: =J56-K56 -> 1043.2579
A57: 50 | B57: UM SAROM | D57: MEMBER | E57: 45420 | G57: 15.292225 | I57: =G57*0.83% -> 0.12692547 | J57: =G57+H57+I57 -> 15.419151 | L57: =J57-K57 -> 15.419151
A58: 51 | B58: PHAL CHANTHA | D58: MEMBER | E58: 45506 | G58: 111.25121 | H58: 20 | I58: =G58*0.83% -> 0.92338506 | J58: =G58+H58+I58 -> 132.1746 | L58: =J58-K58 -> 132.1746
A59: 52 | B59: VA SARA | D59: MEMBER | E59: 45390 | F59: ATH THORN | G59: 20.417761 | I59: =G59*0.83% -> 0.16946742 | J59: =G59+H59+I59 -> 20.587229 | L59: =J59-K59 -> 20.587229
A60: 53 | B60: KET LENG | D60: MEMBER | E60: 45390 | F60: ATH THORN | G60: 40.417761 | H60: 20 | I60: =G60*0.83% -> 0.33546742 | J60: =G60+H60+I60 -> 60.753229 | L60: =J60-K60 -> 60.753229
A61: 54 | B61: EAN OUN | D61: MEMBER | E61: 45390 | F61: ATH THORN | G61: 20.417761 | I61: =G61*0.83% -> 0.16946742 | J61: =G61+H61+I61 -> 20.587229 | L61: =J61-K61 -> 20.587229
A62: 55 | B62: IEN SOPHOEURN | D62: MEMBER | E62: 45420 | G62: 10.166689 | I62: =G62*0.83% -> 0.084383518 | J62: =G62+H62+I62 -> 10.251072 | L62: =J62-K62 -> 10.251072
A63: 56 | B63: Chea Sopheap | D63: MEMBER | H63: 5 | I63: =G63*0.83% -> 0 | J63: =G63+H63+I63 -> 5 | L63: =H63 -> 5 | M63: .
G69: =SUM(G7:G59) -> 49142.33 | H69: =SUM(H7:H68) -> 670.52 | I69: =SUM(I7:I57) -> 406.78849 | J69: =SUM(J7:J59) -> 50195.731 | K69: =SUM(K7:K55) -> 0 | L69: =SUM(L7:L59) -> 50195.731

Sheet Sep-24
A1: SANSAM SAVING GROUP
A2: SAVING FROM 5USD PER MONTH BY GETTING INTEREST 10% PER YEAR
A3: SAVING DEPOSIT FROM 1ST - 10TH EVERY MONTH
A4: ACCESSIBLE LOAN ON 15TH EACH MONTH
A5: SAVING IN Sep 2024
A6: NO | B6: NAME | C6: SEX | D6: ROLE | E6: SAVING DATE | F6: TEAM LEADER | G6: CAPITAL | H6: SAVING | I6: INTEREST | J6: BALANCE | K6: WITHDRAWAL | L6: TOTAL
A7: 1 | B7: ATH THORN | C7: M | D7: FOUNDER | E7: 45422 | G7: 4591.671 | I7: =G7*0.83% -> 38.110869 | J7: =G7+H7+I7 -> 4629.7819 | L7: =J7-K7 -> 4629.7819
A8: 2 | B8: PECH PISEY | C8: M | D8: FOUNDER | E8: 45545 | G8: 7586.0025 | H8: 30 | I8: =G8*0.83% -> 62.96382 | J8: =G8+H8+I8 -> 7678.9663 | L8: =J8-K8 -> 7678.9663
A9: 3 | B9: HONG REAKSMEY | C9: M | D9: FOUNDER | E9: 45545 | G9: 7476.6848 | H9: 50 | I9: =G9*0.83% -> 62.056484 | J9: =G9+H9+I9 -> 7588.7413 | L9: =J9-K9 -> 7588.7413
A10: 4 | B10: SIN PUTHEARY | C10: F | D10: FOUNDER | E10: 45171 | G10: 3076.6225 | I10: =G10*0.83% -> 25.535967 | J10: =G10+H10+I10 -> 3102.1585 | L10: =J10-K10 -> 3102.1585
A11: 5 | B11: PAO VORN | C11: M | D11: FOUNDER | E11: 45239 | G11: 493.0439 | H11: 20 | I11: =G11*0.83% -> 4.0922644 | J11: =G11+H11+I11 -> 517.13617 | L11: =J11-K11 -> 517.13617
A12: 6 | B12: SOR MORA | C12: M | D12: FOUNDER | E12: 45383 | G12: 262.56976 | H12: 25 | I12: =G12*0.83% -> 2.179329 | J12: =G12+H12+I12 -> 289.74909 | L12: =J12-K12 -> 289.74909
A13: 7 | B13: NOP VY | C13: M | D13: FOUNDER | E13: 45422 | G13: 7239.7894 | H13: 23.84 | I13: =G13*0.83% -> 60.090252 | J13: =G13+H13+I13 -> 7323.7197 | L13: =J13-K13 -> 7323.7197
A14: 8 | B14: OU RITHTY | C14: M | D14: FOUNDER | E14: 45544 | G14: 7007.9128 | H14: 100 | I14: =G14*0.83% -> 58.165676 | J14: =G14+H14+I14 -> 7166.0785 | L14: =J14-K14 -> 7166.0785
A15: 9 | B15: SENG RITHY | C15: M | D15: MEMBER | E15: 45418 | F15: NOP VY | G15: 133.07107 | I15: =G15*0.83% -> 1.1044899 | J15: =G15+H15+I15 -> 134.17556 | L15: =J15-K15 -> 134.17556
A16: 10 | B16: OU TEP PHALLIN | C16: F | D16: MEMBER | E16: 45383 | F16: OU RITHY | G16: 323.39254 | I16: =G16*0.83% -> 2.684158 | J16: =G16+H16+I16 -> 326.07669 | L16: =J16-K16 -> 326.07669
A17: 11 | B17: YIM BUNTHENG | C17: M | D17: MEMBER | E17: 45294 | F17: HONG REAKSMEY | G17: 99.430148 | H17: 10 | I17: =G17*0.83% -> 0.82527023 | J17: =G17+H17+I17 -> 110.25542 | L17: =J17-K17 -> 110.25542
A18: 12 | B18: THENG SAVOEUN | C18: M | D18: MEMBER | E18: 45029 | F18: NOP VY | G18: 86.555976 | I18: =G18*0.83% -> 0.7184146 | J18: =G18+H18+I18 -> 87.274391 | L18: =J18-K18 -> 87.274391
A19: 13 | B19: UL VANN | C19: M | D19: MEMBER | E19: 45387 | F19: NOP VY | G19: 237.20363 | I19: =G19*0.83% -> 1.9687901 | J19: =G19+H19+I19 -> 239.17242 | L19: =J19-K19 -> 239.17242
A20: 14 | B20: SIYONN SOTHEARITH | C20: M | D20: MEMBER | E20: 45414 | F20: HONG REAKSMEY | G20: 1608.9257 | H20: 100 | I20: =G20*0.83% -> 13.354083 | J20: =G20+H20+I20 -> 1722.2798 | L20: =J20-K20 -> 1722.2798
A21: 15 | B21: YEAN REAKSMEY | C21: M | D21: MEMBER | E21: 45386 | F21: PECH PISEY | G21: 183.1948 | I21: =G21*0.83% -> 1.5205168 | J21: =G21+H21+I21 -> 184.71531 | L21: =J21-K21 -> 184.71531
A22: 16 | B22: SAM SOMONY | C22: M | D22: MEMBER | E22: 45415 | F22: NOP VY | G22: 1797.6361 | H22: 50 | I22: =G22*0.83% -> 14.920379 | J22: =G22+H22+I22 -> 1862.5565 | L22: =J22-K22 -> 1862.5565
A23: 17 | B23: KOY MAQUIS | C23: M | D23: MEMBER | E23: 45414 | F23: HONG REAKSMEY | G23: 273.81092 | H23: 20 | I23: =G23*0.83% -> 2.2726307 | J23: =G23+H23+I23 -> 296.08355 | L23: =J23-K23 -> 296.08355
A24: 18 | B24: LY MALIN | C24: F | D24: MEMBER | E24: 45427 | F24: OU RITHY | G24: 623.12368 | H24: 10 | I24: =G24*0.83% -> 5.1719266 | J24: =G24+H24+I24 -> 638.29561 | L24: =J24-K24 -> 638.29561
A25: 19 | B25: VAN BUNNA | C25: M | D25: MEMBER | E25: 45388 | F25: PECH PISEY | G25: 239.79373 | I25: =G25*0.83% -> 1.9902879 | J25: =G25+H25+I25 -> 241.78402 | L25: =J25-K25 -> 241.78402
A26: 20 | B26: CHAN THEARA | C26: F | D26: MEMBER | E26: 45386 | F26: HONG REAKSMEY | G26: 81.085945 | I26: =G26*0.83% -> 0.67301334 | J26: =G26+H26+I26 -> 81.758958 | L26: =J26-K26 -> 81.758958
A27: 21 | B27: LONG BORIN | C27: F | D27: MEMBER | E27: 45140 | F27: NOP VY | G27: 119.02291 | I27: =G27*0.83% -> 0.98789014 | J27: =G27+H27+I27 -> 120.0108 | L27: =J27-K27 -> 120.0108
A28: 22 | B28: SOEUNG SAROEUN | C28: M | D28: MEMBER | E28: 45235 | F28: NOP VY | G28: 140.12904 | I28: =G28*0.83% -> 1.163071 | J28: =G28+H28+I28 -> 141.29211 | L28: =J28-K28 -> 141.29211
A29: 23 | B29: TUY SYTHIENG | C29: M | D29: MEMBER | E29: 45422 | F29: OU RITHY | G29: 1010.1915 | I29: =G29*0.83% -> 8.3845896 | J29: =G29+H29+I29 -> 1018.5761 | L29: =J29-K29 -> 1018.5761
A30: 24 | B30: CHHEOUNG VEASNA | C30: M | D30: MEMBER | E30: 45420 | F30: SAM SOMONY | G30: 660.63652 | I30: =G30*0.83% -> 5.4832831 | J30: =G30+H30+I30 -> 666.11981 | L30: =J30-K30 -> 666.11981
A31: 25 | B31: OM MANITH | C31: M | D31: MEMBER | E31: 45383 | F31: OU RITHY | G31: 43.398107 | I31: =G31*0.83% -> 0.36020429 | J31: =G31+H31+I31 -> 43.758311 | L31: =J31-K31 -> 43.758311
A32: 26 | B32: IM SOTHY | C32: M | D32: MEMBER | E32: 45209 | F32: PECH PISEY | G32: 66.545096 | I32: =G32*0.83% -> 0.5523243 | J32: =G32+H32+I32 -> 67.097421 | L32: =J32-K32 -> 67.097421
A33: 27 | B33: PA CHANROEUN | C33: M | D33: MEMBER | E33: 45085 | F33: NOP VY | G33: 224.53282 | I33: =G33*0.83% -> 1.8636224 | J33: =G33+H33+I33 -> 226.39644 | L33: =J33-K33 -> 226.39644
A34: 28 | B34: HENG SOCHEA | C34: F | D34: MEMBER | E34: 45427 | F34: OU RITHY | G34: 68.371574 | I34: =G34*0.83% -> 0.56748406 | J34: =G34+H34+I34 -> 68.939058 | L34: =J34-K34 -> 68.939058
A35: 29 | B35: TUM SOKRAKSA | C35: F | D35: MEMBER | E35: 45235 | G35: 1078.5735 | I35: =G35*0.83% -> 8.9521603 | J35: =G35+H35+I35 -> 1087.5257 | L35: =J35-K35 -> 1087.5257
A36: 30 | B36: SDEUNG PHEARONG | D36: MEMBER | E36: 45235 | G36: 16.203874 | I36: =G36*0.83% -> 0.13449216 | J36: =G36+H36+I36 -> 16.338366 | L36: =J36-K36 -> 16.338366
A37: 31 | B37: TY SAMPHORS VICHEKA | D37: MEMBER | E37: 45416 | G37: 141.13791 | H37: 15 | I37: =G37*0.83% -> 1.1714447 | J37: =G37+H37+I37 -> 157.30936 | L37: =J37-K37 -> 157.30936
A38: 32 | B38: CHUM CHANDARIN | D38: MEMBER | E38: 45420 | G38: 250.46416 | I38: =G38*0.83% -> 2.0788526 | J38: =G38+H38+I38 -> 252.54302 | L38: =J38-K38 -> 252.54302
A39: 33 | B39: PEANH KOEUN | D39: MEMBER | E39: 45414 | G39: 109.55539 | H39: 10 | I39: =G39*0.83% -> 0.90930973 | J39: =G39+H39+I39 -> 120.4647 | L39: =J39-K39 -> 120.4647
A40: 34 | B40: YANG SOPHORN | D40: MEMBER | E40: 45414 | G40: 210.20852 | I40: =G40*0.83% -> 1.7447307 | J40: =G40+H40+I40 -> 211.95325 | L40: =J40-K40 -> 211.95325
A41: 35 | B41: RO VANNAK | D41: MEMBER | E41: 45330 | G41: 58.505058 | I41: =G41*0.83% -> 0.48559198 | J41: =G41+H41+I41 -> 58.99065 | L41: =J41-K41 -> 58.99065
A42: 36 | B42: SENG VANLY | D42: MEMBER | E42: 45333 | G42: 169.39295 | H42: 10 | I42: =G42*0.83% -> 1.4059615 | J42: =G42+H42+I42 -> 180.79891 | L42: =J42-K42 -> 180.79891
A43: 37 | B43: YORNG SOKHAI | D43: MEMBER | E43: 45418 | G43: 170.57575 | I43: =G43*0.83% -> 1.4157787 | J43: =G43+H43+I43 -> 171.99153 | L43: =J43-K43 -> 171.99153
A44: 38 | B44: MENGHAK VICHHAY | D44: MEMBER | E44: 45333 | G44: 53.964798 | I44: =G44*0.83% -> 0.44790783 | J44: =G44+H44+I44 -> 54.412706 | L44: =J44-K44 -> 54.412706
A45: 39 | B45: SIM SUNNARY | D45: MEMBER | E45: 45245 | G45: 21.633983 | I45: =G45*0.83% -> 0.17956206 | J45: =G45+H45+I45 -> 21.813546 | L45: =J45-K45 -> 21.813546
A46: 40 | B46: AN NITH | D46: MEMBER | E46: 45293 | G46: 10.595669 | I46: =G46*0.83% -> 0.08794405 | J46: =G46+H46+I46 -> 10.683613 | L46: =J46-K46 -> 10.683613
A47: 41 | B47: SRENG SAREN | D47: MEMBER | E47: 45414 | G47: 361.39991 | I47: =G47*0.83% -> 2.9996192 | J47: =G47+H47+I47 -> 364.39953 | L47: =J47-K47 -> 364.39953
A48: 42 | B48: LAUT PHEAKDEY | D48: MEMBER | E48: 45303 | G48: 21.191337 | I48: =G48*0.83% -> 0.1758881 | J48: =G48+H48+I48 -> 21.367225 | L48: =J48-K48 -> 21.367225
A49: 43 | B49: KRUY BOPHA | D49: MEMBER | E49: 45419 | G49: 71.767313 | H49: 10 | I49: =G49*0.83% -> 0.59566869 | J49: =G49+H49+I49 -> 82.362981 | L49: =J49-K49 -> 82.362981
A50: 44 | B50: HORN RITHY | D50: MEMBER | E50: 45324 | G50: 10.508449 | I50: =G50*0.83% -> 0.087220123 | J50: =G50+H50+I50 -> 10.595669 | L50: =J50-K50 -> 10.595669
A51: 45 | B51: SAY SAMPOLIDA | D51: MEMBER | E51: 45332 | G51: 30.591449 | H51: 10 | I51: =G51*0.83% -> 0.25390902 | J51: =G51+H51+I51 -> 40.845358 | L51: =J51-K51 -> 40.845358
A52: 46 | B52: CHHEAV NAK | D52: MEMBER | E52: 45423 | G52: 103.02193 | I52: =G52*0.83% -> 0.85508205 | J52: =G52+H52+I52 -> 103.87702 | L52: =J52-K52 -> 103.87702
A53: 47 | B53: CHUN SOKTHOUTHEAREACH | D53: MEMBER | E53: 45420 | G53: 238.04696 | H53: 10 | I53: =G53*0.83% -> 1.9757897 | J53: =G53+H53+I53 -> 250.02275 | L53: =J53-K53 -> 250.02275
A54: 48 | B54: MENG SOTHY VATNAK | D54: MEMBER | E54: 45420 | G54: 41.346038 | I54: =G54*0.83% -> 0.34317211 | J54: =G54+H54+I54 -> 41.68921 | L54: =J54-K54 -> 41.68921
A55: 49 | B55: HUN SOT | D55: MEMBER | E55: 45414 | G55: 61.258864 | H55: 10 | I55: =G55*0.83% -> 0.50844857 | J55: =G55+H55+I55 -> 71.767313 | L55: =J55-K55 -> 71.767313
A56: 50 | B56: KET SOKSEILA | D56: MEMBER | E56: 45545 | F56: TUM SOKRAKSA | G56: 1043.2579 | H56: 10 | I56: =G56*0.83% -> 8.6590408 | J56: =G56+H56+I56 -> 1061.917 | L56: =J56-K56 -> 1061.917
A57: 50 | B57: UM SAROM | D57: MEMBER | E57: 45420 | G57: 15.419151 | I57: =G57*0.83% -> 0.12797895 | J57: =G57+H57+I57 -> 15.54713 | L57: =J57-K57 -> 15.54713
A58: 51 | B58: PHAL CHANTHA | D58: MEMBER | E58: 45541 | G58: 132.1746 | H58: 30 | I58: =G58*0.83% -> 1.0970492 | J58: =G58+H58+I58 -> 163.27165 | L58: =J58-K58 -> 163.27165
A59: 52 | B59: VA SARA | D59: MEMBER | E59: 45390 | F59: ATH THORN | G59: 20.587229 | I59: =G59*0.83% -> 0.170874 | J59: =G59+H59+I59 -> 20.758103 | L59: =J59-K59 -> 20.758103
A60: 53 | B60: KET LENG | D60: MEMBER | E60: 45390 | F60: ATH THORN | G60: 60.753229 | H60: 20 | I60: =G60*0.83% -> 0.5042518 | J60: =G60+H60+I60 -> 81.257481 | L60: =J60-K60 -> 81.257481
A61: 54 | B61: EAN OUN | D61: MEMBER | E61: 45390 | F61: ATH THORN | G61: 20.587229 | I61: =G61*0.83% -> 0.170874 | J61: =G61+H61+I61 -> 20.758103 | L61: =J61-K61 -> 20.758103
A62: 55 | B62: IEN SOPHOEURN | D62: MEMBER | E62: 45420 | G62: 10.251072 | I62: =G62*0.83% -> 0.085083901 | J62: =G62+H62+I62 -> 10.336156 | L62: =J62-K62 -> 10.336156
A63: 56 | B63: Chea Sopheap | D63: MEMBER | G63: 5 | H63: 10 | I63: =G63*0.83% -> 0.0415 | J63: =G63+H63+I63 -> 15.0415 | L63: =J63-K63 -> 15.0415
G69: =SUM(G7:G59) -> 50195.731 | H69: =SUM(H7:H68) -> 583.84 | I69: =SUM(I7:I57) -> 415.35665 | J69: =SUM(J7:J59) -> 51166.196 | K69: =SUM(K7:K55) -> 0 | L69: =SUM(L7:L59) -> 51166.196

Sheet Oct-24
A1: SANSAM SAVING GROUP
A2: SAVING FROM 5USD PER MONTH BY GETTING INTEREST 10% PER YEAR
A3: SAVING DEPOSIT FROM 1ST - 10TH EVERY MONTH
A4: ACCESSIBLE LOAN ON 15TH EACH MONTH
A5: SAVING IN OCT 2024
A6: NO | B6: NAME | C6: SEX | D6: ROLE | E6: SAVING DATE | F6: TEAM LEADER | G6: CAPITAL | H6: SAVING | I6: INTEREST | J6: BALANCE | K6: WITHDRAWAL | L6: TOTAL
A7: 1 | B7: ATH THORN | C7: M | D7: FOUNDER | E7: 45422 | G7: 4629.7819 | I7: =G7*0.83% -> 38.42719 | J7: =G7+H7+I7 -> 4668.2091 | L7: =J7-K7 -> 4668.2091
A8: 2 | B8: PECH PISEY | C8: M | D8: FOUNDER | E8: 45422 | G8: 7678.9663 | H8: 50 | I8: =G8*0.83% -> 63.73542 | J8: =G8+H8+I8 -> 7792.7017 | L8: =J8-K8 -> 7792.7017
A9: 3 | B9: HONG REAKSMEY | C9: M | D9: FOUNDER | E9: 45423 | G9: 7588.7413 | I9: =G9*0.83% -> 62.986553 | J9: =G9+H9+I9 -> 7651.7279 | L9: =J9-K9 -> 7651.7279
A10: 4 | B10: SIN PUTHEARY | C10: F | D10: FOUNDER | E10: 45171 | G10: 3102.1585 | I10: =G10*0.83% -> 25.747916 | J10: =G10+H10+I10 -> 3127.9064 | L10: =J10-K10 -> 3127.9064
A11: 5 | B11: PAO VORN | C11: M | D11: FOUNDER | E11: 45239 | G11: 517.13617 | I11: =G11*0.83% -> 4.2922302 | J11: =G11+H11+I11 -> 521.4284 | L11: =J11-K11 -> 521.4284
A12: 6 | B12: SOR MORA | C12: M | D12: FOUNDER | E12: 45383 | G12: 289.74909 | H12: 25 | I12: =G12*0.83% -> 2.4049174 | J12: =G12+H12+I12 -> 317.154 | L12: =J12-K12 -> 317.154
A13: 7 | B13: NOP VY | C13: M | D13: FOUNDER | E13: 45422 | G13: 7323.7197 | H13: 77.16 | I13: =G13*0.83% -> 60.786873 | J13: =G13+H13+I13 -> 7461.6665 | L13: =J13-K13 -> 7461.6665
A14: 8 | B14: OU RITHTY | C14: M | D14: FOUNDER | E14: 45572 | G14: 3583.0392 | H14: 50 | I14: =G14*0.83% -> 29.739226 | J14: =G14+H14+I14 -> 3662.7785 | L14: =J14-K14 -> 3662.7785
A15: 9 | B15: Lim Solinn | C15: M | D15: MEMBER | E15: 45414 | G15: 3583.0392 | H15: 20 | I15: =G15*0.83% -> 29.739226 | J15: =G15+H15+I15 -> 3632.7785 | L15: =J15-K15 -> 3632.7785
A16: 9 | B16: SENG RITHY | C16: M | D16: MEMBER | E16: 45418 | F16: NOP VY | G16: 134.17556 | H16: 10 | I16: =G16*0.83% -> 1.1136571 | J16: =G16+H16+I16 -> 145.28921 | L16: =J16-K16 -> 145.28921
A17: 10 | B17: OU TEP PHALLIN | C17: F | D17: MEMBER | E17: 45383 | F17: OU RITHY | G17: 326.07669 | H17: 20 | I17: =G17*0.83% -> 2.7064366 | J17: =G17+H17+I17 -> 348.78313 | L17: =J17-K17 -> 348.78313
A18: 11 | B18: YIM BUNTHENG | C18: M | D18: MEMBER | E18: 45294 | F18: HONG REAKSMEY | G18: 110.25542 | I18: =G18*0.83% -> 0.91511997 | J18: =G18+H18+I18 -> 111.17054 | L18: =J18-K18 -> 111.17054
A19: 12 | B19: THENG SAVOEUN | C19: M | D19: MEMBER | E19: 45029 | F19: NOP VY | G19: 87.274391 | I19: =G19*0.83% -> 0.72437744 | J19: =G19+H19+I19 -> 87.998768 | L19: =J19-K19 -> 87.998768
A20: 13 | B20: UL VANN | C20: M | D20: MEMBER | E20: 45387 | F20: NOP VY | G20: 239.17242 | I20: =G20*0.83% -> 1.985131 | J20: =G20+H20+I20 -> 241.15755 | L20: =J20-K20 -> 241.15755
A21: 14 | B21: SIYONN SOTHEARITH | C21: M | D21: MEMBER | E21: 45414 | F21: HONG REAKSMEY | G21: 1722.2798 | I21: =G21*0.83% -> 14.294922 | J21: =G21+H21+I21 -> 1736.5747 | L21: =J21-K21 -> 1736.5747
A22: 15 | B22: YEAN REAKSMEY | C22: M | D22: MEMBER | E22: 45386 | F22: PECH PISEY | G22: 184.71531 | H22: 40 | I22: =G22*0.83% -> 1.5331371 | J22: =G22+H22+I22 -> 226.24845 | L22: =J22-K22 -> 226.24845
A23: 16 | B23: SAM SOMONY | C23: M | D23: MEMBER | E23: 45415 | F23: NOP VY | G23: 1862.5565 | H23: 50 | I23: =G23*0.83% -> 15.459219 | J23: =G23+H23+I23 -> 1928.0157 | L23: =J23-K23 -> 1928.0157
A24: 17 | B24: KOY MAQUIS | C24: M | D24: MEMBER | E24: 45414 | F24: HONG REAKSMEY | G24: 296.08355 | I24: =G24*0.83% -> 2.4574935 | J24: =G24+H24+I24 -> 298.54105 | L24: =J24-K24 -> 298.54105
A25: 18 | B25: LY MALIN | C25: F | D25: MEMBER | E25: 45427 | F25: OU RITHY | G25: 638.29561 | H25: 10 | I25: =G25*0.83% -> 5.2978536 | J25: =G25+H25+I25 -> 653.59347 | L25: =J25-K25 -> 653.59347
A26: 19 | B26: VAN BUNNA | C26: M | D26: MEMBER | E26: 45388 | F26: PECH PISEY | G26: 241.78402 | H26: 10 | I26: =G26*0.83% -> 2.0068073 | J26: =G26+H26+I26 -> 253.79082 | L26: =J26-K26 -> 253.79082
A27: 20 | B27: CHAN THEARA | C27: F | D27: MEMBER | E27: 45386 | F27: HONG REAKSMEY | G27: 81.758958 | I27: =G27*0.83% -> 0.67859935 | J27: =G27+H27+I27 -> 82.437558 | L27: =J27-K27 -> 82.437558
A28: 21 | B28: LONG BORIN | C28: F | D28: MEMBER | E28: 45140 | F28: NOP VY | G28: 120.0108 | I28: =G28*0.83% -> 0.99608963 | J28: =G28+H28+I28 -> 121.00689 | L28: =J28-K28 -> 121.00689
A29: 22 | B29: SOEUNG SAROEUN | C29: M | D29: MEMBER | E29: 45235 | F29: NOP VY | G29: 141.29211 | I29: =G29*0.83% -> 1.1727245 | J29: =G29+H29+I29 -> 142.46484 | L29: =J29-K29 -> 142.46484
A30: 23 | B30: TUY SYTHIENG | C30: M | D30: MEMBER | E30: 45422 | F30: OU RITHY | G30: 1018.5761 | I30: =G30*0.83% -> 8.4541817 | J30: =G30+H30+I30 -> 1027.0303 | L30: =J30-K30 -> 1027.0303
A31: 24 | B31: CHHEOUNG VEASNA | C31: M | D31: MEMBER | E31: 45420 | F31: SAM SOMONY | G31: 666.11981 | I31: =G31*0.83% -> 5.5287944 | J31: =G31+H31+I31 -> 671.6486 | L31: =J31-K31 -> 671.6486
A32: 25 | B32: OM MANITH | C32: M | D32: MEMBER | E32: 45383 | F32: OU RITHY | G32: 43.758311 | I32: =G32*0.83% -> 0.36319398 | J32: =G32+H32+I32 -> 44.121505 | L32: =J32-K32 -> 44.121505
A33: 26 | B33: IM SOTHY | C33: M | D33: MEMBER | E33: 45209 | F33: PECH PISEY | G33: 67.097421 | I33: =G33*0.83% -> 0.55690859 | J33: =G33+H33+I33 -> 67.654329 | L33: =J33-K33 -> 67.654329
A34: 27 | B34: PA CHANROEUN | C34: M | D34: MEMBER | E34: 45085 | F34: NOP VY | G34: 226.39644 | I34: =G34*0.83% -> 1.8790904 | J34: =G34+H34+I34 -> 228.27553 | L34: =J34-K34 -> 228.27553
A35: 28 | B35: HENG SOCHEA | C35: F | D35: MEMBER | E35: 45427 | F35: OU RITHY | G35: 68.939058 | I35: =G35*0.83% -> 0.57219418 | J35: =G35+H35+I35 -> 69.511252 | L35: =J35-K35 -> 69.511252
A36: 29 | B36: TUM SOKRAKSA | C36: F | D36: MEMBER | E36: 45235 | G36: 1087.5257 | I36: =G36*0.83% -> 9.0264633 | J36: =G36+H36+I36 -> 1096.5522 | L36: =J36-K36 -> 1096.5522
A37: 30 | B37: SDEUNG PHEARONG | D37: MEMBER | E37: 45235 | G37: 16.338366 | I37: =G37*0.83% -> 0.13560844 | J37: =G37+H37+I37 -> 16.473975 | L37: =J37-K37 -> 16.473975
A38: 31 | B38: TY SAMPHORS VICHEKA | D38: MEMBER | E38: 45416 | G38: 157.30936 | H38: 15 | I38: =G38*0.83% -> 1.3056677 | J38: =G38+H38+I38 -> 173.61503 | L38: =J38-K38 -> 173.61503
A39: 32 | B39: CHUM CHANDARIN | D39: MEMBER | E39: 45420 | G39: 252.54302 | I39: =G39*0.83% -> 2.096107 | J39: =G39+H39+I39 -> 254.63912 | L39: =J39-K39 -> 254.63912
A40: 33 | B40: PEANH KOEUN | D40: MEMBER | E40: 45414 | G40: 120.4647 | H40: 10 | I40: =G40*0.83% -> 0.999857 | J40: =G40+H40+I40 -> 131.46456 | L40: =J40-K40 -> 131.46456
A41: 34 | B41: YANG SOPHORN | D41: MEMBER | E41: 45414 | G41: 211.95325 | I41: =G41*0.83% -> 1.759212 | J41: =G41+H41+I41 -> 213.71246 | L41: =J41-K41 -> 213.71246
A42: 35 | B42: RO VANNAK | D42: MEMBER | E42: 45330 | G42: 58.99065 | I42: =G42*0.83% -> 0.48962239 | J42: =G42+H42+I42 -> 59.480272 | L42: =J42-K42 -> 59.480272
A43: 36 | B43: SENG VANLY | D43: MEMBER | E43: 45333 | G43: 180.79891 | I43: =G43*0.83% -> 1.500631 | J43: =G43+H43+I43 -> 182.29954 | L43: =J43-K43 -> 182.29954
A44: 37 | B44: YORNG SOKHAI | D44: MEMBER | E44: 45418 | G44: 171.99153 | I44: =G44*0.83% -> 1.4275297 | J44: =G44+H44+I44 -> 173.41906 | L44: =J44-K44 -> 173.41906
A45: 38 | B45: MENGHAK VICHHAY | D45: MEMBER | E45: 45333 | G45: 54.412706 | I45: =G45*0.83% -> 0.45162546 | J45: =G45+H45+I45 -> 54.864332 | L45: =J45-K45 -> 54.864332
A46: 39 | B46: SIM SUNNARY | D46: MEMBER | E46: 45245 | G46: 21.813546 | I46: =G46*0.83% -> 0.18105243 | J46: =G46+H46+I46 -> 21.994598 | L46: =J46-K46 -> 21.994598
A47: 40 | B47: AN NITH | D47: MEMBER | E47: 45293 | G47: 10.683613 | I47: =G47*0.83% -> 0.088673986 | J47: =G47+H47+I47 -> 10.772287 | L47: =J47-K47 -> 10.772287
A48: 41 | B48: SRENG SAREN | D48: MEMBER | E48: 45414 | G48: 364.39953 | H48: 50 | I48: =G48*0.83% -> 3.0245161 | J48: =G48+H48+I48 -> 417.42404 | L48: =J48-K48 -> 417.42404
A49: 42 | B49: LAUT PHEAKDEY | D49: MEMBER | E49: 45303 | G49: 21.367225 | I49: =G49*0.83% -> 0.17734797 | J49: =G49+H49+I49 -> 21.544573 | L49: =J49-K49 -> 21.544573
A50: 43 | B50: KRUY BOPHA | D50: MEMBER | E50: 45419 | G50: 82.362981 | H50: 10 | I50: =G50*0.83% -> 0.68361275 | J50: =G50+H50+I50 -> 93.046594 | L50: =J50-K50 -> 93.046594
A51: 44 | B51: HORN RITHY | D51: MEMBER | E51: 45324 | G51: 10.595669 | I51: =G51*0.83% -> 0.08794405 | J51: =G51+H51+I51 -> 10.683613 | L51: =J51-K51 -> 10.683613
A52: 45 | B52: SAY SAMPOLIDA | D52: MEMBER | E52: 45332 | G52: 40.845358 | H52: 10 | I52: =G52*0.83% -> 0.33901647 | J52: =G52+H52+I52 -> 51.184374 | L52: =J52-K52 -> 51.184374
A53: 46 | B53: CHHEAV NAK | D53: MEMBER | E53: 45423 | G53: 103.87702 | I53: =G53*0.83% -> 0.86217923 | J53: =G53+H53+I53 -> 104.7392 | L53: =J53-K53 -> 104.7392
A54: 47 | B54: CHUN SOKTHOUTHEAREACH | D54: MEMBER | E54: 45420 | G54: 250.02275 | H54: 10 | I54: =G54*0.83% -> 2.0751888 | J54: =G54+H54+I54 -> 262.09794 | L54: =J54-K54 -> 262.09794
A55: 48 | B55: MENG SOTHY VATNAK | D55: MEMBER | E55: 45420 | G55: 41.68921 | I55: =G55*0.83% -> 0.34602044 | J55: =G55+H55+I55 -> 42.03523 | L55: =J55-K55 -> 42.03523
A56: 49 | B56: HUN SOT | D56: MEMBER | E56: 45414 | G56: 71.767313 | H56: 10 | I56: =G56*0.83% -> 0.59566869 | J56: =G56+H56+I56 -> 82.362981 | L56: =J56-K56 -> 82.362981
A57: 50 | B57: KET SOKSEILA | D57: MEMBER | E57: 45423 | F57: TUM SOKRAKSA | G57: 1061.917 | H57: 10 | I57: =G57*0.83% -> 8.8139108 | J57: =G57+H57+I57 -> 1080.7309 | L57: =J57-K57 -> 1080.7309
A58: 50 | B58: UM SAROM | D58: MEMBER | E58: 45420 | G58: 15.54713 | I58: =G58*0.83% -> 0.12904118 | J58: =G58+H58+I58 -> 15.676171 | L58: =J58-K58 -> 15.676171
A59: 51 | B59: PHAL CHANTHA | D59: MEMBER | E59: 45572 | G59: 163.27165 | H59: 30 | I59: =G59*0.83% -> 1.3551547 | J59: =G59+H59+I59 -> 194.6268 | L59: =J59-K59 -> 194.6268
A60: 52 | B60: VA SARA | D60: MEMBER | E60: 45390 | F60: ATH THORN | G60: 20.758103 | I60: =G60*0.83% -> 0.17229225 | J60: =G60+H60+I60 -> 20.930395 | L60: =J60-K60 -> 20.930395
A61: 53 | B61: KET LENG | D61: MEMBER | E61: 45390 | F61: ATH THORN | G61: 81.257481 | H61: 20 | I61: =G61*0.83% -> 0.67443709 | J61: =G61+H61+I61 -> 101.93192 | L61: =J61-K61 -> 101.93192
A62: 54 | B62: EAN OUN | D62: MEMBER | E62: 45390 | F62: ATH THORN | G62: 20.758103 | I62: =G62*0.83% -> 0.17229225 | J62: =G62+H62+I62 -> 20.930395 | L62: =J62-K62 -> 20.930395
A63: 55 | B63: IEN SOPHOEURN | D63: MEMBER | E63: 45420 | G63: 10.336156 | I63: =G63*0.83% -> 0.085790097 | J63: =G63+H63+I63 -> 10.421946 | L63: =J63-K63 -> 10.421946
A64: 56 | B64: Chea Sopheap | D64: MEMBER | G64: 15.0415 | H64: 10 | I64: =G64*0.83% -> 0.12484445 | J64: =G64+H64+I64 -> 25.166344 | L64: =J64-K64 -> 25.166344
G70: =SUM(G7:G60) -> 51166.196 | H70: =SUM(H7:H69) -> 547.16 | I70: =SUM(I7:I58) -> 423.15198 | J70: =SUM(J7:J60) -> 52108.035 | K70: =SUM(K7:K56) -> 0 | L70: =SUM(L7:L60) -> 52108.035

Sheet Nov-24
A1: SANSAM SAVING GROUP
A2: SAVING FROM 5USD PER MONTH BY GETTING INTEREST 10% PER YEAR
A3: SAVING DEPOSIT FROM 1ST - 10TH EVERY MONTH
A4: ACCESSIBLE LOAN ON 15TH EACH MONTH
A5: SAVING IN NOV 2024
A6: NO | B6: NAME | C6: SEX | D6: ROLE | E6: SAVING DATE | F6: TEAM LEADER | G6: CAPITAL | H6: SAVING | I6: INTEREST | J6: BALANCE | K6: WITHDRAWAL | L6: TOTAL
A7: 1 | B7: ATH THORN | C7: M | D7: FOUNDER | E7: 45422 | G7: 4668.2091 | I7: =G7*0.83% -> 38.746135 | J7: =G7+H7+I7 -> 4706.9552 | L7: =J7-K7 -> 4706.9552
A8: 2 | B8: PECH PISEY | C8: M | D8: FOUNDER | E8: 45422 | G8: 7792.7017 | H8: 30 | I8: =G8*0.83% -> 64.679424 | J8: =G8+H8+I8 -> 7887.3811 | L8: =J8-K8 -> 7887.3811
A9: 3 | B9: HONG REAKSMEY | C9: M | D9: FOUNDER | E9: 45423 | G9: 7651.7279 | H9: 50 | I9: =G9*0.83% -> 63.509341 | J9: =G9+H9+I9 -> 7765.2372 | L9: =J9-K9 -> 7765.2372
A10: 4 | B10: SIN PUTHEARY | C10: F | D10: FOUNDER | E10: 45171 | G10: 3127.9064 | I10: =G10*0.83% -> 25.961623 | J10: =G10+H10+I10 -> 3153.868 | L10: =J10-K10 -> 3153.868
A11: 5 | B11: PAO VORN | C11: M | D11: FOUNDER | E11: 45239 | G11: 521.4284 | I11: =G11*0.83% -> 4.3278557 | J11: =G11+H11+I11 -> 525.75625 | L11: =J11-K11 -> 525.75625
A12: 6 | B12: SOR MORA | C12: M | D12: FOUNDER | E12: 45383 | G12: 317.154 | I12: =G12*0.83% -> 2.6323782 | J12: =G12+H12+I12 -> 319.78638 | L12: =J12-K12 -> 319.78638
A13: 7 | B13: NOP VY | C13: M | D13: FOUNDER | E13: 45422 | G13: 7461.6665 | H13: 80.48 | I13: =G13*0.83% -> 61.931832 | J13: =G13+H13+I13 -> 7604.0784 | L13: =J13-K13 -> 7604.0784
A14: 8 | B14: OU RITHTY | C14: M | D14: FOUNDER | E14: 45606 | G14: 3662.7785 | H14: 30 | I14: =G14*0.83% -> 30.401061 | J14: =G14+H14+I14 -> 3723.1795 | L14: =J14-K14 -> 3723.1795
A15: 9 | B15: Lim Solinn | C15: M | D15: FOUNDER | E15: 45414 | G15: 3632.7785 | H15: 10 | I15: =G15*0.83% -> 30.152061 | J15: =G15+H15+I15 -> 3672.9305 | L15: =J15-K15 -> 3672.9305
A16: 9 | B16: SENG RITHY | C16: M | D16: MEMBER | E16: 45418 | F16: NOP VY | G16: 145.28921 | H16: 10 | I16: =G16*0.83% -> 1.2059005 | J16: =G16+H16+I16 -> 156.49511 | L16: =J16-K16 -> 156.49511
A17: 10 | B17: OU TEP PHALLIN | C17: F | D17: MEMBER | E17: 45600 | F17: OU RITHY | G17: 348.78313 | H17: 20 | I17: =G17*0.83% -> 2.8949 | J17: =G17+H17+I17 -> 371.67803 | L17: =J17-K17 -> 371.67803
A18: 11 | B18: YIM BUNTHENG | C18: M | D18: MEMBER | E18: 45294 | F18: HONG REAKSMEY | G18: 111.17054 | I18: =G18*0.83% -> 0.92271546 | J18: =G18+H18+I18 -> 112.09325 | L18: =J18-K18 -> 112.09325
A19: 12 | B19: THENG SAVOEUN | C19: M | D19: MEMBER | E19: 45029 | F19: NOP VY | G19: 87.998768 | I19: =G19*0.83% -> 0.73038978 | J19: =G19+H19+I19 -> 88.729158 | L19: =J19-K19 -> 88.729158
A20: 13 | B20: UL VANN | C20: M | D20: MEMBER | E20: 45387 | F20: NOP VY | G20: 241.15755 | I20: =G20*0.83% -> 2.0016076 | J20: =G20+H20+I20 -> 243.15915 | L20: =J20-K20 -> 243.15915
A21: 14 | B21: SIYONN SOTHEARITH | C21: M | D21: MEMBER | E21: 45414 | F21: HONG REAKSMEY | G21: 1736.5747 | I21: =G21*0.83% -> 14.41357 | J21: =G21+H21+I21 -> 1750.9883 | L21: =J21-K21 -> 1750.9883
A22: 15 | B22: YEAN REAKSMEY | C22: M | D22: MEMBER | E22: 45386 | F22: PECH PISEY | G22: 226.24845 | H22: 25 | I22: =G22*0.83% -> 1.8778622 | J22: =G22+H22+I22 -> 253.12631 | L22: =J22-K22 -> 253.12631
A23: 16 | B23: SAM SOMONY | C23: M | D23: MEMBER | E23: 45415 | F23: NOP VY | G23: 1928.0157 | H23: 50 | I23: =G23*0.83% -> 16.00253 | J23: =G23+H23+I23 -> 1994.0182 | L23: =J23-K23 -> 1994.0182
A24: 17 | B24: KOY MAQUIS | C24: M | D24: MEMBER | E24: 45414 | F24: HONG REAKSMEY | G24: 298.54105 | H24: 20 | I24: =G24*0.83% -> 2.4778907 | J24: =G24+H24+I24 -> 321.01894 | L24: =J24-K24 -> 321.01894
A25: 18 | B25: LY MALIN | C25: F | D25: MEMBER | E25: 45427 | F25: OU RITHY | G25: 653.59347 | H25: 5 | I25: =G25*0.83% -> 5.4248258 | J25: =G25+H25+I25 -> 664.01829 | L25: =J25-K25 -> 664.01829
A26: 19 | B26: VAN BUNNA | C26: M | D26: MEMBER | E26: 45388 | F26: PECH PISEY | G26: 253.79082 | I26: =G26*0.83% -> 2.1064638 | J26: =G26+H26+I26 -> 255.89729 | L26: =J26-K26 -> 255.89729
A27: 20 | B27: CHAN THEARA | C27: F | D27: MEMBER | E27: 45386 | F27: HONG REAKSMEY | G27: 82.437558 | I27: =G27*0.83% -> 0.68423173 | J27: =G27+H27+I27 -> 83.121789 | L27: =J27-K27 -> 83.121789
A28: 21 | B28: LONG BORIN | C28: F | D28: MEMBER | E28: 45140 | F28: NOP VY | G28: 121.00689 | I28: =G28*0.83% -> 1.0043572 | J28: =G28+H28+I28 -> 122.01125 | L28: =J28-K28 -> 122.01125
A29: 22 | B29: SOEUNG SAROEUN | C29: M | D29: MEMBER | E29: 45235 | F29: NOP VY | G29: 142.46484 | I29: =G29*0.83% -> 1.1824581 | J29: =G29+H29+I29 -> 143.64729 | L29: =J29-K29 -> 143.64729
A30: 23 | B30: TUY SYTHIENG | C30: M | D30: MEMBER | E30: 45422 | F30: OU RITHY | G30: 1027.0303 | I30: =G30*0.83% -> 8.5243514 | J30: =G30+H30+I30 -> 1035.5546 | L30: =J30-K30 -> 1035.5546
A31: 24 | B31: CHHEOUNG VEASNA | C31: M | D31: MEMBER | E31: 45420 | F31: SAM SOMONY | G31: 671.6486 | I31: =G31*0.83% -> 5.5746834 | J31: =G31+H31+I31 -> 677.22328 | L31: =J31-K31 -> 677.22328
A32: 25 | B32: OM MANITH | C32: M | D32: MEMBER | E32: 45383 | F32: OU RITHY | G32: 44.121505 | I32: =G32*0.83% -> 0.36620849 | J32: =G32+H32+I32 -> 44.487714 | L32: =J32-K32 -> 44.487714
A33: 26 | B33: IM SOTHY | C33: M | D33: MEMBER | E33: 45209 | F33: PECH PISEY | G33: 67.654329 | I33: =G33*0.83% -> 0.56153093 | J33: =G33+H33+I33 -> 68.21586 | L33: =J33-K33 -> 68.21586
A34: 27 | B34: PA CHANROEUN | C34: M | D34: MEMBER | E34: 45085 | F34: NOP VY | G34: 228.27553 | I34: =G34*0.83% -> 1.8946869 | J34: =G34+H34+I34 -> 230.17022 | L34: =J34-K34 -> 230.17022
A35: 28 | B35: HENG SOCHEA | C35: F | D35: MEMBER | E35: 45427 | F35: OU RITHY | G35: 69.511252 | I35: =G35*0.83% -> 0.57694339 | J35: =G35+H35+I35 -> 70.088195 | L35: =J35-K35 -> 70.088195
A36: 29 | B36: TUM SOKRAKSA | C36: F | D36: MEMBER | E36: 45235 | G36: 1096.5522 | I36: =G36*0.83% -> 9.1013829 | J36: =G36+H36+I36 -> 1105.6535 | L36: =J36-K36 -> 1105.6535
A37: 30 | B37: SDEUNG PHEARONG | D37: MEMBER | E37: 45235 | G37: 16.473975 | I37: =G37*0.83% -> 0.13673399 | J37: =G37+H37+I37 -> 16.610709 | L37: =J37-K37 -> 16.610709
A38: 31 | B38: TY SAMPHORS VICHEKA | D38: MEMBER | E38: 45416 | G38: 173.61503 | H38: 15 | I38: =G38*0.83% -> 1.4410047 | J38: =G38+H38+I38 -> 190.05603 | L38: =J38-K38 -> 190.05603
A39: 32 | B39: CHUM CHANDARIN | D39: MEMBER | E39: 45420 | G39: 254.63912 | I39: =G39*0.83% -> 2.1135047 | J39: =G39+H39+I39 -> 256.75263 | L39: =J39-K39 -> 256.75263
A40: 33 | B40: PEANH KOEUN | D40: MEMBER | E40: 45414 | G40: 131.46456 | H40: 10 | I40: =G40*0.83% -> 1.0911558 | J40: =G40+H40+I40 -> 142.55571 | L40: =J40-K40 -> 142.55571
A41: 34 | B41: YANG SOPHORN | D41: MEMBER | E41: 45414 | G41: 213.71246 | I41: =G41*0.83% -> 1.7738134 | J41: =G41+H41+I41 -> 215.48628 | L41: =J41-K41 -> 215.48628
A42: 35 | B42: RO VANNAK | D42: MEMBER | E42: 45330 | G42: 59.480272 | I42: =G42*0.83% -> 0.49368626 | J42: =G42+H42+I42 -> 59.973959 | L42: =J42-K42 -> 59.973959
A43: 36 | B43: SENG VANLY | D43: MEMBER | E43: 45333 | G43: 182.29954 | I43: =G43*0.83% -> 1.5130862 | J43: =G43+H43+I43 -> 183.81263 | L43: =J43-K43 -> 183.81263
A44: 37 | B44: YORNG SOKHAI | D44: MEMBER | E44: 45418 | G44: 173.41906 | I44: =G44*0.83% -> 1.4393782 | J44: =G44+H44+I44 -> 174.85844 | L44: =J44-K44 -> 174.85844
A45: 38 | B45: MENGHAK VICHHAY | D45: MEMBER | E45: 45333 | G45: 54.864332 | I45: =G45*0.83% -> 0.45537395 | J45: =G45+H45+I45 -> 55.319706 | L45: =J45-K45 -> 55.319706
A46: 39 | B46: SIM SUNNARY | D46: MEMBER | E46: 45245 | G46: 21.994598 | I46: =G46*0.83% -> 0.18255516 | J46: =G46+H46+I46 -> 22.177153 | L46: =J46-K46 -> 22.177153
A47: 40 | B47: AN NITH | D47: MEMBER | E47: 45293 | G47: 10.772287 | I47: =G47*0.83% -> 0.08940998 | J47: =G47+H47+I47 -> 10.861697 | L47: =J47-K47 -> 10.861697
A48: 41 | B48: SRENG SAREN | D48: MEMBER | E48: 45414 | G48: 417.42404 | I48: =G48*0.83% -> 3.4646195 | J48: =G48+H48+I48 -> 420.88866 | L48: =J48-K48 -> 420.88866
A49: 42 | B49: LAUT PHEAKDEY | D49: MEMBER | E49: 45303 | G49: 21.544573 | I49: =G49*0.83% -> 0.17881996 | J49: =G49+H49+I49 -> 21.723393 | L49: =J49-K49 -> 21.723393
A50: 43 | B50: KRUY BOPHA | D50: MEMBER | E50: 45419 | G50: 93.046594 | H50: 10 | I50: =G50*0.83% -> 0.77228673 | J50: =G50+H50+I50 -> 103.81888 | L50: =J50-K50 -> 103.81888
A51: 44 | B51: HORN RITHY | D51: MEMBER | E51: 45324 | G51: 10.683613 | I51: =G51*0.83% -> 0.088673986 | J51: =G51+H51+I51 -> 10.772287 | L51: =J51-K51 -> 10.772287
A52: 45 | B52: SAY SAMPOLIDA | D52: MEMBER | E52: 45332 | G52: 51.184374 | H52: 10 | I52: =G52*0.83% -> 0.4248303 | J52: =G52+H52+I52 -> 61.609204 | L52: =J52-K52 -> 61.609204
A53: 46 | B53: CHHEAV NAK | D53: MEMBER | E53: 45423 | G53: 104.7392 | I53: =G53*0.83% -> 0.86933532 | J53: =G53+H53+I53 -> 105.60853 | L53: =J53-K53 -> 105.60853
A54: 47 | B54: CHUN SOKTHOUTHEAREACH | D54: MEMBER | E54: 45420 | G54: 262.09794 | I54: =G54*0.83% -> 2.1754129 | J54: =G54+H54+I54 -> 264.27335 | L54: =J54-K54 -> 264.27335
A55: 48 | B55: MENG SOTHY VATNAK | D55: MEMBER | E55: 45420 | G55: 42.03523 | I55: =G55*0.83% -> 0.34889241 | J55: =G55+H55+I55 -> 42.384123 | L55: =J55-K55 -> 42.384123
A56: 49 | B56: HUN SOT | D56: MEMBER | E56: 45414 | G56: 82.362981 | H56: 10 | I56: =G56*0.83% -> 0.68361275 | J56: =G56+H56+I56 -> 93.046594 | L56: =J56-K56 -> 93.046594
A57: 50 | B57: KET SOKSEILA | D57: MEMBER | E57: 45423 | F57: TUM SOKRAKSA | G57: 1080.7309 | H57: 5 | I57: =G57*0.83% -> 8.9700663 | J57: =G57+H57+I57 -> 1094.7009 | L57: =J57-K57 -> 1094.7009
A58: 50 | B58: UM SAROM | D58: MEMBER | E58: 45420 | G58: 15.676171 | I58: =G58*0.83% -> 0.13011222 | J58: =G58+H58+I58 -> 15.806283 | L58: =J58-K58 -> 15.806283
A59: 51 | B59: PHAL CHANTHA | D59: MEMBER | E59: 45606 | G59: 194.6268 | H59: 70 | I59: =G59*0.83% -> 1.6154024 | J59: =G59+H59+I59 -> 266.2422 | L59: =J59-K59 -> 266.2422
A60: 52 | B60: VA SARA | D60: MEMBER | E60: 45390 | F60: ATH THORN | G60: 20.930395 | I60: =G60*0.83% -> 0.17372228 | J60: =G60+H60+I60 -> 21.104117 | L60: =J60-K60 -> 21.104117
A61: 53 | B61: KET LENG | D61: MEMBER | E61: 45390 | F61: ATH THORN | G61: 101.93192 | H61: 20 | I61: =G61*0.83% -> 0.84603492 | J61: =G61+H61+I61 -> 122.77795 | L61: =J61-K61 -> 122.77795
A62: 54 | B62: EAN OUN | D62: MEMBER | E62: 45390 | F62: ATH THORN | G62: 20.930395 | I62: =G62*0.83% -> 0.17372228 | J62: =G62+H62+I62 -> 21.104117 | L62: =J62-K62 -> 21.104117
A63: 55 | B63: IEN SOPHOEURN | D63: MEMBER | E63: 45420 | G63: 10.421946 | I63: =G63*0.83% -> 0.086502155 | J63: =G63+H63+I63 -> 10.508449 | L63: =J63-K63 -> 10.508449
A64: 56 | B64: Chea Sopheap | D64: MEMBER | G64: 25.166344 | I64: =G64*0.83% -> 0.20888066 | J64: =G64+H64+I64 -> 25.375225 | L64: =J64-K64 -> 25.375225
G69: =SUM(G7:G59) -> 52087.105 | H69: =SUM(H7:H68) -> 480.48 | I69: =SUM(I7:I57) -> 430.57746 | J69: =SUM(J7:J59) -> 52979.908 | K69: =SUM(K7:K55) -> 0 | L69: =SUM(L7:L59) -> 52979.908

Sheet Dec-24
A1: SANSAM SAVING GROUP
A2: SAVING FROM 5USD PER MONTH BY GETTING INTEREST 10% PER YEAR
A3: SAVING DEPOSIT FROM 1ST - 10TH EVERY MONTH
A4: ACCESSIBLE LOAN ON 15TH EACH MONTH
A5: SAVING IN DEC 2024
A6: NO | B6: NAME | C6: SEX | D6: ROLE | E6: SAVING DATE | F6: TEAM LEADER | G6: CAPITAL | H6: SAVING | I6: INTEREST | J6: BALANCE | K6: WITHDRAWAL | L6: TOTAL
A7: 1 | B7: ATH THORN | C7: M | D7: FOUNDER | E7: 45422 | G7: 4706.9552 | I7: =G7*0.83% -> 39.067728 | J7: =G7+H7+I7 -> 4746.0229 | L7: =J7-K7 -> 4746.0229
A8: 2 | B8: PECH PISEY | C8: M | D8: FOUNDER | E8: 45636 | G8: 7887.3811 | H8: 30 | I8: =G8*0.83% -> 65.465263 | J8: =G8+H8+I8 -> 7982.8464 | L8: =J8-K8 -> 7982.8464
A9: 3 | B9: HONG REAKSMEY | C9: M | D9: FOUNDER | E9: 45636 | G9: 7765.2372 | H9: 50 | I9: =G9*0.83% -> 64.451469 | J9: =G9+H9+I9 -> 7879.6887 | L9: =J9-K9 -> 7879.6887
A10: 4 | B10: SIN PUTHEARY | C10: F | D10: FOUNDER | E10: 45171 | G10: 3153.868 | I10: =G10*0.83% -> 26.177105 | J10: =G10+H10+I10 -> 3180.0451 | L10: =J10-K10 -> 3180.0451 | M10: ស្នើដកលុយសន្សំ​ $3000
A11: 5 | B11: PAO VORN | C11: M | D11: FOUNDER | E11: 45631 | G11: 525.75625 | H11: 20 | I11: =G11*0.83% -> 4.3637769 | J11: =G11+H11+I11 -> 550.12003 | L11: =J11-K11 -> 550.12003
A12: 6 | B12: SOR MORA | C12: M | D12: FOUNDER | E12: 45383 | G12: 319.78638 | I12: =G12*0.83% -> 2.654227 | J12: =G12+H12+I12 -> 322.44061 | L12: =J12-K12 -> 322.44061
A13: 7 | B13: NOP VY | C13: M | D13: FOUNDER | E13: 45636 | G13: 7604.0784 | H13: 83.8 | I13: =G13*0.83% -> 63.11385 | J13: =G13+H13+I13 -> 7750.9922 | L13: =J13-K13 -> 7750.9922
A14: 8 | B14: OU RITHTY | C14: M | D14: FOUNDER | E14: 45631 | G14: 3723.1795 | H14: 50 | I14: =G14*0.83% -> 30.90239 | J14: =G14+H14+I14 -> 3804.0819 | L14: =J14-K14 -> 3804.0819 | M14: ស្នើដកលុយសន្សំ​ $2000
A15: 9 | B15: Lim Solinn | C15: M | D15: MEMBER | E15: 45630 | G15: 3672.9305 | H15: 20 | I15: =G15*0.83% -> 30.485323 | J15: =G15+H15+I15 -> 3723.4159 | L15: =J15-K15 -> 3723.4159
A16: 9 | B16: SENG RITHY | C16: M | D16: MEMBER | E16: 45629 | F16: NOP VY | G16: 156.49511 | H16: 10 | I16: =G16*0.83% -> 1.2989094 | J16: =G16+H16+I16 -> 167.79402 | L16: =J16-K16 -> 167.79402
A17: 10 | B17: OU TEP PHALLIN | C17: F | D17: MEMBER | E17: 45383 | F17: OU RITHY | G17: 371.67803 | I17: =G17*0.83% -> 3.0849276 | J17: =G17+H17+I17 -> 374.76296 | L17: =J17-K17 -> 374.76296
A18: 11 | B18: YIM BUNTHENG | C18: M | D18: MEMBER | E18: 45294 | F18: HONG REAKSMEY | G18: 112.09325 | I18: =G18*0.83% -> 0.930374 | J18: =G18+H18+I18 -> 113.02363 | L18: =J18-K18 -> 113.02363
A19: 12 | B19: THENG SAVOEUN | C19: M | D19: MEMBER | E19: 45029 | F19: NOP VY | G19: 88.729158 | I19: =G19*0.83% -> 0.73645201 | J19: =G19+H19+I19 -> 89.46561 | L19: =J19-K19 -> 89.46561
A20: 13 | B20: UL VANN | C20: M | D20: MEMBER | E20: 45387 | F20: NOP VY | G20: 243.15915 | I20: =G20*0.83% -> 2.018221 | J20: =G20+H20+I20 -> 245.17738 | L20: =J20-K20 -> 245.17738
A21: 14 | B21: SIYONN SOTHEARITH | C21: M | D21: MEMBER | E21: 45630 | F21: HONG REAKSMEY | G21: 1750.9883 | H21: 100 | I21: =G21*0.83% -> 14.533203 | J21: =G21+H21+I21 -> 1865.5215 | L21: =J21-K21 -> 1865.5215
A22: 15 | B22: YEAN REAKSMEY | C22: M | D22: MEMBER | E22: 45636 | F22: PECH PISEY | G22: 253.12631 | H22: 25 | I22: =G22*0.83% -> 2.1009484 | J22: =G22+H22+I22 -> 280.22726 | L22: =J22-K22 -> 280.22726
A23: 16 | B23: SAM SOMONY | C23: M | D23: MEMBER | E23: 45633 | F23: NOP VY | G23: 1994.0182 | H23: 50 | I23: =G23*0.83% -> 16.550351 | J23: =G23+H23+I23 -> 2060.5686 | L23: =J23-K23 -> 2060.5686
A24: 17 | B24: KOY MAQUIS | C24: M | D24: MEMBER | E24: 45631 | F24: HONG REAKSMEY | G24: 321.01894 | H24: 20 | I24: =G24*0.83% -> 2.6644572 | J24: =G24+H24+I24 -> 343.6834 | L24: =J24-K24 -> 343.6834
A25: 18 | B25: LY MALIN | C25: F | D25: MEMBER | E25: 45631 | F25: OU RITHY | G25: 664.01829 | H25: 10 | I25: =G25*0.83% -> 5.5113518 | J25: =G25+H25+I25 -> 679.52964 | L25: =J25-K25 -> 679.52964
A26: 19 | B26: VAN BUNNA | C26: M | D26: MEMBER | E26: 45388 | F26: PECH PISEY | G26: 255.89729 | I26: =G26*0.83% -> 2.1239475 | J26: =G26+H26+I26 -> 258.02124 | K26: 258.02 | L26: =J26-K26 -> 0.0012354232 | M26: ស្នើដកលុយសន្សំ
A27: 20 | B27: CHAN THEARA | C27: F | D27: MEMBER | E27: 45386 | F27: HONG REAKSMEY | G27: 83.121789 | I27: =G27*0.83% -> 0.68991085 | J27: =G27+H27+I27 -> 83.8117 | L27: =J27-K27 -> 83.8117
A28: 21 | B28: LONG BORIN | C28: F | D28: MEMBER | E28: 45140 | F28: NOP VY | G28: 122.01125 | I28: =G28*0.83% -> 1.0126933 | J28: =G28+H28+I28 -> 123.02394 | L28: =J28-K28 -> 123.02394
A29: 22 | B29: SOEUNG SAROEUN | C29: M | D29: MEMBER | E29: 45235 | F29: NOP VY | G29: 143.64729 | I29: =G29*0.83% -> 1.1922725 | J29: =G29+H29+I29 -> 144.83957 | L29: =J29-K29 -> 144.83957
A30: 23 | B30: TUY SYTHIENG | C30: M | D30: MEMBER | E30: 45422 | F30: OU RITHY | G30: 1035.5546 | I30: =G30*0.83% -> 8.5951035 | J30: =G30+H30+I30 -> 1044.1497 | L30: =J30-K30 -> 1044.1497
A31: 24 | B31: CHHEOUNG VEASNA | C31: M | D31: MEMBER | E31: 45420 | F31: SAM SOMONY | G31: 677.22328 | I31: =G31*0.83% -> 5.6209533 | J31: =G31+H31+I31 -> 682.84424 | L31: =J31-K31 -> 682.84424 | M31: 176.31
A32: 25 | B32: OM MANITH | C32: M | D32: MEMBER | E32: 45383 | F32: OU RITHY | G32: 44.487714 | I32: =G32*0.83% -> 0.36924802 | J32: =G32+H32+I32 -> 44.856962 | L32: =J32-K32 -> 44.856962 | M32: 258.02
A33: 26 | B33: IM SOTHY | C33: M | D33: MEMBER | E33: 45209 | F33: PECH PISEY | G33: 68.21586 | I33: =G33*0.83% -> 0.56619164 | J33: =G33+H33+I33 -> 68.782052 | L33: =J33-K33 -> 68.782052 | M33: 3000
A34: 27 | B34: PA CHANROEUN | C34: M | D34: MEMBER | E34: 45085 | F34: NOP VY | G34: 230.17021 | I34: =G34*0.83% -> 1.9104128 | J34: =G34+H34+I34 -> 232.08063 | L34: =J34-K34 -> 232.08063 | M34: 2000
A35: 28 | B35: HENG SOCHEA | C35: F | D35: MEMBER | E35: 45427 | F35: OU RITHY | G35: 70.088195 | I35: =G35*0.83% -> 0.58173202 | J35: =G35+H35+I35 -> 70.669927 | L35: =J35-K35 -> 70.669927
A36: 29 | B36: TUM SOKRAKSA | C36: F | D36: MEMBER | E36: 45235 | G36: 1105.6535 | I36: =G36*0.83% -> 9.1769244 | J36: =G36+H36+I36 -> 1114.8305 | L36: =J36-K36 -> 1114.8305
A37: 30 | B37: SDEUNG PHEARONG | D37: MEMBER | E37: 45235 | G37: 16.610709 | I37: =G37*0.83% -> 0.13786888 | J37: =G37+H37+I37 -> 16.748578 | L37: =J37-K37 -> 16.748578
A38: 31 | B38: TY SAMPHORS VICHEKA | D38: MEMBER | E38: 45633 | G38: 190.05603 | H38: 15 | I38: =G38*0.83% -> 1.5774651 | J38: =G38+H38+I38 -> 206.6335 | L38: =J38-K38 -> 206.6335
A39: 32 | B39: CHUM CHANDARIN | D39: MEMBER | E39: 45420 | G39: 256.75263 | I39: =G39*0.83% -> 2.1310468 | J39: =G39+H39+I39 -> 258.88368 | L39: =J39-K39 -> 258.88368 | M39: ស្នើដកលុយសន្សំ
A40: 33 | B40: PEANH KOEUN | D40: MEMBER | E40: 45628 | G40: 142.55571 | H40: 10 | I40: =G40*0.83% -> 1.1832124 | J40: =G40+H40+I40 -> 153.73892 | L40: =J40-K40 -> 153.73892
A41: 34 | B41: YANG SOPHORN | D41: MEMBER | E41: 45414 | G41: 215.48628 | I41: =G41*0.83% -> 1.7885361 | J41: =G41+H41+I41 -> 217.27481 | L41: =J41-K41 -> 217.27481
A42: 35 | B42: RO VANNAK | D42: MEMBER | E42: 45330 | G42: 59.973959 | I42: =G42*0.83% -> 0.49778386 | J42: =G42+H42+I42 -> 60.471742 | L42: =J42-K42 -> 60.471742
A43: 36 | B43: SENG VANLY | D43: MEMBER | E43: 45333 | G43: 183.81263 | I43: =G43*0.83% -> 1.5256448 | J43: =G43+H43+I43 -> 185.33828 | L43: =J43-K43 -> 185.33828
A44: 37 | B44: YORNG SOKHAI | D44: MEMBER | E44: 45418 | G44: 174.85844 | I44: =G44*0.83% -> 1.451325 | J44: =G44+H44+I44 -> 176.30976 | K44: 176.31 | L44: =J44-K44 -> -0.00023838014 | M44: ស្នើដកលុយសន្សំ
A45: 38 | B45: MENGHAK VICHHAY | D45: MEMBER | E45: 45333 | G45: 55.319706 | I45: =G45*0.83% -> 0.45915356 | J45: =G45+H45+I45 -> 55.778859 | L45: =J45-K45 -> 55.778859
A46: 39 | B46: SIM SUNNARY | D46: MEMBER | E46: 45245 | G46: 22.177153 | I46: =G46*0.83% -> 0.18407037 | J46: =G46+H46+I46 -> 22.361223 | L46: =J46-K46 -> 22.361223
A47: 40 | B47: AN NITH | D47: MEMBER | E47: 45293 | G47: 10.861697 | I47: =G47*0.83% -> 0.090152083 | J47: =G47+H47+I47 -> 10.951849 | L47: =J47-K47 -> 10.951849
A48: 41 | B48: SRENG SAREN | D48: MEMBER | E48: 45414 | G48: 420.88866 | I48: =G48*0.83% -> 3.4933759 | J48: =G48+H48+I48 -> 424.38204 | L48: =J48-K48 -> 424.38204
A49: 42 | B49: LAUT PHEAKDEY | D49: MEMBER | E49: 45303 | G49: 21.723393 | I49: =G49*0.83% -> 0.18030417 | J49: =G49+H49+I49 -> 21.903698 | L49: =J49-K49 -> 21.903698
A50: 43 | B50: KRUY BOPHA | D50: MEMBER | E50: 45632 | G50: 103.81888 | H50: 10 | I50: =G50*0.83% -> 0.86169671 | J50: =G50+H50+I50 -> 114.68058 | L50: =J50-K50 -> 114.68058
A51: 44 | B51: HORN RITHY | D51: MEMBER | E51: 45324 | G51: 10.772287 | I51: =G51*0.83% -> 0.08940998 | J51: =G51+H51+I51 -> 10.861697 | L51: =J51-K51 -> 10.861697
A52: 45 | B52: SAY SAMPOLIDA | D52: MEMBER | E52: 45332 | G52: 61.609204 | H52: 10 | I52: =G52*0.83% -> 0.5113564 | J52: =G52+H52+I52 -> 72.120561 | L52: =J52-K52 -> 72.120561
A53: 46 | B53: CHHEAV NAK | D53: MEMBER | E53: 45423 | G53: 105.60853 | I53: =G53*0.83% -> 0.8765508 | J53: =G53+H53+I53 -> 106.48508 | L53: =J53-K53 -> 106.48508
A54: 47 | B54: CHUN SOKTHOUTHEAREACH | D54: MEMBER | E54: 45631 | G54: 264.27335 | H54: 5 | I54: =G54*0.83% -> 2.1934688 | J54: =G54+H54+I54 -> 271.46682 | L54: =J54-K54 -> 271.46682
A55: 48 | B55: MENG SOTHY VATNAK | D55: MEMBER | E55: 45420 | G55: 42.384123 | I55: =G55*0.83% -> 0.35178822 | J55: =G55+H55+I55 -> 42.735911 | L55: =J55-K55 -> 42.735911
A56: 49 | B56: HUN SOT | D56: MEMBER | E56: 45631 | G56: 93.046594 | H56: 10 | I56: =G56*0.83% -> 0.77228673 | J56: =G56+H56+I56 -> 103.81888 | L56: =J56-K56 -> 103.81888
A57: 50 | B57: KET SOKSEILA | D57: MEMBER | E57: 45637 | F57: TUM SOKRAKSA | G57: 1094.7009 | H57: 10 | I57: =G57*0.83% -> 9.0860178 | J57: =G57+H57+I57 -> 1113.787 | L57: =J57-K57 -> 1113.787
A58: 50 | B58: UM SAROM | D58: MEMBER | E58: 45420 | G58: 15.806283 | I58: =G58*0.83% -> 0.13119215 | J58: =G58+H58+I58 -> 15.937475 | L58: =J58-K58 -> 15.937475
A59: 51 | B59: PHAL CHANTHA | D59: MEMBER | E59: 45636 | G59: 266.2422 | H59: 140 | I59: =G59*0.83% -> 2.2098103 | J59: =G59+H59+I59 -> 408.45201 | L59: =J59-K59 -> 408.45201
A60: 52 | B60: VA SARA | D60: MEMBER | E60: 45390 | F60: ATH THORN | G60: 21.104117 | I60: =G60*0.83% -> 0.17516417 | J60: =G60+H60+I60 -> 21.279281 | L60: =J60-K60 -> 21.279281
A61: 53 | B61: KET LENG | D61: MEMBER | E61: 45636 | F61: ATH THORN | G61: 122.77795 | H61: 20 | I61: =G61*0.83% -> 1.019057 | J61: =G61+H61+I61 -> 143.79701 | L61: =J61-K61 -> 143.79701
A62: 54 | B62: EAN OUN | D62: MEMBER | E62: 45390 | F62: ATH THORN | G62: 21.104117 | I62: =G62*0.83% -> 0.17516417 | J62: =G62+H62+I62 -> 21.279281 | L62: =J62-K62 -> 21.279281
A63: 55 | B63: IEN SOPHOEURN | D63: MEMBER | E63: 45420 | G63: 10.508449 | I63: =G63*0.83% -> 0.087220123 | J63: =G63+H63+I63 -> 10.595669 | L63: =J63-K63 -> 10.595669
A64: 56 | B64: Chea Sopheap | D64: MEMBER | E64: 45640 | G64: 25.375225 | I64: =G64*0.83% -> 0.21061437 | J64: =G64+H64+I64 -> 25.585839 | L64: =J64-K64 -> 25.585839
G66: =SUM(G7:G59) -> 52979.908 | H66: =SUM(H7:H65) -> 698.8 | I66: =SUM(I7:I57) -> 437.39223 | J66: =SUM(J7:J59) -> 54098.441 | K66: =SUM(K7:K55) -> 434.33 | L66: =SUM(L7:L59) -> 53664.111

Sheet Jan-2025
A1: SANSAM SAVING GROUP
A2: SAVING FROM 5USD PER MONTH BY GETTING INTEREST 10% PER YEAR
A3: SAVING DEPOSIT FROM 1ST - 10TH EVERY MONTH
A4: ACCESSIBLE LOAN ON 15TH EACH MONTH
A5: SAVING IN Jan 2025
A6: NO | B6: NAME | C6: SEX | D6: ROLE | E6: SAVING DATE | F6: TEAM LEADER | G6: CAPITAL | H6: SAVING | I6: INTEREST | J6: BALANCE | K6: WITHDRAWAL | L6: TOTAL
A7: 1 | B7: ATH THORN | C7: M | D7: FOUNDER | E7: 45422 | G7: 4746.0229 | I7: =G7*0.83% -> 39.39199 | J7: =G7+H7+I7 -> 4785.4149 | L7: =J7-K7 -> 4785.4149
A8: 2 | B8: PECH PISEY | C8: M | D8: FOUNDER | E8: 45668 | G8: 7982.8464 | H8: 30 | I8: =G8*0.83% -> 66.257625 | J8: =G8+H8+I8 -> 8079.104 | L8: =J8-K8 -> 8079.104
A9: 3 | B9: HONG REAKSMEY | C9: M | D9: FOUNDER | E9: 45666 | G9: 7879.6887 | H9: 100 | I9: =G9*0.83% -> 65.401416 | J9: =G9+H9+I9 -> 8045.0901 | L9: =J9-K9 -> 8045.0901
A10: 4 | B10: SIN PUTHEARY | C10: F | D10: FOUNDER | E10: 45171 | G10: 3180.05 | I10: =G10*0.83% -> 26.394415 | J10: =G10+H10+I10 -> 3206.4444 | K10: 3000 | L10: =J10-K10 -> 206.44441
